Workbook

Sheet (SFD 4-5 Bed) Break Even
A1: 2023 Municipal and School Fiscal Impact Break Even Analysis for Single Family Detached (4-5 Bedroom) in Selected NJ Communities
A3: Single Family Detached (4-5 Bedroom) with Revised Updated 2021 Multipliers
A4: Category | B4: Multiplier
A5: Household Size | B5: 3.369
A6: School Age Children | B6: 0.683
A8: Location | C8: 4-5 Bedroom Single Family Detached "Break Even Analysis" | G8: Fiscal Analysis | K8: Municipal and School Public Finanace Data
A9: County | B9: Municipality | C9: Municipal Tax Supported Cost | D9: School Tax Supported Cost | E9: Total Tax Supported Cost | F9: Market Value "Break Even" | G9: Imputed Average (2023) Market Value of Potential Buyout Properties | H9: Fiscal Surplus or Deficit (Based on Average Buyout Market Value) | I9: Average 2023 Residential Value in Buyout Community | J9: Fiscal Surplus or Deficit (Based on Average Residential Value) | K9: Total Municipal + School Equalized Property Tax Rate | L9: Percent of Total Parcels that are Residential | M9: Percent of Total Assessed Value that is Residential | N9: Average of Residential Parcels % and Assessed Value % | O9: Total Municipal Property Tax Levy | P9: Estimated Residential Share of Total Municipal Property Tax Levy | Q9: 2020 Municipal Population | R9: 2020 Municipal Property Tax Supported Cost Per Person | S9: Total School Property Tax Levy | T9: 2020 Total School Enrollment | U9: 2020 School Property Tax Supported Cost Per Pupil
A10: Camden | B10: Bellmawr | C10: =$B$5*R10 -> 2442.4749 | D10: =U10*$B$6 -> 0 | E10: =C10+D10 -> 2442.4749 | F10: =E10/(K10/100) -> 103626.43 | G10: 129554 | H10: =G10-F10 -> 25927.572 | I10: 187760 | J10: =I10-F10 -> 84133.572 | K10: 2.357 | L10: 0.9525 | M10: 0.7751 | N10: =(L10+M10)/2 -> 0.8638 | O10: 9805512 | P10: =N10*O10 -> 8470001.3 | Q10: 11683 | R10: =P10/Q10 -> 724.98513
A11: Camden | B11: Brooklawn | C11: =$B$5*R11 -> 3357.7384 | D11: =U11*$B$6 -> 4036.53 | E11: =C11+D11 -> 7394.2684 | F11: =E11/(K11/100) -> 307966.2 | G11: 94881 | H11: =G11-F11 -> -213085.2 | I11: 137509 | J11: =I11-F11 -> -170457.2 | K11: 2.401 | L11: 0.9117 | M11: 0.6552 | N11: =(L11+M11)/2 -> 0.78345 | O11: 2297483 | P11: =N11*O11 -> 1799963.1 | Q11: 1806 | R11: =P11/Q11 -> 996.65728 | S11: 1554520 | T11: 263 | U11: 5910
A12: Camden | B12: Gloucester City | C12: =$B$5*R12 -> 3702.4248 | D12: =U12*$B$6 -> 1921.962 | E12: =C12+D12 -> 5624.3868 | F12: =E12/(K12/100) -> 190141.54 | G12: 94239 | H12: =G12-F12 -> -95902.541 | I12: 136578 | J12: =I12-F12 -> -53563.541 | K12: 2.958 | L12: 0.9331 | M12: 0.7821 | N12: =(L12+M12)/2 -> 0.8576 | O12: 14690502 | P12: =N12*O12 -> 12598575 | Q12: 11464 | R12: =P12/Q12 -> 1098.9685 | S12: 26724337 | T12: 2390 | U12: 2814
A13: Camden | B13: Mt Ephraim | C13: =$B$5*R13 -> 3062.6257 | D13: =U13*$B$6 -> 11261.987 | E13: =C13+D13 -> 14324.613 | F13: =E13/(K13/100) -> 498941.58 | G13: 133784 | H13: =G13-F13 -> -365157.58 | I13: 193890 | J13: =I13-F13 -> -305051.58 | K13: 2.871 | L13: 0.946 | M13: 0.8759 | N13: =(L13+M13)/2 -> 0.91095 | O13: 4629379 | P13: =N13*O13 -> 4217132.8 | Q13: 4639 | R13: =P13/Q13 -> 909.06075 | S13: 7090693 | T13: 430 | U13: 16489
A14: Gloucester | B14: Westville | C14: =$B$5*R14 -> 2181.3657 | D14: =U14*$B$6 -> 0 | E14: =C14+D14 -> 2181.3657 | F14: =E14/(K14/100) -> 76085.306 | G14: 113598 | H14: =G14-F14 -> 37512.694 | I14: 164635 | J14: =I14-F14 -> 88549.694 | K14: 2.867 | L14: 0.8626 | M14: 0.807 | N14: =(L14+M14)/2 -> 0.8348 | O14: 3338238 | P14: =N14*O14 -> 2786761.1 | Q14: 4304 | R14: =P14/Q14 -> 647.48166

Sheet (SFD 4-5 Bed) Muni Break Even
A1: 2023 Municipal Fiscal Impact Break Even Analysis for Single Family Detached (4-5 Bedroom) in Selected NJ Communities
A3: Single Family Detached (4-5 Bedroom) with Revised Updated 2021 Multipliers
A4: Category | B4: Multiplier
A5: Household Size | B5: 3.369
A6: School Age Children | B6: 0.683
A8: Location | C8: 4-5 Bedroom Single Family Detached Municipal"Break Even Analysis" | E8: Fiscal Analysis | I8: Municipal Public Finance Data
A9: County | B9: Municipality | C9: Municipal Tax Supported Cost | D9: Market Value "Break Even" | E9: Imputed Average (2023) Market Value of Potential Buyout Properties | F9: Fiscal Surplus or Deficit (Based on Average Buyout Market Value) | G9: Average 2023 Residential Value in Buyout Community | H9: Fiscal Surplus or Deficit (Based on Average Residential Value) | I9: Municipal Equalized Property Tax Rate | J9: Percent of Total Parcels that are Residential | K9: Percent of Total Assessed Value that is Residential | L9: Average of Residential Parcels % and Assessed Value % | M9: Total Municipal Property Tax Levy | N9: Estimated Residential Share of Total Municipal Property Tax Levy | O9: 2022 Municipal Population | P9: 2023 Municipal Property Tax Supported Cost Per Person
A10: Camden | B10: Bellmawr | C10: =$B$5*P10 -> 2442.4749 | D10: =C10/(I10/100) -> 253106.21 | E10: 129554 | F10: =E10-D10 -> -123552.21 | G10: 187760 | H10: =G10-D10 -> -65346.207 | I10: 0.965 | J10: 0.9525 | K10: 0.7751 | L10: =(J10+K10)/2 -> 0.8638 | M10: 9805512 | N10: =L10*M10 -> 8470001.3 | O10: 11683 | P10: =N10/O10 -> 724.98513
A11: Camden | B11: Brooklawn | C11: =$B$5*P11 -> 3357.7384 | D11: =C11/(I11/100) -> 234478.94 | E11: 94881 | F11: =E11-D11 -> -139597.94 | G11: 137509 | H11: =G11-D11 -> -96969.938 | I11: 1.432 | J11: 0.9117 | K11: 0.6552 | L11: =(J11+K11)/2 -> 0.78345 | M11: 2297483 | N11: =L11*M11 -> 1799963.1 | O11: 1806 | P11: =N11/O11 -> 996.65728
A12: Camden | B12: Gloucester City | C12: =$B$5*P12 -> 3702.4248 | D12: =C12/(I12/100) -> 179816.65 | E12: 94239 | F12: =E12-D12 -> -85577.647 | G12: 136578 | H12: =G12-D12 -> -43238.647 | I12: 2.059 | J12: 0.9331 | K12: 0.7821 | L12: =(J12+K12)/2 -> 0.8576 | M12: 14690502 | N12: =L12*M12 -> 12598575 | O12: 11464 | P12: =N12/O12 -> 1098.9685
A13: Camden | B13: Mt Ephraim | C13: =$B$5*P13 -> 3062.6257 | D13: =C13/(I13/100) -> 270072.81 | E13: 133784 | F13: =E13-D13 -> -136288.81 | G13: 193890 | H13: =G13-D13 -> -76182.809 | I13: 1.134 | J13: 0.946 | K13: 0.8759 | L13: =(J13+K13)/2 -> 0.91095 | M13: 4629379 | N13: =L13*M13 -> 4217132.8 | O13: 4639 | P13: =N13/O13 -> 909.06075
A14: Gloucester | B14: Westville | C14: =$B$5*P14 -> 2181.3657 | D14: =C14/(I14/100) -> 219895.74 | E14: 113598 | F14: =E14-D14 -> -106297.74 | G14: 164635 | H14: =G14-D14 -> -55260.739 | I14: 0.992 | J14: 0.8626 | K14: 0.807 | L14: =(J14+K14)/2 -> 0.8348 | M14: 3338238 | N14: =L14*M14 -> 2786761.1 | O14: 4304 | P14: =N14/O14 -> 647.48166

Sheet (SFD 3 Bed) Break Even
A1: 2020 Break Even Analysis for Single Family Detached (3 Bedroom) in Selected NJ Communities
A3: Single Family Detached (3 Bedroom) Multipliers
A4: Category | B4: Multiplier
A5: Household Size | B5: 2.757
A6: School Age Children | B6: 0.425
A8: Location | C8: 3 Bedroom Single Family Detached "Break Even Analysis" | G8: Fiscal Analysis | K8: School and Municipal Fiscal Impact Analysis
A9: County | B9: Municipality | C9: Municipal Tax Supported Cost | D9: School Tax Supported Cost | E9: Total Tax Supported Cost | F9: Market Value "Break Even" | G9: Average Real (2020) Market Value of Buyout Properties | H9: Fiscal Surplus or Deficit (Based on Average Buyout Market Value) | I9: Average 2020 Residential Value in Buyout Community | J9: Fiscal Surplus or Deficit (Based on Average Residential Value) | K9: Total Municipal + School Equalized Property Tax Rate | L9: Percent of Total Parcels that are Residential | M9: Percent of Total Assessed Value that is Residential | N9: Average of Residential Parcels % and Assessed Value % | O9: Total Municipal Property Tax Levy | P9: Estimated Residential Share of Total Municipal Property Tax Levy | Q9: 2020 Municipal Population | R9: 2020 Municipal Property Tax Supported Cost Per Person | S9: Total School Property Tax Levy | T9: 2020 Total School Enrollment | U9: 2020 School Property Tax Supported Cost Per Pupil
A10: Atlantic | B10: Pleasantville City | C10: =$B$5*R10 -> 2629.6625 | D10: =U10*$B$6 -> 988.24162 | E10: =C10+D10 -> 3617.9042 | F10: =E10/(K10/100) -> 82783.394 | G10: 60235 | H10: =G10-F10 -> -22548.394 | I10: 98362.768 | J10: =I10-F10 -> 15579.374 | K10: ='Tax Levies and EQ Tax Rates'!O5 -> 4.370326 | L10: ='# and Assessed Value of Parcels'!G5/'# and Assessed Value of Parcels'!O5 -> 0.92172813 | M10: ='# and Assessed Value of Parcels'!H5/'# and Assessed Value of Parcels'!P5 -> 0.73101366 | N10: =(L10+M10)/2 -> 0.8263709 | O10: ='Tax Levies and EQ Tax Rates'!I5 -> 23810385 | P10: =N10*O10 -> 19676209 | Q10: 20629 | R10: =P10/Q10 -> 953.81304 | S10: ='Tax Levies and EQ Tax Rates'!C5 -> 10152148 | T10: 4366 | U10: =S10/T10 -> 2325.2744
A11: Bergen | B11: New Milford Borough | C11: =$B$5*R11 -> 2706.2841 | D11: =U11*$B$6 -> 6563.9319 | E11: =C11+D11 -> 9270.216 | F11: =E11/(K11/100) -> 365033.9 | G11: 373724 | H11: =G11-F11 -> 8690.095 | I11: 426888.09 | J11: =I11-F11 -> 61854.185 | K11: ='Tax Levies and EQ Tax Rates'!O7 -> 2.5395493 | L11: ='# and Assessed Value of Parcels'!G7/'# and Assessed Value of Parcels'!O7 -> 0.98144233 | M11: ='# and Assessed Value of Parcels'!H7/'# and Assessed Value of Parcels'!P7 -> 0.94433259 | N11: =(L11+M11)/2 -> 0.96288746 | O11: ='Tax Levies and EQ Tax Rates'!I7 -> 17251960 | P11: =N11*O11 -> 16611696 | Q11: 16923 | R11: =P11/Q11 -> 981.6047 | S11: ='Tax Levies and EQ Tax Rates'!C7 -> 35244453 | T11: 2282 | U11: =S11/T11 -> 15444.546
A12: Essex | B12: Newark City | C12: =$B$5*R12 -> 1545.9463 | D12: =U12*$B$6 -> 959.89573 | E12: =C12+D12 -> 2505.842 | F12: =E12/(K12/100) -> 94709.031 | G12: 164529.67 | H12: =G12-F12 -> 69820.636 | I12: 206835.02 | J12: =I12-F12 -> 112125.99 | K12: ='Tax Levies and EQ Tax Rates'!O18 -> 2.6458321 | L12: ='# and Assessed Value of Parcels'!G18/'# and Assessed Value of Parcels'!O18 -> 0.84162884 | M12: ='# and Assessed Value of Parcels'!H18/'# and Assessed Value of Parcels'!P18 -> 0.54365223 | N12: =(L12+M12)/2 -> 0.69264054 | O12: ='Tax Levies and EQ Tax Rates'!I18 -> 252218004 | P12: =N12*O12 -> 1.7469641e+08 | Q12: 311549 | R12: =P12/Q12 -> 560.73495 | S12: ='Tax Levies and EQ Tax Rates'!C18 -> 135819599 | T12: 60135 | U12: =S12/T12 -> 2258.5782
A13: Middlesex | B13: East Brunswick Township | C13: =$B$5*R13 -> 2171.3074 | D13: =U13*$B$6 -> 6949.8966 | E13: =C13+D13 -> 9121.204 | F13: =E13/(K13/100) -> 383523.89 | G13: 228185.83 | H13: =G13-F13 -> -155338.06 | I13: 380312.49 | J13: =I13-F13 -> -3211.4023 | K13: ='Tax Levies and EQ Tax Rates'!O20 -> 2.3782623 | L13: ='# and Assessed Value of Parcels'!G20/'# and Assessed Value of Parcels'!O20 -> 0.95667524 | M13: ='# and Assessed Value of Parcels'!H20/'# and Assessed Value of Parcels'!P20 -> 0.81220548 | N13: =(L13+M13)/2 -> 0.88444036 | O13: ='Tax Levies and EQ Tax Rates'!I20 -> 44269380 | P13: =N13*O13 -> 39153626 | Q13: 49715 | R13: =P13/Q13 -> 787.56163 | S13: ='Tax Levies and EQ Tax Rates'!C20 -> 137771480 | T13: 8425 | U13: =S13/T13 -> 16352.698
A14: Middlesex | B14: Old Bridge Township | C14: =$B$5*R14 -> 1449.0294 | D14: =U14*$B$6 -> 5612.7613 | E14: =C14+D14 -> 7061.7907 | F14: =E14/(K14/100) -> 419009.73 | G14: 131130.71 | H14: =G14-F14 -> -287879.02 | I14: 375525.05 | J14: =I14-F14 -> -43484.678 | K14: ='Tax Levies and EQ Tax Rates'!O21 -> 1.6853524 | L14: ='# and Assessed Value of Parcels'!G21/'# and Assessed Value of Parcels'!O21 -> 0.97122792 | M14: ='# and Assessed Value of Parcels'!H21/'# and Assessed Value of Parcels'!P21 -> 0.88589383 | N14: =(L14+M14)/2 -> 0.92856088 | O14: ='Tax Levies and EQ Tax Rates'!I21 -> 37853002 | P14: =N14*O14 -> 35148817 | Q14: 66876 | R14: =P14/Q14 -> 525.58193 | S14: ='Tax Levies and EQ Tax Rates'!C21 -> 106576433 | T14: 8070 | U14: =S14/T14 -> 13206.497
A15: Middlesex | B15: Middlesex Borough | C15: =$B$5*R15 -> 2290.0211 | D15: =U15*$B$6 -> 5510.6844 | E15: =C15+D15 -> 7800.7056 | F15: =E15/(K15/100) -> 330909.58 | G15: 306079.81 | H15: =G15-F15 -> -24829.771 | I15: 324882.84 | J15: =I15-F15 -> -6026.7441 | K15: ='Tax Levies and EQ Tax Rates'!O22 -> 2.3573526 | L15: ='# and Assessed Value of Parcels'!G22/'# and Assessed Value of Parcels'!O22 -> 0.92460317 | M15: ='# and Assessed Value of Parcels'!H22/'# and Assessed Value of Parcels'!P22 -> 0.82398227 | N15: =(L15+M15)/2 -> 0.87429272 | O15: ='Tax Levies and EQ Tax Rates'!I22 -> 13904913 | P15: =N15*O15 -> 12156964 | Q15: 14636 | R15: =P15/Q15 -> 830.62065 | S15: ='Tax Levies and EQ Tax Rates'!C22 -> 26438319 | T15: 2039 | U15: =S15/T15 -> 12966.316
A16: Middlesex | B16: Sayreville Borough | C16: =$B$5*R16 -> 1959.3985 | D16: =U16*$B$6 -> 4365.442 | E16: =C16+D16 -> 6324.8405 | F16: =E16/(K16/100) -> 321163.24 | G16: 208675.08 | H16: =G16-F16 -> -112488.16 | I16: 330954.76 | J16: =I16-F16 -> 9791.5223 | K16: ='Tax Levies and EQ Tax Rates'!O23 -> 1.9693538 | L16: ='# and Assessed Value of Parcels'!G23/'# and Assessed Value of Parcels'!O23 -> 0.96279666 | M16: ='# and Assessed Value of Parcels'!H23/'# and Assessed Value of Parcels'!P23 -> 0.85286918 | N16: =(L16+M16)/2 -> 0.90783292 | O16: ='Tax Levies and EQ Tax Rates'!I23 -> 35498458 | P16: =N16*O16 -> 32226669 | Q16: 45345 | R16: =P16/Q16 -> 710.69949 | S16: ='Tax Levies and EQ Tax Rates'!C23 -> 67957093 | T16: 6616 | U16: =S16/T16 -> 10271.628
A17: Middlesex | B17: South River Borough | C17: =$B$5*R17 -> 1682.9131 | D17: =U17*$B$6 -> 3171.173 | E17: =C17+D17 -> 4854.0861 | F17: =E17/(K17/100) -> 255903.15 | G17: 163469.67 | H17: =G17-F17 -> -92433.485 | I17: 293469.91 | J17: =I17-F17 -> 37566.757 | K17: ='Tax Levies and EQ Tax Rates'!O24 -> 1.896845 | L17: ='# and Assessed Value of Parcels'!G24/'# and Assessed Value of Parcels'!O24 -> 0.95376862 | M17: ='# and Assessed Value of Parcels'!H24/'# and Assessed Value of Parcels'!P24 -> 0.87694473 | N17: =(L17+M17)/2 -> 0.91535668 | O17: ='Tax Levies and EQ Tax Rates'!I24 -> 10748447 | P17: =N17*O17 -> 9838662.7 | Q17: 16118 | R17: =P17/Q17 -> 610.41461 | S17: ='Tax Levies and EQ Tax Rates'!C24 -> 18146571 | T17: 2432 | U17: =S17/T17 -> 7461.5835
A18: Middlesex | B18: Woodbridge Township | C18: =$B$5*R18 -> 2315.5769 | D18: =U18*$B$6 -> 5638.8502 | E18: =C18+D18 -> 7954.4271 | F18: =E18/(K18/100) -> 340011.86 | G18: 232839.67 | H18: =G18-F18 -> -107172.19 | I18: 307619.51 | J18: =I18-F18 -> -32392.358 | K18: ='Tax Levies and EQ Tax Rates'!O25 -> 2.3394558 | L18: ='# and Assessed Value of Parcels'!G25/'# and Assessed Value of Parcels'!O25 -> 0.95527754 | M18: ='# and Assessed Value of Parcels'!H25/'# and Assessed Value of Parcels'!P25 -> 0.7164271 | N18: =(L18+M18)/2 -> 0.83585232 | O18: ='Tax Levies and EQ Tax Rates'!I25 -> 1.0413965e+08 | P18: =N18*O18 -> 87045366 | Q18: 103639 | R18: =P18/Q18 -> 839.89006 | S18: ='Tax Levies and EQ Tax Rates'!C25 -> 190553334 | T18: 14362 | U18: =S18/T18 -> 13267.883
A19: Monmouth | B19: Keansburg Borough | C19: =$B$5*R19 -> 3145.2065 | D19: =U19*$B$6 -> 1264.2511 | E19: =C19+D19 -> 4409.4575 | F19: =E19/(K19/100) -> 163479.66 | G19: 134718.75 | H19: =G19-F19 -> -28760.905 | I19: 183891.1 | J19: =I19-F19 -> 20411.448 | K19: ='Tax Levies and EQ Tax Rates'!O26 -> 2.6972516 | L19: ='# and Assessed Value of Parcels'!G26/'# and Assessed Value of Parcels'!O26 -> 0.96441281 | M19: ='# and Assessed Value of Parcels'!H26/'# and Assessed Value of Parcels'!P26 -> 0.88303144 | N19: =(L19+M19)/2 -> 0.92372213 | O19: ='Tax Levies and EQ Tax Rates'!I26 -> 12047538 | P19: =N19*O19 -> 11128578 | Q19: 9755 | R19: =P19/Q19 -> 1140.8076 | S19: ='Tax Levies and EQ Tax Rates'!C26 -> 5294981 | T19: 1780 | U19: =S19/T19 -> 2974.7084
A20: Monmouth | B20: Manalapan Township | C20: =$B$5*R20 -> 1593.4249 | D20: =U20*$B$6 -> 5811.8988 | E20: =C20+D20 -> 7405.3237 | F20: =E20/(K20/100) -> 457489.09 | G20: 292062.5 | H20: =G20-F20 -> -165426.59 | I20: 480487.37 | J20: =I20-F20 -> 22998.28 | K20: ='Tax Levies and EQ Tax Rates'!O27 -> 1.6186886 | L20: ='# and Assessed Value of Parcels'!G27/'# and Assessed Value of Parcels'!O27 -> 0.97272104 | M20: ='# and Assessed Value of Parcels'!H27/'# and Assessed Value of Parcels'!P27 -> 0.9220575 | N20: =(L20+M20)/2 -> 0.94738927 | O20: ='Tax Levies and EQ Tax Rates'!I27 -> 24954149 | P20: =N20*O20 -> 23641293 | Q20: 40905 | R20: =P20/Q20 -> 577.95608 | S20: ='Tax Levies and EQ Tax Rates'!C27 -> 66693248 | T20: 4877 | U20: =S20/T20 -> 13675.056
A21: Passaic | B21: Paterson City | C21: =$B$5*R21 -> 2099.9796 | D21: =U21*$B$6 -> 686.56224 | E21: =C21+D21 -> 2786.5418 | F21: =E21/(K21/100) -> 107841.82 | G21: 127704.12 | H21: =G21-F21 -> 19862.305 | I21: 259019.58 | J21: =I21-F21 -> 151177.77 | K21: ='Tax Levies and EQ Tax Rates'!O33 -> 2.5839159 | L21: ='# and Assessed Value of Parcels'!G33/'# and Assessed Value of Parcels'!O33 -> 0.82159481 | M21: ='# and Assessed Value of Parcels'!H33/'# and Assessed Value of Parcels'!P33 -> 0.65337602 | N21: =(L21+M21)/2 -> 0.73748542 | O21: ='Tax Levies and EQ Tax Rates'!I33 -> 1.6497449e+08 | P21: =N21*O21 -> 1.2166628e+08 | Q21: 159732 | R21: =P21/Q21 -> 761.69008 | S21: ='Tax Levies and EQ Tax Rates'!C33 -> 50970381 | T21: 31552 | U21: =S21/T21 -> 1615.4406
A22: Passaic | B22: Pompton Lakes Borough | C22: =$B$5*R22 -> 2449.0171 | D22: =U22*$B$6 -> 5631.4716 | E22: =C22+D22 -> 8080.4887 | F22: =E22/(K22/100) -> 283432.71 | G22: 277978.02 | H22: =G22-F22 -> -5454.6889 | I22: 297009.71 | J22: =I22-F22 -> 13577.009 | K22: ='Tax Levies and EQ Tax Rates'!O34 -> 2.8509373 | L22: ='# and Assessed Value of Parcels'!G34/'# and Assessed Value of Parcels'!O34 -> 0.95521999 | M22: ='# and Assessed Value of Parcels'!H34/'# and Assessed Value of Parcels'!P34 -> 0.87552226 | N22: =(L22+M22)/2 -> 0.91537113 | O22: ='Tax Levies and EQ Tax Rates'!I34 -> 10797816 | P22: =N22*O22 -> 9884009 | Q22: 11127 | R22: =P22/Q22 -> 888.29056 | S22: ='Tax Levies and EQ Tax Rates'!C34 -> 25639759 | T22: 1935 | U22: =S22/T22 -> 13250.521
A23: Passaic | B23: Wayne Township | C23: =$B$5*R23 -> 2768.1416 | D23: =U23*$B$6 -> 8457.9535 | E23: =C23+D23 -> 11226.095 | F23: =E23/(K23/100) -> 552668.28 | G23: 153319.37 | H23: =G23-F23 -> -399348.9 | I23: 477846.14 | J23: =I23-F23 -> -74822.141 | K23: ='Tax Levies and EQ Tax Rates'!O35 -> 2.0312538 | L23: ='# and Assessed Value of Parcels'!G35/'# and Assessed Value of Parcels'!O35 -> 0.95973428 | M23: ='# and Assessed Value of Parcels'!H35/'# and Assessed Value of Parcels'!P35 -> 0.74630979 | N23: =(L23+M23)/2 -> 0.85302204 | O23: ='Tax Levies and EQ Tax Rates'!I35 -> 64546529 | P23: =N23*O23 -> 55059612 | Q23: 54838 | R23: =P23/Q23 -> 1004.0412 | S23: ='Tax Levies and EQ Tax Rates'!C35 -> 156760706 | T23: 7877 | U23: =S23/T23 -> 19901.067
A24: Somerset | B24: Franklin Township | C24: =$B$5*R24 -> 1514.177 | D24: =U24*$B$6 -> 7590.1128 | E24: =C24+D24 -> 9104.2898 | F24: =E24/(K24/100) -> 560897.18 | G24: 141634.5 | H24: =G24-F24 -> -419262.68 | I24: 369483.93 | J24: =I24-F24 -> -191413.25 | K24: ='Tax Levies and EQ Tax Rates'!O38 -> 1.6231655 | L24: ='# and Assessed Value of Parcels'!G38/'# and Assessed Value of Parcels'!O38 -> 0.96646123 | M24: ='# and Assessed Value of Parcels'!H38/'# and Assessed Value of Parcels'!P38 -> 0.74002785 | N24: =(L24+M24)/2 -> 0.85324454 | O24: ='Tax Levies and EQ Tax Rates'!I38 -> 44004169 | P24: =N24*O24 -> 37546317 | Q24: 68364 | R24: =P24/Q24 -> 549.21182 | S24: ='Tax Levies and EQ Tax Rates'!C38 -> 151105752 | T24: 8461 | U24: =S24/T24 -> 17859.089
A25: Somerset | B25: Manville Borough | C25: =$B$5*R25 -> 2179.8075 | D25: =U25*$B$6 -> 4022.8578 | E25: =C25+D25 -> 6202.6653 | F25: =E25/(K25/100) -> 235097.44 | G25: 194522.93 | H25: =G25-F25 -> -40574.503 | I25: 253303.85 | J25: =I25-F25 -> 18206.418 | K25: ='Tax Levies and EQ Tax Rates'!O39 -> 2.6383382 | L25: ='# and Assessed Value of Parcels'!G39/'# and Assessed Value of Parcels'!O39 -> 0.95111773 | M25: ='# and Assessed Value of Parcels'!H39/'# and Assessed Value of Parcels'!P39 -> 0.86385135 | N25: =(L25+M25)/2 -> 0.90748454 | O25: ='Tax Levies and EQ Tax Rates'!I39 -> 9542787.2 | P25: =N25*O25 -> 8659931.8 | Q25: 10953 | R25: =P25/Q25 -> 790.64474 | S25: ='Tax Levies and EQ Tax Rates'!C39 -> 15656016 | T25: 1654 | U25: =S25/T25 -> 9465.5478
A26: Union | B26: Linden City | C26: =$B$5*R26 -> 2837.4457 | D26: =U26*$B$6 -> 6081.6774 | E26: =C26+D26 -> 8919.1231 | F26: =E26/(K26/100) -> 384214.47 | G26: 208675.72 | H26: =G26-F26 -> -175538.75 | I26: 326673.73 | J26: =I26-F26 -> -57540.74 | K26: ='Tax Levies and EQ Tax Rates'!O40 -> 2.3213918 | L26: ='# and Assessed Value of Parcels'!G40/'# and Assessed Value of Parcels'!O40 -> 0.90298507 | M26: ='# and Assessed Value of Parcels'!H40/'# and Assessed Value of Parcels'!P40 -> 0.53546516 | N26: =(L26+M26)/2 -> 0.71922512 | O26: ='Tax Levies and EQ Tax Rates'!I40 -> 62587105 | P26: =N26*O26 -> 45014218 | Q26: 43738 | R26: =P26/Q26 -> 1029.1787 | S26: ='Tax Levies and EQ Tax Rates'!C40 -> 94215916 | T26: 6584 | U26: =S26/T26 -> 14309.829
A27: Union | B27: Rahway City | C27: =$B$5*R27 -> 3051.4642 | D27: =U27*$B$6 -> 4663.7175 | E27: =C27+D27 -> 7715.1818 | F27: =E27/(K27/100) -> 267382.16 | G27: 264304.56 | H27: =G27-F27 -> -3077.5992 | I27: 271614.82 | J27: =I27-F27 -> 4232.6661 | K27: ='Tax Levies and EQ Tax Rates'!O41 -> 2.8854512 | L27: ='# and Assessed Value of Parcels'!G41/'# and Assessed Value of Parcels'!O41 -> 0.94367816 | M27: ='# and Assessed Value of Parcels'!H41/'# and Assessed Value of Parcels'!P41 -> 0.73460248 | N27: =(L27+M27)/2 -> 0.83914032 | O27: ='Tax Levies and EQ Tax Rates'!I41 -> 38983658 | P27: =N27*O27 -> 32712759 | Q27: 29556 | R27: =P27/Q27 -> 1106.806 | S27: ='Tax Levies and EQ Tax Rates'!C41 -> 45342308 | T27: 4132 | U27: =S27/T27 -> 10973.453
C28: =AVERAGE(C10:C27) -> 2243.8224 | D28: =AVERAGE(D10:D27) -> 4665.0767 | E28: =AVERAGE(E10:E27) -> 6908.8991 | F28: =AVERAGE(F10:F27) -> 311419.48 | G28: =AVERAGE(G10:G27) -> 203543.88 | H28: =AVERAGE(H10:H27) -> -107875.59 | I28: =AVERAGE(I10:I27) -> 314676.7 | J28: =AVERAGE(J10:J27) -> 3257.2281 | ... U28: =AVERAGE(U10:U27) -> 10976.651

Sheet (SFD 3 Bed) Muni Break Even
A1: 2020 Municipal Break Even Analysis for Single Family Detached (3 Bedroom) in Selected NJ Communities
A3: Single Family Detached (3 Bedroom) Multipliers
A4: Category | B4: Multiplier
A5: Household Size | B5: 2.757
A6: School Age Children | B6: 0.425
A8: Location | C8: 3 Bedroom Single Family Detached Municipal "Break Even Analysis" | E8: Fiscal Analysis | I8: Municipal Fiscal Impact Analysis
A9: County | B9: Municipality | C9: Municipal Tax Supported Cost | D9: Market Value "Break Even" | E9: Average Real (2020) Market Value of Buyout Properties | F9: Fiscal Surplus or Deficit (Based on Average Buyout Market Value) | G9: Average 2020 Residential Value in Buyout Community | H9: Fiscal Surplus or Deficit (Based on Average Residential Value) | I9: Municipal Equalized Property Tax Rate | J9: Percent of Total Parcels that are Residential | K9: Percent of Total Assessed Value that is Residential | L9: Average of Residential Parcels % and Assessed Value % | M9: Total Municipal Property Tax Levy | N9: Estimated Residential Share of Total Municipal Property Tax Levy | O9: 2020 Municipal Population | P9: 2020 Municipal Property Tax Supported Cost Per Person
A10: Atlantic | B10: Pleasantville City | C10: =$B$5*P10 -> 2629.6625 | D10: =C10/(I10/100) -> 85826.192 | E10: 60235 | F10: =E10-D10 -> -25591.192 | G10: 98363 | H10: =G10-D10 -> 12536.808 | I10: 3.0639394 | J10: ='# and Assessed Value of Parcels'!G5/'# and Assessed Value of Parcels'!O5 -> 0.92172813 | K10: ='# and Assessed Value of Parcels'!H5/'# and Assessed Value of Parcels'!P5 -> 0.73101366 | L10: =(J10+K10)/2 -> 0.8263709 | M10: ='Tax Levies and EQ Tax Rates'!I5 -> 23810385 | N10: =L10*M10 -> 19676209 | O10: 20629 | P10: =N10/O10 -> 953.81304
A11: Bergen | B11: Hillsdale Borough | C11: =$B$5*P11 -> 2609.5499 | D11: =C11/(I11/100) -> 486674.59 | E11: 221888 | F11: =E11-D11 -> -264786.59 | G11: 524210 | H11: =G11-D11 -> 37535.415 | I11: 0.53620016 | J11: ='# and Assessed Value of Parcels'!G6/'# and Assessed Value of Parcels'!O6 -> 0.96785506 | K11: ='# and Assessed Value of Parcels'!H6/'# and Assessed Value of Parcels'!P6 -> 0.93507138 | L11: =(J11+K11)/2 -> 0.95146322 | M11: ='Tax Levies and EQ Tax Rates'!I6 -> 10090281 | N11: =L11*M11 -> 9600531.2 | O11: 10143 | P11: =N11/O11 -> 946.51792
A12: Bergen | B12: New Milford Borough | C12: =$B$5*P12 -> 2706.2841 | D12: =C12/(I12/100) -> 324270.86 | E12: 373724 | F12: =E12-D12 -> 49453.139 | G12: 426888 | H12: =G12-D12 -> 102617.14 | I12: 0.83457519 | J12: ='# and Assessed Value of Parcels'!G7/'# and Assessed Value of Parcels'!O7 -> 0.98144233 | K12: ='# and Assessed Value of Parcels'!H7/'# and Assessed Value of Parcels'!P7 -> 0.94433259 | L12: =(J12+K12)/2 -> 0.96288746 | M12: ='Tax Levies and EQ Tax Rates'!I7 -> 17251960 | N12: =L12*M12 -> 16611696 | O12: 16923 | P12: =N12/O12 -> 981.6047
A13: Bergen | B13: Oakland Borough | C13: =$B$5*P13 -> 3082.9716 | D13: =C13/(I13/100) -> 511042.17 | E13: 366173 | F13: =E13-D13 -> -144869.17 | G13: 498789 | H13: =G13-D13 -> -12253.17 | I13: 0.60327146 | J13: ='# and Assessed Value of Parcels'!G8/'# and Assessed Value of Parcels'!O8 -> 0.9566732 | K13: ='# and Assessed Value of Parcels'!H8/'# and Assessed Value of Parcels'!P8 -> 0.84635298 | L13: =(J13+K13)/2 -> 0.90151309 | M13: ='Tax Levies and EQ Tax Rates'!I8 -> 15812581 | N13: =L13*M13 -> 14255249 | O13: 12748 | P13: =N13/O13 -> 1118.2342
A14: Bergen | B14: Westwood Borough | C14: =$B$5*P14 -> 3210.5266 | D14: =C14/(I14/100) -> 437612.4 | E14: 468655 | F14: =E14-D14 -> 31042.605 | G14: 459467 | H14: =G14-D14 -> 21854.605 | I14: 0.73364618 | J14: ='# and Assessed Value of Parcels'!G9/'# and Assessed Value of Parcels'!O9 -> 0.91940211 | K14: ='# and Assessed Value of Parcels'!H9/'# and Assessed Value of Parcels'!P9 -> 0.75552222 | L14: =(J14+K14)/2 -> 0.83746217 | M14: ='Tax Levies and EQ Tax Rates'!I9 -> 15687741 | N14: =L14*M14 -> 13137890 | O14: 11282 | P14: =N14/O14 -> 1164.5
A15: Burlington | B15: Lumberton Township | C15: =$B$5*P15 -> 1077.5897 | D15: =C15/(I15/100) -> 276189.13 | E15: 466392.16 | F15: =E15-D15 -> 190203.03 | G15: 306836 | H15: =G15-D15 -> 30646.87 | I15: 0.39016368 | J15: ='# and Assessed Value of Parcels'!G10/'# and Assessed Value of Parcels'!O10 -> 0.96040113 | K15: ='# and Assessed Value of Parcels'!H10/'# and Assessed Value of Parcels'!P10 -> 0.85301722 | L15: =(J15+K15)/2 -> 0.90670917 | M15: ='Tax Levies and EQ Tax Rates'!I10 -> 5518999.9 | N15: =L15*M15 -> 5004127.9 | O15: 12803 | P15: =N15/O15 -> 390.85588
A16: Burlington | B16: Medford Township | C16: =$B$5*P16 -> 1379.4002 | D16: =C16/(I16/100) -> 365342.55 | E16: 109349.33 | F16: =E16-D16 -> -255993.22 | G16: 370784 | H16: =G16-D16 -> 5441.4455 | I16: 0.37756351 | J16: ='# and Assessed Value of Parcels'!G11/'# and Assessed Value of Parcels'!O11 -> 0.95851299 | K16: ='# and Assessed Value of Parcels'!H11/'# and Assessed Value of Parcels'!P11 -> 0.91282275 | L16: =(J16+K16)/2 -> 0.93566787 | M16: ='Tax Levies and EQ Tax Rates'!I11 -> 13099198 | N16: =L16*M16 -> 12256498 | O16: 24497 | P16: =N16/O16 -> 500.32651
A17: Burlington | B17: Pemberton Township | C17: =$B$5*P17 -> 1499.5368 | D17: =C17/(I17/100) -> 147910.57 | E17: 93906.75 | F17: =E17-D17 -> -54003.816 | G17: 166312 | H17: =G17-D17 -> 18401.434 | I17: 1.0138132 | J17: ='# and Assessed Value of Parcels'!G12/'# and Assessed Value of Parcels'!O12 -> 0.98128309 | K17: ='# and Assessed Value of Parcels'!H12/'# and Assessed Value of Parcels'!P12 -> 0.9332896 | L17: =(J17+K17)/2 -> 0.95728635 | M17: ='Tax Levies and EQ Tax Rates'!I12 -> 15285485 | N17: =L17*M17 -> 14632586 | O17: 26903 | P17: =N17/O17 -> 543.90165
A18: Burlington | B18: Southampton Township | C18: =$B$5*P18 -> 1061.9192 | D18: =C18/(I18/100) -> 313012.69 | E18: 131465.05 | F18: =E18-D18 -> -181547.64 | G18: 238534 | H18: =G18-D18 -> -74478.694 | I18: 0.33925754 | J18: ='# and Assessed Value of Parcels'!G13/'# and Assessed Value of Parcels'!O13 -> 0.96051204 | K18: ='# and Assessed Value of Parcels'!H13/'# and Assessed Value of Parcels'!P13 -> 0.90183161 | L18: =(J18+K18)/2 -> 0.93117183 | M18: ='Tax Levies and EQ Tax Rates'!I13 -> 4267546.8 | N18: =L18*M18 -> 3973819.4 | O18: 10317 | P18: =N18/O18 -> 385.17198
A19: Cumberland | B19: Downe Township | C19: =$B$5*P19 -> 941.32413 | D19: =C19/(I19/100) -> 247311.12 | E19: 98620.342 | F19: =E19-D19 -> -148690.78 | G19: 118489 | H19: =G19-D19 -> -128822.12 | I19: 0.38062345 | J19: ='# and Assessed Value of Parcels'!G14/'# and Assessed Value of Parcels'!O14 -> 0.94935452 | K19: ='# and Assessed Value of Parcels'!H14/'# and Assessed Value of Parcels'!P14 -> 0.95309492 | L19: =(J19+K19)/2 -> 0.95122472 | M19: ='Tax Levies and EQ Tax Rates'!I14 -> 502154.1 | N19: =L19*M19 -> 477661.39 | O19: 1399 | P19: =N19/O19 -> 341.43059
A20: Cumberland | B20: Fairfield Township | C20: =$B$5*P20 -> 631.91841 | D20: =C20/(I20/100) -> 129279.22 | E20: 87057.657 | F20: =E20-D20 -> -42221.565 | G20: 142843 | H20: =G20-D20 -> 13563.778 | I20: 0.48880122 | J20: ='# and Assessed Value of Parcels'!G15/'# and Assessed Value of Parcels'!O15 -> 0.95576808 | K20: ='# and Assessed Value of Parcels'!H15/'# and Assessed Value of Parcels'!P15 -> 0.9003797 | L20: =(J20+K20)/2 -> 0.92807389 | M20: ='Tax Levies and EQ Tax Rates'!I15 -> 1369687.7 | N20: =L20*M20 -> 1271171.4 | O20: 5546 | P20: =N20/O20 -> 229.20508
A21: Cumberland | B21: Lawrence Township | C21: =$B$5*P21 -> 1042.647 | D21: =C21/(I21/100) -> 191227.92 | E21: 36085 | F21: =E21-D21 -> -155142.92 | G21: 165078 | H21: =G21-D21 -> -26149.921 | I21: 0.54523786 | J21: ='# and Assessed Value of Parcels'!G16/'# and Assessed Value of Parcels'!O16 -> 0.96660808 | K21: ='# and Assessed Value of Parcels'!H16/'# and Assessed Value of Parcels'!P16 -> 0.93631576 | L21: =(J21+K21)/2 -> 0.95146192 | M21: ='Tax Levies and EQ Tax Rates'!I16 -> 1227003.4 | N21: =L21*M21 -> 1167447 | O21: 3087 | P21: =N21/O21 -> 378.18173
A22: Essex | B22: Fairfield Township | C22: =$B$5*P22 -> 3424.9496 | D22: =C22/(I22/100) -> 787752.69 | E22: 219689 | F22: =E22-D22 -> -568063.69 | G22: 603218.44 | H22: =G22-D22 -> -184534.25 | I22: 0.43477472 | J22: ='[1]# and Assessed Value of Parcels'!G17/'[1]# and Assessed Value of Parcels'!O17 -> 0.78907204 | K22: ='[1]# and Assessed Value of Parcels'!H17/'[1]# and Assessed Value of Parcels'!P17 -> 0.44402102 | L22: =(J22+K22)/2 -> 0.61654653 | M22: ='[1]Tax Levies and EQ Tax Rates'!I17 -> 15861222 | N22: =L22*M22 -> 9779181.4 | O22: 7872 | P22: =N22/O22 -> 1242.2741
A23: Essex | B23: Newark City | C23: =$B$5*P23 -> 1545.9463 | D23: =C23/(I23/100) -> 91834.175 | E23: 164529.67 | F23: =E23-D23 -> 72695.492 | G23: 206835 | H23: =G23-D23 -> 115000.83 | I23: 1.6834106 | J23: ='# and Assessed Value of Parcels'!G18/'# and Assessed Value of Parcels'!O18 -> 0.84162884 | K23: ='# and Assessed Value of Parcels'!H18/'# and Assessed Value of Parcels'!P18 -> 0.54365223 | L23: =(J23+K23)/2 -> 0.69264054 | M23: ='Tax Levies and EQ Tax Rates'!I18 -> 252218004 | N23: =L23*M23 -> 1.7469641e+08 | O23: 311549 | P23: =N23/O23 -> 560.73495
A24: Hunterdon | B24: Lebanon Township | C24: =$B$5*P24 -> 1181.2888 | D24: =C24/(I24/100) -> 398624.01 | E24: 60691.5 | F24: =E24-D24 -> -337932.51 | G24: 379827 | H24: =G24-D24 -> -18797.013 | I24: 0.29634161 | J24: ='# and Assessed Value of Parcels'!G19/'# and Assessed Value of Parcels'!O19 -> 0.96383866 | K24: ='# and Assessed Value of Parcels'!H19/'# and Assessed Value of Parcels'!P19 -> 0.93906348 | L24: =(J24+K24)/2 -> 0.95145107 | M24: ='Tax Levies and EQ Tax Rates'!I19 -> 2789807.1 | N24: =L24*M24 -> 2654365 | O24: 6195 | P24: =N24/O24 -> 428.46893
A25: Middlesex | B25: East Brunswick Township | C25: =$B$5*P25 -> 2171.3074 | D25: =C25/(I25/100) -> 375428.3 | E25: 228185.83 | F25: =E25-D25 -> -147242.46 | G25: 380312 | H25: =G25-D25 -> 4883.7025 | I25: 0.57835476 | J25: ='# and Assessed Value of Parcels'!G20/'# and Assessed Value of Parcels'!O20 -> 0.95667524 | K25: ='# and Assessed Value of Parcels'!H20/'# and Assessed Value of Parcels'!P20 -> 0.81220548 | L25: =(J25+K25)/2 -> 0.88444036 | M25: ='Tax Levies and EQ Tax Rates'!I20 -> 44269380 | N25: =L25*M25 -> 39153626 | O25: 49715 | P25: =N25/O25 -> 787.56163
A26: Middlesex | B26: Old Bridge Township | C26: =$B$5*P26 -> 1449.0294 | D26: =C26/(I26/100) -> 328051.36 | E26: 131130.71 | F26: =E26-D26 -> -196920.64 | G26: 375525 | H26: =G26-D26 -> 47473.643 | I26: 0.44170809 | J26: ='# and Assessed Value of Parcels'!G21/'# and Assessed Value of Parcels'!O21 -> 0.97122792 | K26: ='# and Assessed Value of Parcels'!H21/'# and Assessed Value of Parcels'!P21 -> 0.88589383 | L26: =(J26+K26)/2 -> 0.92856088 | M26: ='Tax Levies and EQ Tax Rates'!I21 -> 37853002 | N26: =L26*M26 -> 35148817 | O26: 66876 | P26: =N26/O26 -> 525.58193
A27: Middlesex | B27: Middlesex Borough | C27: =$B$5*P27 -> 2290.0211 | D27: =C27/(I27/100) -> 281849.57 | E27: 306079.81 | F27: =E27-D27 -> 24230.246 | G27: 324883 | H27: =G27-D27 -> 43033.434 | I27: 0.81249766 | J27: ='# and Assessed Value of Parcels'!G22/'# and Assessed Value of Parcels'!O22 -> 0.92460317 | K27: ='# and Assessed Value of Parcels'!H22/'# and Assessed Value of Parcels'!P22 -> 0.82398227 | L27: =(J27+K27)/2 -> 0.87429272 | M27: ='Tax Levies and EQ Tax Rates'!I22 -> 13904913 | N27: =L27*M27 -> 12156964 | O27: 14636 | P27: =N27/O27 -> 830.62065
A28: Middlesex | B28: Sayreville Borough | C28: =$B$5*P28 -> 1959.3985 | D28: =C28/(I28/100) -> 289963.5 | E28: 208675.08 | F28: =E28-D28 -> -81288.419 | G28: 330955 | H28: =G28-D28 -> 40991.501 | I28: 0.67573971 | J28: ='# and Assessed Value of Parcels'!G23/'# and Assessed Value of Parcels'!O23 -> 0.96279666 | K28: ='# and Assessed Value of Parcels'!H23/'# and Assessed Value of Parcels'!P23 -> 0.85286918 | L28: =(J28+K28)/2 -> 0.90783292 | M28: ='Tax Levies and EQ Tax Rates'!I23 -> 35498458 | N28: =L28*M28 -> 32226669 | O28: 45345 | P28: =N28/O28 -> 710.69949
A29: Middlesex | B29: South River Borough | C29: =$B$5*P29 -> 1682.9131 | D29: =C29/(I29/100) -> 238510.28 | E29: 163469.67 | F29: =E29-D29 -> -75040.613 | G29: 293470 | H29: =G29-D29 -> 54959.721 | I29: 0.70559352 | J29: ='# and Assessed Value of Parcels'!G24/'# and Assessed Value of Parcels'!O24 -> 0.95376862 | K29: ='# and Assessed Value of Parcels'!H24/'# and Assessed Value of Parcels'!P24 -> 0.87694473 | L29: =(J29+K29)/2 -> 0.91535668 | M29: ='Tax Levies and EQ Tax Rates'!I24 -> 10748447 | N29: =L29*M29 -> 9838662.7 | O29: 16118 | P29: =N29/O29 -> 610.41461
A30: Middlesex | B30: Woodbridge Township | C30: =$B$5*P30 -> 2315.5769 | D30: =C30/(I30/100) -> 280090.29 | E30: 232839.67 | F30: =E30-D30 -> -47250.624 | G30: 307620 | H30: =G30-D30 -> 27529.705 | I30: 0.82672514 | J30: ='# and Assessed Value of Parcels'!G25/'# and Assessed Value of Parcels'!O25 -> 0.95527754 | K30: ='# and Assessed Value of Parcels'!H25/'# and Assessed Value of Parcels'!P25 -> 0.7164271 | L30: =(J30+K30)/2 -> 0.83585232 | M30: ='Tax Levies and EQ Tax Rates'!I25 -> 1.0413965e+08 | N30: =L30*M30 -> 87045366 | O30: 103639 | P30: =N30/O30 -> 839.89006
A31: Monmouth | B31: Keansburg Borough | C31: =$B$5*P31 -> 3145.2065 | D31: =C31/(I31/100) -> 167857.82 | E31: 134718.75 | F31: =E31-D31 -> -33139.069 | G31: 183891 | H31: =G31-D31 -> 16033.181 | I31: 1.8737325 | J31: ='# and Assessed Value of Parcels'!G26/'# and Assessed Value of Parcels'!O26 -> 0.96441281 | K31: ='# and Assessed Value of Parcels'!H26/'# and Assessed Value of Parcels'!P26 -> 0.88303144 | L31: =(J31+K31)/2 -> 0.92372213 | M31: ='Tax Levies and EQ Tax Rates'!I26 -> 12047538 | N31: =L31*M31 -> 11128578 | O31: 9755 | P31: =N31/O31 -> 1140.8076
A32: Monmouth | B32: Manalapan Township | C32: =$B$5*P32 -> 1593.4249 | D32: =C32/(I32/100) -> 477471.67 | E32: 292062.5 | F32: =E32-D32 -> -185409.17 | G32: 480487 | H32: =G32-D32 -> 3015.3312 | I32: 0.33372135 | J32: ='# and Assessed Value of Parcels'!G27/'# and Assessed Value of Parcels'!O27 -> 0.97272104 | K32: ='# and Assessed Value of Parcels'!H27/'# and Assessed Value of Parcels'!P27 -> 0.9220575 | L32: =(J32+K32)/2 -> 0.94738927 | M32: ='Tax Levies and EQ Tax Rates'!I27 -> 24954149 | N32: =L32*M32 -> 23641293 | O32: 40905 | P32: =N32/O32 -> 577.95608
A33: Monmouth | B33: Ocean Township | C33: =$B$5*P33 -> 2094.8251 | D33: =C33/(I33/100) -> 517601.17 | E33: 899998.8 | F33: =E33-D33 -> 382397.63 | G33: 542012 | H33: =G33-D33 -> 24410.83 | I33: 0.404718 | J33: ='# and Assessed Value of Parcels'!G28/'# and Assessed Value of Parcels'!O28 -> 0.95530169 | K33: ='# and Assessed Value of Parcels'!H28/'# and Assessed Value of Parcels'!P28 -> 0.88451081 | L33: =(J33+K33)/2 -> 0.91990625 | M33: ='Tax Levies and EQ Tax Rates'!I28 -> 22856408 | N33: =L33*M33 -> 21025753 | O33: 27672 | P33: =N33/O33 -> 759.82049
A34: Monmouth | B34: Sea Bright Borough | C34: =$B$5*P34 -> 7782.1828 | D34: =C34/(I34/100) -> 1515173.6 | E34: 1438976 | F34: =E34-D34 -> -76197.631 | G34: 697318 | H34: =G34-D34 -> -817855.63 | I34: 0.51361656 | J34: ='# and Assessed Value of Parcels'!G29/'# and Assessed Value of Parcels'!O29 -> 0.9358047 | K34: ='# and Assessed Value of Parcels'!H29/'# and Assessed Value of Parcels'!P29 -> 0.81959946 | L34: =(J34+K34)/2 -> 0.87770208 | M34: ='Tax Levies and EQ Tax Rates'!I29 -> 4660000 | N34: =L34*M34 -> 4090091.7 | O34: 1449 | P34: =N34/O34 -> 2822.6996
... A47: Warren | B47: Harmony Township | C47: =$B$5*P47 -> 1243.1437 | D47: =C47/(I47/100) -> 433268.6 | E47: 114179.2 | F47: =E47-D47 -> -319089.39 | G47: 240185 | H47: =G47-D47 -> -193083.6 | I47: 0.28692219 | J47: ='# and Assessed Value of Parcels'!G42/'# and Assessed Value of Parcels'!O42 -> 0.95134062 | K47: ='# and Assessed Value of Parcels'!H42/'# and Assessed Value of Parcels'!P42 -> 0.44542234 | L47: =(J47+K47)/2 -> 0.69838148 | M47: ='Tax Levies and EQ Tax Rates'!I42 -> 1616042.3 | N47: =L47*M47 -> 1128614 | O47: 2503 | P47: =N47/O47 -> 450.90451
C48: =AVERAGE(C10:C47) -> 2219.9955 | D48: =AVERAGE(D10:D47) -> 359859.61 | E48: =AVERAGE(E10:E47) -> 248533.53 | F48: =AVERAGE(F10:F47) -> -111326.07 | G48: =AVERAGE(G10:G47) -> 345015.35 | H48: =AVERAGE(H10:H47) -> -14844.252 | I48: =AVERAGE(I10:I47) -> 0.7753169 | J48: =AVERAGE(J10:J47) -> 0.94289016 | ... P48: =AVERAGE(P10:P47) -> 805.22145

Sheet (SFA 3 Bed) Break Even
A1: 2020 Break Even Analysis for Single Family Attached (3 Bedroom) in Selected NJ Communities
A3: Single Family Attached (3 Bedroom) Multipliers
A4: Category | B4: Multiplier
A5: Household Size | B5: 2.899
A6: School Age Children | B6: 0.564
A8: Location | C8: 2.5 Bedroom Single Family Attached "Break Even Analysis" | G8: Fiscal Analysis | M8: School and Municipal Fiscal Impact Analysis
A9: County | B9: Municipality | C9: Municipal Tax Supported Cost | D9: School Tax Supported Cost | E9: Total Tax Supported Cost | F9: Market Value "Break Even" | G9: Adjusted Average Real (2020) Market Value of Buyout Properties | H9: Average Real (2020) Market Value of Buyout Properties | I9: Fiscal Surplus or Deficit (Based on Average Buyout Market Value) | J9: Adjusted Average 2020 Residential Value in Buyout Community | K9: Average 2020 Residential Value in Buyout Community | L9: Fiscal Surplus or Deficit (Based on Average Residential Value) | M9: Total Municipal + School Equalized Property Tax Rate | N9: Percent of Total Parcels that are Residential | O9: Percent of Total Assessed Value that is Residential | P9: Average of Residential Parcels % and Assessed Value % | Q9: Total Municipal Property Tax Levy | R9: Estimated Residential Share of Total Municipal Property Tax Levy | S9: 2020 Municipal Population | T9: 2020 Municipal Property Tax Supported Cost Per Person | U9: Total School Property Tax Levy | V9: 2020 Total School Enrollment | W9: 2020 School Property Tax Supported Cost Per Pupil
A10: Atlantic | B10: Pleasantville City | C10: =$B$5*T10 -> 2765.104 | D10: =W10*$B$6 -> 1311.4548 | E10: =C10+D10 -> 4076.5588 | F10: =E10/(M10/100) -> 93278.14 | G10: =0.9*H10 -> 54211.5 | H10: 60235 | I10: =H10-F10 -> -33043.14 | J10: =0.9*K10 -> 88526.492 | K10: 98362.768 | L10: =K10-F10 -> 5084.6287 | M10: ='Tax Levies and EQ Tax Rates'!O5 -> 4.370326 | N10: ='# and Assessed Value of Parcels'!G5/'# and Assessed Value of Parcels'!O5 -> 0.92172813 | O10: ='# and Assessed Value of Parcels'!H5/'# and Assessed Value of Parcels'!P5 -> 0.73101366 | P10: =(N10+O10)/2 -> 0.8263709 | Q10: ='Tax Levies and EQ Tax Rates'!I5 -> 23810385 | R10: =P10*Q10 -> 19676209 | S10: 20629 | T10: =R10/S10 -> 953.81304 | U10: ='Tax Levies and EQ Tax Rates'!C5 -> 10152148 | V10: 4366 | W10: =U10/V10 -> 2325.2744
A11: Bergen | B11: New Milford Borough | C11: =$B$5*T11 -> 2845.672 | D11: =W11*$B$6 -> 8710.7237 | E11: =C11+D11 -> 11556.396 | F11: =E11/(M11/100) -> 455056.95 | G11: =0.9*H11 -> 336351.6 | H11: 373724 | I11: =H11-F11 -> -81332.953 | J11: =0.9*K11 -> 384199.28 | K11: 426888.09 | L11: =K11-F11 -> -28168.863 | M11: ='Tax Levies and EQ Tax Rates'!O7 -> 2.5395493 | N11: ='# and Assessed Value of Parcels'!G7/'# and Assessed Value of Parcels'!O7 -> 0.98144233 | O11: ='# and Assessed Value of Parcels'!H7/'# and Assessed Value of Parcels'!P7 -> 0.94433259 | P11: =(N11+O11)/2 -> 0.96288746 | Q11: ='Tax Levies and EQ Tax Rates'!I7 -> 17251960 | R11: =P11*Q11 -> 16611696 | S11: 16923 | T11: =R11/S11 -> 981.6047 | U11: ='Tax Levies and EQ Tax Rates'!C7 -> 35244453 | V11: 2282 | W11: =U11/V11 -> 15444.546
A12: Essex | B12: Newark City | C12: =$B$5*T12 -> 1625.5706 | D12: =W12*$B$6 -> 1273.8381 | E12: =C12+D12 -> 2899.4087 | F12: =E12/(M12/100) -> 109584 | G12: =0.9*H12 -> 148076.7 | H12: 164529.67 | I12: =H12-F12 -> 54945.666 | J12: =0.9*K12 -> 186151.52 | K12: 206835.02 | L12: =K12-F12 -> 97251.019 | M12: ='Tax Levies and EQ Tax Rates'!O18 -> 2.6458321 | N12: ='# and Assessed Value of Parcels'!G18/'# and Assessed Value of Parcels'!O18 -> 0.84162884 | O12: ='# and Assessed Value of Parcels'!H18/'# and Assessed Value of Parcels'!P18 -> 0.54365223 | P12: =(N12+O12)/2 -> 0.69264054 | Q12: ='Tax Levies and EQ Tax Rates'!I18 -> 252218004 | R12: =P12*Q12 -> 1.7469641e+08 | S12: 311549 | T12: =R12/S12 -> 560.73495 | U12: ='Tax Levies and EQ Tax Rates'!C18 -> 135819599 | V12: 60135 | W12: =U12/V12 -> 2258.5782
A13: Middlesex | B13: East Brunswick Township | C13: =$B$5*T13 -> 2283.1412 | D13: =W13*$B$6 -> 9222.9216 | E13: =C13+D13 -> 11506.063 | F13: =E13/(M13/100) -> 483801.25 | G13: =0.9*H13 -> 205367.25 | H13: 228185.83 | I13: =H13-F13 -> -255615.42 | J13: =0.9*K13 -> 342281.24 | K13: 380312.49 | L13: =K13-F13 -> -103488.77 | M13: ='Tax Levies and EQ Tax Rates'!O20 -> 2.3782623 | N13: ='# and Assessed Value of Parcels'!G20/'# and Assessed Value of Parcels'!O20 -> 0.95667524 | O13: ='# and Assessed Value of Parcels'!H20/'# and Assessed Value of Parcels'!P20 -> 0.81220548 | P13: =(N13+O13)/2 -> 0.88444036 | Q13: ='Tax Levies and EQ Tax Rates'!I20 -> 44269380 | R13: =P13*Q13 -> 39153626 | S13: 49715 | T13: =R13/S13 -> 787.56163 | U13: ='Tax Levies and EQ Tax Rates'!C20 -> 137771480 | V13: 8425 | W13: =U13/V13 -> 16352.698
A14: Middlesex | B14: Old Bridge Township | C14: =$B$5*T14 -> 1523.662 | D14: =W14*$B$6 -> 7448.4645 | E14: =C14+D14 -> 8972.1265 | F14: =E14/(M14/100) -> 532359.06 | G14: =0.9*H14 -> 118017.64 | H14: 131130.71 | I14: =H14-F14 -> -401228.35 | J14: =0.9*K14 -> 337972.55 | K14: 375525.05 | L14: =K14-F14 -> -156834.01 | M14: ='Tax Levies and EQ Tax Rates'!O21 -> 1.6853524 | N14: ='# and Assessed Value of Parcels'!G21/'# and Assessed Value of Parcels'!O21 -> 0.97122792 | O14: ='# and Assessed Value of Parcels'!H21/'# and Assessed Value of Parcels'!P21 -> 0.88589383 | P14: =(N14+O14)/2 -> 0.92856088 | Q14: ='Tax Levies and EQ Tax Rates'!I21 -> 37853002 | R14: =P14*Q14 -> 35148817 | S14: 66876 | T14: =R14/S14 -> 525.58193 | U14: ='Tax Levies and EQ Tax Rates'!C21 -> 106576433 | V14: 8070 | W14: =U14/V14 -> 13206.497
A15: Middlesex | B15: Middlesex Borough | C15: =$B$5*T15 -> 2407.9693 | D15: =W15*$B$6 -> 7313.0024 | E15: =C15+D15 -> 9720.9717 | F15: =E15/(M15/100) -> 412368.17 | G15: =0.9*H15 -> 275471.83 | H15: 306079.81 | I15: =H15-F15 -> -106288.36 | J15: =0.9*K15 -> 292394.56 | K15: 324882.84 | L15: =K15-F15 -> -87485.331 | M15: ='Tax Levies and EQ Tax Rates'!O22 -> 2.3573526 | N15: ='# and Assessed Value of Parcels'!G22/'# and Assessed Value of Parcels'!O22 -> 0.92460317 | O15: ='# and Assessed Value of Parcels'!H22/'# and Assessed Value of Parcels'!P22 -> 0.82398227 | P15: =(N15+O15)/2 -> 0.87429272 | Q15: ='Tax Levies and EQ Tax Rates'!I22 -> 13904913 | R15: =P15*Q15 -> 12156964 | S15: 14636 | T15: =R15/S15 -> 830.62065 | U15: ='Tax Levies and EQ Tax Rates'!C22 -> 26438319 | V15: 2039 | W15: =U15/V15 -> 12966.316
A16: Middlesex | B16: Sayreville Borough | C16: =$B$5*T16 -> 2060.3178 | D16: =W16*$B$6 -> 5793.1984 | E16: =C16+D16 -> 7853.5162 | F16: =E16/(M16/100) -> 398786.45 | G16: =0.9*H16 -> 187807.57 | H16: 208675.08 | I16: =H16-F16 -> -190111.37 | J16: =0.9*K16 -> 297859.28 | K16: 330954.76 | L16: =K16-F16 -> -67831.688 | M16: ='Tax Levies and EQ Tax Rates'!O23 -> 1.9693538 | N16: ='# and Assessed Value of Parcels'!G23/'# and Assessed Value of Parcels'!O23 -> 0.96279666 | O16: ='# and Assessed Value of Parcels'!H23/'# and Assessed Value of Parcels'!P23 -> 0.85286918 | P16: =(N16+O16)/2 -> 0.90783292 | Q16: ='Tax Levies and EQ Tax Rates'!I23 -> 35498458 | R16: =P16*Q16 -> 32226669 | S16: 45345 | T16: =R16/S16 -> 710.69949 | U16: ='Tax Levies and EQ Tax Rates'!C23 -> 67957093 | V16: 6616 | W16: =U16/V16 -> 10271.628
A17: Middlesex | B17: South River Borough | C17: =$B$5*T17 -> 1769.592 | D17: =W17*$B$6 -> 4208.3331 | E17: =C17+D17 -> 5977.925 | F17: =E17/(M17/100) -> 315150.96 | G17: =0.9*H17 -> 147122.7 | H17: 163469.67 | I17: =H17-F17 -> -151681.29 | J17: =0.9*K17 -> 264122.92 | K17: 293469.91 | L17: =K17-F17 -> -21681.046 | M17: ='Tax Levies and EQ Tax Rates'!O24 -> 1.896845 | N17: ='# and Assessed Value of Parcels'!G24/'# and Assessed Value of Parcels'!O24 -> 0.95376862 | O17: ='# and Assessed Value of Parcels'!H24/'# and Assessed Value of Parcels'!P24 -> 0.87694473 | P17: =(N17+O17)/2 -> 0.91535668 | Q17: ='Tax Levies and EQ Tax Rates'!I24 -> 10748447 | R17: =P17*Q17 -> 9838662.7 | S17: 16118 | T17: =R17/S17 -> 610.41461 | U17: ='Tax Levies and EQ Tax Rates'!C24 -> 18146571 | V17: 2432 | W17: =U17/V17 -> 7461.5835
A18: Middlesex | B18: Woodbridge Township | C18: =$B$5*T18 -> 2434.8413 | D18: =W18*$B$6 -> 7483.0859 | E18: =C18+D18 -> 9917.9272 | F18: =E18/(M18/100) -> 423941.65 | G18: =0.9*H18 -> 209555.7 | H18: 232839.67 | I18: =H18-F18 -> -191101.97 | J18: =0.9*K18 -> 276857.56 | K18: 307619.51 | L18: =K18-F18 -> -116322.14 | M18: ='Tax Levies and EQ Tax Rates'!O25 -> 2.3394558 | N18: ='# and Assessed Value of Parcels'!G25/'# and Assessed Value of Parcels'!O25 -> 0.95527754 | O18: ='# and Assessed Value of Parcels'!H25/'# and Assessed Value of Parcels'!P25 -> 0.7164271 | P18: =(N18+O18)/2 -> 0.83585232 | Q18: ='Tax Levies and EQ Tax Rates'!I25 -> 1.0413965e+08 | R18: =P18*Q18 -> 87045366 | S18: 103639 | T18: =R18/S18 -> 839.89006 | U18: ='Tax Levies and EQ Tax Rates'!C25 -> 190553334 | V18: 14362 | W18: =U18/V18 -> 13267.883
A19: Monmouth | B19: Keansburg Borough | C19: =$B$5*T19 -> 3307.2011 | D19: =W19*$B$6 -> 1677.7356 | E19: =C19+D19 -> 4984.9367 | F19: =E19/(M19/100) -> 184815.42 | G19: =0.9*H19 -> 121246.88 | H19: 134718.75 | I19: =H19-F19 -> -50096.666 | J19: =0.9*K19 -> 165501.99 | K19: 183891.1 | L19: =K19-F19 -> -924.31329 | M19: ='Tax Levies and EQ Tax Rates'!O26 -> 2.6972516 | N19: ='# and Assessed Value of Parcels'!G26/'# and Assessed Value of Parcels'!O26 -> 0.96441281 | O19: ='# and Assessed Value of Parcels'!H26/'# and Assessed Value of Parcels'!P26 -> 0.88303144 | P19: =(N19+O19)/2 -> 0.92372213 | Q19: ='Tax Levies and EQ Tax Rates'!I26 -> 12047538 | R19: =P19*Q19 -> 11128578 | S19: 9755 | T19: =R19/S19 -> 1140.8076 | U19: ='Tax Levies and EQ Tax Rates'!C26 -> 5294981 | V19: 1780 | W19: =U19/V19 -> 2974.7084
A20: Monmouth | B20: Manalapan Township | C20: =$B$5*T20 -> 1675.4947 | D20: =W20*$B$6 -> 7712.7316 | E20: =C20+D20 -> 9388.2262 | F20: =E20/(M20/100) -> 579989.65 | G20: =0.9*H20 -> 262856.25 | H20: 292062.5 | I20: =H20-F20 -> -287927.15 | J20: =0.9*K20 -> 432438.64 | K20: 480487.37 | L20: =K20-F20 -> -99502.278 | M20: ='Tax Levies and EQ Tax Rates'!O27 -> 1.6186886 | N20: ='# and Assessed Value of Parcels'!G27/'# and Assessed Value of Parcels'!O27 -> 0.97272104 | O20: ='# and Assessed Value of Parcels'!H27/'# and Assessed Value of Parcels'!P27 -> 0.9220575 | P20: =(N20+O20)/2 -> 0.94738927 | Q20: ='Tax Levies and EQ Tax Rates'!I27 -> 24954149 | R20: =P20*Q20 -> 23641293 | S20: 40905 | T20: =R20/S20 -> 577.95608 | U20: ='Tax Levies and EQ Tax Rates'!C27 -> 66693248 | V20: 4877 | W20: =U20/V20 -> 13675.056
A21: Passaic | B21: Paterson City | C21: =$B$5*T21 -> 2208.1395 | D21: =W21*$B$6 -> 911.10848 | E21: =C21+D21 -> 3119.248 | F21: =E21/(M21/100) -> 120717.86 | G21: =0.9*H21 -> 114933.71 | H21: 127704.12 | I21: =H21-F21 -> 6986.2576 | J21: =0.9*K21 -> 233117.62 | K21: 259019.58 | L21: =K21-F21 -> 138301.72 | M21: ='Tax Levies and EQ Tax Rates'!O33 -> 2.5839159 | N21: ='# and Assessed Value of Parcels'!G33/'# and Assessed Value of Parcels'!O33 -> 0.82159481 | O21: ='# and Assessed Value of Parcels'!H33/'# and Assessed Value of Parcels'!P33 -> 0.65337602 | P21: =(N21+O21)/2 -> 0.73748542 | Q21: ='Tax Levies and EQ Tax Rates'!I33 -> 1.6497449e+08 | R21: =P21*Q21 -> 1.2166628e+08 | S21: 159732 | T21: =R21/S21 -> 761.69008 | U21: ='Tax Levies and EQ Tax Rates'!C33 -> 50970381 | V21: 31552 | W21: =U21/V21 -> 1615.4406
A22: Passaic | B22: Pompton Lakes Borough | C22: =$B$5*T22 -> 2575.1543 | D22: =W22*$B$6 -> 7473.2941 | E22: =C22+D22 -> 10048.448 | F22: =E22/(M22/100) -> 352461.22 | G22: =0.9*H22 -> 250180.21 | H22: 277978.02 | I22: =H22-F22 -> -74483.206 | J22: =0.9*K22 -> 267308.74 | K22: 297009.71 | L22: =K22-F22 -> -55451.508 | M22: ='Tax Levies and EQ Tax Rates'!O34 -> 2.8509373 | N22: ='# and Assessed Value of Parcels'!G34/'# and Assessed Value of Parcels'!O34 -> 0.95521999 | O22: ='# and Assessed Value of Parcels'!H34/'# and Assessed Value of Parcels'!P34 -> 0.87552226 | P22: =(N22+O22)/2 -> 0.91537113 | Q22: ='Tax Levies and EQ Tax Rates'!I34 -> 10797816 | R22: =P22*Q22 -> 9884009 | S22: 11127 | T22: =R22/S22 -> 888.29056 | U22: ='Tax Levies and EQ Tax Rates'!C34 -> 25639759 | V22: 1935 | W22: =U22/V22 -> 13250.521
A23: Passaic | B23: Wayne Township | C23: =$B$5*T23 -> 2910.7155 | D23: =W23*$B$6 -> 11224.202 | E23: =C23+D23 -> 14134.917 | F23: =E23/(M23/100) -> 695871.57 | G23: =0.9*H23 -> 137987.44 | H23: 153319.37 | I23: =H23-F23 -> -542552.19 | J23: =0.9*K23 -> 430061.52 | K23: 477846.14 | L23: =K23-F23 -> -218025.43 | M23: ='Tax Levies and EQ Tax Rates'!O35 -> 2.0312538 | N23: ='# and Assessed Value of Parcels'!G35/'# and Assessed Value of Parcels'!O35 -> 0.95973428 | O23: ='# and Assessed Value of Parcels'!H35/'# and Assessed Value of Parcels'!P35 -> 0.74630979 | P23: =(N23+O23)/2 -> 0.85302204 | Q23: ='Tax Levies and EQ Tax Rates'!I35 -> 64546529 | R23: =P23*Q23 -> 55059612 | S23: 54838 | T23: =R23/S23 -> 1004.0412 | U23: ='Tax Levies and EQ Tax Rates'!C35 -> 156760706 | V23: 7877 | W23: =U23/V23 -> 19901.067
A24: Somerset | B24: Franklin Township | C24: =$B$5*T24 -> 1592.1651 | D24: =W24*$B$6 -> 10072.526 | E24: =C24+D24 -> 11664.691 | F24: =E24/(M24/100) -> 718638.42 | G24: =0.9*H24 -> 127471.05 | H24: 141634.5 | I24: =H24-F24 -> -577003.92 | J24: =0.9*K24 -> 332535.54 | K24: 369483.93 | L24: =K24-F24 -> -349154.49 | M24: ='Tax Levies and EQ Tax Rates'!O38 -> 1.6231655 | N24: ='# and Assessed Value of Parcels'!G38/'# and Assessed Value of Parcels'!O38 -> 0.96646123 | O24: ='# and Assessed Value of Parcels'!H38/'# and Assessed Value of Parcels'!P38 -> 0.74002785 | P24: =(N24+O24)/2 -> 0.85324454 | Q24: ='Tax Levies and EQ Tax Rates'!I38 -> 44004169 | R24: =P24*Q24 -> 37546317 | S24: 68364 | T24: =R24/S24 -> 549.21182 | U24: ='Tax Levies and EQ Tax Rates'!C38 -> 151105752 | V24: 8461 | W24: =U24/V24 -> 17859.089
A25: Somerset | B25: Manville Borough | C25: =$B$5*T25 -> 2292.0791 | D25: =W25*$B$6 -> 5338.5689 | E25: =C25+D25 -> 7630.648 | F25: =E25/(M25/100) -> 289221.76 | G25: =0.9*H25 -> 175070.64 | H25: 194522.93 | I25: =H25-F25 -> -94698.827 | J25: =0.9*K25 -> 227973.47 | K25: 253303.85 | L25: =K25-F25 -> -35917.906 | M25: ='Tax Levies and EQ Tax Rates'!O39 -> 2.6383382 | N25: ='# and Assessed Value of Parcels'!G39/'# and Assessed Value of Parcels'!O39 -> 0.95111773 | O25: ='# and Assessed Value of Parcels'!H39/'# and Assessed Value of Parcels'!P39 -> 0.86385135 | P25: =(N25+O25)/2 -> 0.90748454 | Q25: ='Tax Levies and EQ Tax Rates'!I39 -> 9542787.2 | R25: =P25*Q25 -> 8659931.8 | S25: 10953 | T25: =R25/S25 -> 790.64474 | U25: ='Tax Levies and EQ Tax Rates'!C39 -> 15656016 | V25: 1654 | W25: =U25/V25 -> 9465.5478
A26: Union | B26: Linden City | C26: =$B$5*T26 -> 2983.5891 | D26: =W26*$B$6 -> 8070.7437 | E26: =C26+D26 -> 11054.333 | F26: =E26/(M26/100) -> 476194.19 | G26: =0.9*H26 -> 187808.15 | H26: 208675.72 | I26: =H26-F26 -> -267518.47 | J26: =0.9*K26 -> 294006.36 | K26: 326673.73 | L26: =K26-F26 -> -149520.46 | M26: ='Tax Levies and EQ Tax Rates'!O40 -> 2.3213918 | N26: ='# and Assessed Value of Parcels'!G40/'# and Assessed Value of Parcels'!O40 -> 0.90298507 | O26: ='# and Assessed Value of Parcels'!H40/'# and Assessed Value of Parcels'!P40 -> 0.53546516 | P26: =(N26+O26)/2 -> 0.71922512 | Q26: ='Tax Levies and EQ Tax Rates'!I40 -> 62587105 | R26: =P26*Q26 -> 45014218 | S26: 43738 | T26: =R26/S26 -> 1029.1787 | U26: ='Tax Levies and EQ Tax Rates'!C40 -> 94215916 | V26: 6584 | W26: =U26/V26 -> 14309.829
A27: Union | B27: Rahway City | C27: =$B$5*T27 -> 3208.6307 | D27: =W27*$B$6 -> 6189.0275 | E27: =C27+D27 -> 9397.6582 | F27: =E27/(M27/100) -> 325691.11 | G27: =0.9*H27 -> 237874.1 | H27: 264304.56 | I27: =H27-F27 -> -61386.553 | J27: =0.9*K27 -> 244453.34 | K27: 271614.82 | L27: =K27-F27 -> -54076.288 | M27: ='Tax Levies and EQ Tax Rates'!O41 -> 2.8854512 | N27: ='# and Assessed Value of Parcels'!G41/'# and Assessed Value of Parcels'!O41 -> 0.94367816 | O27: ='# and Assessed Value of Parcels'!H41/'# and Assessed Value of Parcels'!P41 -> 0.73460248 | P27: =(N27+O27)/2 -> 0.83914032 | Q27: ='Tax Levies and EQ Tax Rates'!I41 -> 38983658 | R27: =P27*Q27 -> 32712759 | S27: 29556 | T27: =R27/S27 -> 1106.806 | U27: ='Tax Levies and EQ Tax Rates'!C41 -> 45342308 | V27: 4132 | W27: =U27/V27 -> 10973.453
C28: =AVERAGE(C10:C27) -> 2359.3911 | D28: =AVERAGE(D10:D27) -> 6190.8311 | E28: =AVERAGE(E10:E27) -> 8550.2222 | F28: =AVERAGE(F10:F27) -> 387107.1 | G28: =AVERAGE(G10:G27) -> 183189.5 | H28: =AVERAGE(H10:H27) -> 203543.88 | I28: =AVERAGE(I10:I27) -> -183563.22 | J28: =AVERAGE(J10:J27) -> 283209.03 | ... W28: =AVERAGE(W10:W27) -> 10976.651

Sheet (SFA 3 Bed) Muni Break Even
A1: 2020 Municipal Break Even Analysis for Single Family Attached (3 Bedroom) in Selected NJ Communities
A3: Single Family Attached (3 Bedroom) Multipliers
A4: Category | B4: Multiplier
A5: Household Size | B5: 2.899
A6: School Age Children | B6: 0.564
A8: Location | C8: 3 Bedroom Single Family Detached Municipal "Break Even Analysis" | E8: Fiscal Analysis | K8: Municipal Fiscal Impact Analysis
A9: County | B9: Municipality | C9: Municipal Tax Supported Cost | D9: Market Value "Break Even" | E9: Adjusted Average Real (2020) Market Value of Buyout Properties | F9: Average Real (2020) Market Value of Buyout Properties | G9: Fiscal Surplus or Deficit (Based on Average Buyout Market Value) | H9: Adjusted Average 2020 Residential Value in Buyout Community | I9: Average 2020 Residential Value in Buyout Community | J9: Fiscal Surplus or Deficit (Based on Average Residential Value) | K9: Municipal Equalized Property Tax Rate | L9: Percent of Total Parcels that are Residential | M9: Percent of Total Assessed Value that is Residential | N9: Average of Residential Parcels % and Assessed Value % | O9: Total Municipal Property Tax Levy | P9: Estimated Residential Share of Total Municipal Property Tax Levy | Q9: 2020 Municipal Population | R9: 2020 Municipal Property Tax Supported Cost Per Person
A10: Atlantic | B10: Pleasantville City | C10: =$B$5*R10 -> 2765.104 | D10: =C10/(K10/100) -> 90246.693 | E10: =0.9*F10 -> 54211.5 | F10: 60235 | G10: =F10-D10 -> -30011.693 | H10: =0.9*I10 -> 88526.7 | I10: 98363 | J10: =I10-D10 -> 8116.3072 | K10: 3.0639394 | L10: ='# and Assessed Value of Parcels'!G5/'# and Assessed Value of Parcels'!O5 -> 0.92172813 | M10: ='# and Assessed Value of Parcels'!H5/'# and Assessed Value of Parcels'!P5 -> 0.73101366 | N10: =(L10+M10)/2 -> 0.8263709 | O10: ='Tax Levies and EQ Tax Rates'!I5 -> 23810385 | P10: =N10*O10 -> 19676209 | Q10: 20629 | R10: =P10/Q10 -> 953.81304
A11: Bergen | B11: Hillsdale Borough | C11: =$B$5*R11 -> 2743.9554 | D11: =C11/(K11/100) -> 511740.89 | E11: =0.9*F11 -> 199699.2 | F11: 221888 | G11: =F11-D11 -> -289852.89 | H11: =0.9*I11 -> 471789 | I11: 524210 | J11: =I11-D11 -> 12469.114 | K11: 0.53620016 | L11: ='# and Assessed Value of Parcels'!G6/'# and Assessed Value of Parcels'!O6 -> 0.96785506 | M11: ='# and Assessed Value of Parcels'!H6/'# and Assessed Value of Parcels'!P6 -> 0.93507138 | N11: =(L11+M11)/2 -> 0.95146322 | O11: ='Tax Levies and EQ Tax Rates'!I6 -> 10090281 | P11: =N11*O11 -> 9600531.2 | Q11: 10143 | R11: =P11/Q11 -> 946.51792
A12: Bergen | B12: New Milford Borough | C12: =$B$5*R12 -> 2845.672 | D12: =C12/(K12/100) -> 340972.52 | E12: =0.9*F12 -> 336351.6 | F12: 373724 | G12: =F12-D12 -> 32751.484 | H12: =0.9*I12 -> 384199.2 | I12: 426888 | J12: =I12-D12 -> 85915.484 | K12: 0.83457519 | L12: ='# and Assessed Value of Parcels'!G7/'# and Assessed Value of Parcels'!O7 -> 0.98144233 | M12: ='# and Assessed Value of Parcels'!H7/'# and Assessed Value of Parcels'!P7 -> 0.94433259 | N12: =(L12+M12)/2 -> 0.96288746 | O12: ='Tax Levies and EQ Tax Rates'!I7 -> 17251960 | P12: =N12*O12 -> 16611696 | Q12: 16923 | R12: =P12/Q12 -> 981.6047
A13: Bergen | B13: Oakland Borough | C13: =$B$5*R13 -> 3241.7608 | D13: =C13/(K13/100) -> 537363.53 | E13: =0.9*F13 -> 329555.7 | F13: 366173 | G13: =F13-D13 -> -171190.53 | H13: =0.9*I13 -> 448910.1 | I13: 498789 | J13: =I13-D13 -> -38574.53 | K13: 0.60327146 | L13: ='# and Assessed Value of Parcels'!G8/'# and Assessed Value of Parcels'!O8 -> 0.9566732 | M13: ='# and Assessed Value of Parcels'!H8/'# and Assessed Value of Parcels'!P8 -> 0.84635298 | N13: =(L13+M13)/2 -> 0.90151309 | O13: ='Tax Levies and EQ Tax Rates'!I8 -> 15812581 | P13: =N13*O13 -> 14255249 | Q13: 12748 | R13: =P13/Q13 -> 1118.2342
A14: Bergen | B14: Westwood Borough | C14: =$B$5*R14 -> 3375.8856 | D14: =C14/(K14/100) -> 460151.74 | E14: =0.9*F14 -> 421789.5 | F14: 468655 | G14: =F14-D14 -> 8503.2648 | H14: =0.9*I14 -> 413520.3 | I14: 459467 | J14: =I14-D14 -> -684.73516 | K14: 0.73364618 | L14: ='# and Assessed Value of Parcels'!G9/'# and Assessed Value of Parcels'!O9 -> 0.91940211 | M14: ='# and Assessed Value of Parcels'!H9/'# and Assessed Value of Parcels'!P9 -> 0.75552222 | N14: =(L14+M14)/2 -> 0.83746217 | O14: ='Tax Levies and EQ Tax Rates'!I9 -> 15687741 | P14: =N14*O14 -> 13137890 | Q14: 11282 | R14: =P14/Q14 -> 1164.5
A15: Burlington | B15: Lumberton Township | C15: =$B$5*R15 -> 1133.0912 | D15: =C15/(K15/100) -> 290414.32 | E15: =0.9*F15 -> 419752.95 | F15: 466392.16 | G15: =F15-D15 -> 175977.84 | H15: =0.9*I15 -> 276152.4 | I15: 306836 | J15: =I15-D15 -> 16421.677 | K15: 0.39016368 | L15: ='# and Assessed Value of Parcels'!G10/'# and Assessed Value of Parcels'!O10 -> 0.96040113 | M15: ='# and Assessed Value of Parcels'!H10/'# and Assessed Value of Parcels'!P10 -> 0.85301722 | N15: =(L15+M15)/2 -> 0.90670917 | O15: ='Tax Levies and EQ Tax Rates'!I10 -> 5518999.9 | P15: =N15*O15 -> 5004127.9 | Q15: 12803 | R15: =P15/Q15 -> 390.85588
A16: Burlington | B16: Medford Township | C16: =$B$5*R16 -> 1450.4465 | D16: =C16/(K16/100) -> 384159.62 | E16: =0.9*F16 -> 98414.4 | F16: 109349.33 | G16: =F16-D16 -> -274810.28 | H16: =0.9*I16 -> 333705.6 | I16: 370784 | J16: =I16-D16 -> -13375.618 | K16: 0.37756351 | L16: ='# and Assessed Value of Parcels'!G11/'# and Assessed Value of Parcels'!O11 -> 0.95851299 | M16: ='# and Assessed Value of Parcels'!H11/'# and Assessed Value of Parcels'!P11 -> 0.91282275 | N16: =(L16+M16)/2 -> 0.93566787 | O16: ='Tax Levies and EQ Tax Rates'!I11 -> 13099198 | P16: =N16*O16 -> 12256498 | Q16: 24497 | R16: =P16/Q16 -> 500.32651
A17: Burlington | B17: Pemberton Township | C17: =$B$5*R17 -> 1576.7709 | D17: =C17/(K17/100) -> 155528.74 | E17: =0.9*F17 -> 84516.075 | F17: 93906.75 | G17: =F17-D17 -> -61621.988 | H17: =0.9*I17 -> 149680.8 | I17: 166312 | J17: =I17-D17 -> 10783.262 | K17: 1.0138132 | L17: ='# and Assessed Value of Parcels'!G12/'# and Assessed Value of Parcels'!O12 -> 0.98128309 | M17: ='# and Assessed Value of Parcels'!H12/'# and Assessed Value of Parcels'!P12 -> 0.9332896 | N17: =(L17+M17)/2 -> 0.95728635 | O17: ='Tax Levies and EQ Tax Rates'!I12 -> 15285485 | P17: =N17*O17 -> 14632586 | Q17: 26903 | R17: =P17/Q17 -> 543.90165
A18: Burlington | B18: Southampton Township | C18: =$B$5*R18 -> 1116.6136 | D18: =C18/(K18/100) -> 329134.49 | E18: =0.9*F18 -> 118318.54 | F18: 131465.05 | G18: =F18-D18 -> -197669.44 | H18: =0.9*I18 -> 214680.6 | I18: 238534 | J18: =I18-D18 -> -90600.494 | K18: 0.33925754 | L18: ='# and Assessed Value of Parcels'!G13/'# and Assessed Value of Parcels'!O13 -> 0.96051204 | M18: ='# and Assessed Value of Parcels'!H13/'# and Assessed Value of Parcels'!P13 -> 0.90183161 | N18: =(L18+M18)/2 -> 0.93117183 | O18: ='Tax Levies and EQ Tax Rates'!I13 -> 4267546.8 | P18: =N18*O18 -> 3973819.4 | Q18: 10317 | R18: =P18/Q18 -> 385.17198
A19: Cumberland | B19: Downe Township | C19: =$B$5*R19 -> 989.80727 | D19: =C19/(K19/100) -> 260048.95 | E19: =0.9*F19 -> 88758.308 | F19: 98620.342 | G19: =F19-D19 -> -161428.6 | H19: =0.9*I19 -> 106640.1 | I19: 118489 | J19: =I19-D19 -> -141559.95 | K19: 0.38062345 | L19: ='# and Assessed Value of Parcels'!G14/'# and Assessed Value of Parcels'!O14 -> 0.94935452 | M19: ='# and Assessed Value of Parcels'!H14/'# and Assessed Value of Parcels'!P14 -> 0.95309492 | N19: =(L19+M19)/2 -> 0.95122472 | O19: ='Tax Levies and EQ Tax Rates'!I14 -> 502154.1 | P19: =N19*O19 -> 477661.39 | Q19: 1399 | R19: =P19/Q19 -> 341.43059
A20: Cumberland | B20: Fairfield Township | C20: =$B$5*R20 -> 664.46554 | D20: =C20/(K20/100) -> 135937.78 | E20: =0.9*F20 -> 78351.891 | F20: 87057.657 | G20: =F20-D20 -> -48880.125 | H20: =0.9*I20 -> 128558.7 | I20: 142843 | J20: =I20-D20 -> 6905.2177 | K20: 0.48880122 | L20: ='# and Assessed Value of Parcels'!G15/'# and Assessed Value of Parcels'!O15 -> 0.95576808 | M20: ='# and Assessed Value of Parcels'!H15/'# and Assessed Value of Parcels'!P15 -> 0.9003797 | N20: =(L20+M20)/2 -> 0.92807389 | O20: ='Tax Levies and EQ Tax Rates'!I15 -> 1369687.7 | P20: =N20*O20 -> 1271171.4 | Q20: 5546 | R20: =P20/Q20 -> 229.20508
A21: Cumberland | B21: Lawrence Township | C21: =$B$5*R21 -> 1096.3488 | D21: =C21/(K21/100) -> 201077.16 | E21: =0.9*F21 -> 32476.5 | F21: 36085 | G21: =F21-D21 -> -164992.16 | H21: =0.9*I21 -> 148570.2 | I21: 165078 | J21: =I21-D21 -> -35999.164 | K21: 0.54523786 | L21: ='# and Assessed Value of Parcels'!G16/'# and Assessed Value of Parcels'!O16 -> 0.96660808 | M21: ='# and Assessed Value of Parcels'!H16/'# and Assessed Value of Parcels'!P16 -> 0.93631576 | N21: =(L21+M21)/2 -> 0.95146192 | O21: ='Tax Levies and EQ Tax Rates'!I16 -> 1227003.4 | P21: =N21*O21 -> 1167447 | Q21: 3087 | R21: =P21/Q21 -> 378.18173
A22: Essex | B22: Fairfield Township | C22: =$B$5*R22 -> 3601.3525 | D22: =C22/(K22/100) -> 828326.1 | E22: =0.9*F22 -> 197720.1 | F22: 219689 | G22: =F22-D22 -> -608637.1 | H22: =0.9*I22 -> 542896.6 | I22: 603218.44 | J22: =I22-D22 -> -225107.65 | K22: 0.43477472 | L22: ='[1]# and Assessed Value of Parcels'!G17/'[1]# and Assessed Value of Parcels'!O17 -> 0.78907204 | M22: ='[1]# and Assessed Value of Parcels'!H17/'[1]# and Assessed Value of Parcels'!P17 -> 0.44402102 | N22: =(L22+M22)/2 -> 0.61654653 | O22: ='[1]Tax Levies and EQ Tax Rates'!I17 -> 15861222 | P22: =N22*O22 -> 9779181.4 | Q22: 7872 | R22: =P22/Q22 -> 1242.2741
A23: Essex | B23: Newark City | C23: =$B$5*R23 -> 1625.5706 | D23: =C23/(K23/100) -> 96564.118 | E23: =0.9*F23 -> 148076.7 | F23: 164529.67 | G23: =F23-D23 -> 67965.549 | H23: =0.9*I23 -> 186151.5 | I23: 206835 | J23: =I23-D23 -> 110270.88 | K23: 1.6834106 | L23: ='# and Assessed Value of Parcels'!G18/'# and Assessed Value of Parcels'!O18 -> 0.84162884 | M23: ='# and Assessed Value of Parcels'!H18/'# and Assessed Value of Parcels'!P18 -> 0.54365223 | N23: =(L23+M23)/2 -> 0.69264054 | O23: ='Tax Levies and EQ Tax Rates'!I18 -> 252218004 | P23: =N23*O23 -> 1.7469641e+08 | Q23: 311549 | R23: =P23/Q23 -> 560.73495
A24: Hunterdon | B24: Lebanon Township | C24: =$B$5*R24 -> 1242.1314 | D24: =C24/(K24/100) -> 419155.25 | E24: =0.9*F24 -> 54622.35 | F24: 60691.5 | G24: =F24-D24 -> -358463.75 | H24: =0.9*I24 -> 341844.3 | I24: 379827 | J24: =I24-D24 -> -39328.246 | K24: 0.29634161 | L24: ='# and Assessed Value of Parcels'!G19/'# and Assessed Value of Parcels'!O19 -> 0.96383866 | M24: ='# and Assessed Value of Parcels'!H19/'# and Assessed Value of Parcels'!P19 -> 0.93906348 | N24: =(L24+M24)/2 -> 0.95145107 | O24: ='Tax Levies and EQ Tax Rates'!I19 -> 2789807.1 | P24: =N24*O24 -> 2654365 | Q24: 6195 | R24: =P24/Q24 -> 428.46893
A25: Middlesex | B25: East Brunswick Township | C25: =$B$5*R25 -> 2283.1412 | D25: =C25/(K25/100) -> 394764.83 | E25: =0.9*F25 -> 205367.25 | F25: 228185.83 | G25: =F25-D25 -> -166579 | H25: =0.9*I25 -> 342280.8 | I25: 380312 | J25: =I25-D25 -> -14452.829 | K25: 0.57835476 | L25: ='# and Assessed Value of Parcels'!G20/'# and Assessed Value of Parcels'!O20 -> 0.95667524 | M25: ='# and Assessed Value of Parcels'!H20/'# and Assessed Value of Parcels'!P20 -> 0.81220548 | N25: =(L25+M25)/2 -> 0.88444036 | O25: ='Tax Levies and EQ Tax Rates'!I20 -> 44269380 | P25: =N25*O25 -> 39153626 | Q25: 49715 | R25: =P25/Q25 -> 787.56163
A26: Middlesex | B26: Old Bridge Township | C26: =$B$5*R26 -> 1523.662 | D26: =C26/(K26/100) -> 344947.73 | E26: =0.9*F26 -> 118017.64 | F26: 131130.71 | G26: =F26-D26 -> -213817.01 | H26: =0.9*I26 -> 337972.5 | I26: 375525 | J26: =I26-D26 -> 30577.273 | K26: 0.44170809 | L26: ='# and Assessed Value of Parcels'!G21/'# and Assessed Value of Parcels'!O21 -> 0.97122792 | M26: ='# and Assessed Value of Parcels'!H21/'# and Assessed Value of Parcels'!P21 -> 0.88589383 | N26: =(L26+M26)/2 -> 0.92856088 | O26: ='Tax Levies and EQ Tax Rates'!I21 -> 37853002 | P26: =N26*O26 -> 35148817 | Q26: 66876 | R26: =P26/Q26 -> 525.58193
A27: Middlesex | B27: Middlesex Borough | C27: =$B$5*R27 -> 2407.9693 | D27: =C27/(K27/100) -> 296366.3 | E27: =0.9*F27 -> 275471.83 | F27: 306079.81 | G27: =F27-D27 -> 9713.5113 | H27: =0.9*I27 -> 292394.7 | I27: 324883 | J27: =I27-D27 -> 28516.699 | K27: 0.81249766 | L27: ='# and Assessed Value of Parcels'!G22/'# and Assessed Value of Parcels'!O22 -> 0.92460317 | M27: ='# and Assessed Value of Parcels'!H22/'# and Assessed Value of Parcels'!P22 -> 0.82398227 | N27: =(L27+M27)/2 -> 0.87429272 | O27: ='Tax Levies and EQ Tax Rates'!I22 -> 13904913 | P27: =N27*O27 -> 12156964 | Q27: 14636 | R27: =P27/Q27 -> 830.62065
A28: Middlesex | B28: Sayreville Borough | C28: =$B$5*R28 -> 2060.3178 | D28: =C28/(K28/100) -> 304898.14 | E28: =0.9*F28 -> 187807.57 | F28: 208675.08 | G28: =F28-D28 -> -96223.064 | H28: =0.9*I28 -> 297859.5 | I28: 330955 | J28: =I28-D28 -> 26056.856 | K28: 0.67573971 | L28: ='# and Assessed Value of Parcels'!G23/'# and Assessed Value of Parcels'!O23 -> 0.96279666 | M28: ='# and Assessed Value of Parcels'!H23/'# and Assessed Value of Parcels'!P23 -> 0.85286918 | N28: =(L28+M28)/2 -> 0.90783292 | O28: ='Tax Levies and EQ Tax Rates'!I23 -> 35498458 | P28: =N28*O28 -> 32226669 | Q28: 45345 | R28: =P28/Q28 -> 710.69949
A29: Middlesex | B29: South River Borough | C29: =$B$5*R29 -> 1769.592 | D29: =C29/(K29/100) -> 250794.81 | E29: =0.9*F29 -> 147122.7 | F29: 163469.67 | G29: =F29-D29 -> -87325.147 | H29: =0.9*I29 -> 264123 | I29: 293470 | J29: =I29-D29 -> 42675.187 | K29: 0.70559352 | L29: ='# and Assessed Value of Parcels'!G24/'# and Assessed Value of Parcels'!O24 -> 0.95376862 | M29: ='# and Assessed Value of Parcels'!H24/'# and Assessed Value of Parcels'!P24 -> 0.87694473 | N29: =(L29+M29)/2 -> 0.91535668 | O29: ='Tax Levies and EQ Tax Rates'!I24 -> 10748447 | P29: =N29*O29 -> 9838662.7 | Q29: 16118 | R29: =P29/Q29 -> 610.41461
A30: Middlesex | B30: Woodbridge Township | C30: =$B$5*R30 -> 2434.8413 | D30: =C30/(K30/100) -> 294516.42 | E30: =0.9*F30 -> 209555.7 | F30: 232839.67 | G30: =F30-D30 -> -61676.747 | H30: =0.9*I30 -> 276858 | I30: 307620 | J30: =I30-D30 -> 13103.582 | K30: 0.82672514 | L30: ='# and Assessed Value of Parcels'!G25/'# and Assessed Value of Parcels'!O25 -> 0.95527754 | M30: ='# and Assessed Value of Parcels'!H25/'# and Assessed Value of Parcels'!P25 -> 0.7164271 | N30: =(L30+M30)/2 -> 0.83585232 | O30: ='Tax Levies and EQ Tax Rates'!I25 -> 1.0413965e+08 | P30: =N30*O30 -> 87045366 | Q30: 103639 | R30: =P30/Q30 -> 839.89006
A31: Monmouth | B31: Keansburg Borough | C31: =$B$5*R31 -> 3307.2011 | D31: =C31/(K31/100) -> 176503.38 | E31: =0.9*F31 -> 121246.88 | F31: 134718.75 | G31: =F31-D31 -> -41784.63 | H31: =0.9*I31 -> 165501.9 | I31: 183891 | J31: =I31-D31 -> 7387.6203 | K31: 1.8737325 | L31: ='# and Assessed Value of Parcels'!G26/'# and Assessed Value of Parcels'!O26 -> 0.96441281 | M31: ='# and Assessed Value of Parcels'!H26/'# and Assessed Value of Parcels'!P26 -> 0.88303144 | N31: =(L31+M31)/2 -> 0.92372213 | O31: ='Tax Levies and EQ Tax Rates'!I26 -> 12047538 | P31: =N31*O31 -> 11128578 | Q31: 9755 | R31: =P31/Q31 -> 1140.8076
A32: Monmouth | B32: Manalapan Township | C32: =$B$5*R32 -> 1675.4947 | D32: =C32/(K32/100) -> 502063.97 | E32: =0.9*F32 -> 262856.25 | F32: 292062.5 | G32: =F32-D32 -> -210001.47 | H32: =0.9*I32 -> 432438.3 | I32: 480487 | J32: =I32-D32 -> -21576.971 | K32: 0.33372135 | L32: ='# and Assessed Value of Parcels'!G27/'# and Assessed Value of Parcels'!O27 -> 0.97272104 | M32: ='# and Assessed Value of Parcels'!H27/'# and Assessed Value of Parcels'!P27 -> 0.9220575 | N32: =(L32+M32)/2 -> 0.94738927 | O32: ='Tax Levies and EQ Tax Rates'!I27 -> 24954149 | P32: =N32*O32 -> 23641293 | Q32: 40905 | R32: =P32/Q32 -> 577.95608
A33: Monmouth | B33: Ocean Township | C33: =$B$5*R33 -> 2202.7196 | D33: =C33/(K33/100) -> 544260.35 | E33: =0.9*F33 -> 809998.92 | F33: 899998.8 | G33: =F33-D33 -> 355738.45 | H33: =0.9*I33 -> 487810.8 | I33: 542012 | J33: =I33-D33 -> -2248.3527 | K33: 0.404718 | L33: ='# and Assessed Value of Parcels'!G28/'# and Assessed Value of Parcels'!O28 -> 0.95530169 | M33: ='# and Assessed Value of Parcels'!H28/'# and Assessed Value of Parcels'!P28 -> 0.88451081 | N33: =(L33+M33)/2 -> 0.91990625 | O33: ='Tax Levies and EQ Tax Rates'!I28 -> 22856408 | P33: =N33*O33 -> 21025753 | Q33: 27672 | R33: =P33/Q33 -> 759.82049
A34: Monmouth | B34: Sea Bright Borough | C34: =$B$5*R34 -> 8183.0061 | D34: =C34/(K34/100) -> 1593213 | E34: =0.9*F34 -> 1295078.4 | F34: 1438976 | G34: =F34-D34 -> -154237.04 | H34: =0.9*I34 -> 627586.2 | I34: 697318 | J34: =I34-D34 -> -895895.04 | K34: 0.51361656 | L34: ='# and Assessed Value of Parcels'!G29/'# and Assessed Value of Parcels'!O29 -> 0.9358047 | M34: ='# and Assessed Value of Parcels'!H29/'# and Assessed Value of Parcels'!P29 -> 0.81959946 | N34: =(L34+M34)/2 -> 0.87770208 | O34: ='Tax Levies and EQ Tax Rates'!I29 -> 4660000 | P34: =N34*O34 -> 4090091.7 | Q34: 1449 | R34: =P34/Q34 -> 2822.6996
... A47: Warren | B47: Harmony Township | C47: =$B$5*R47 -> 1307.1722 | D47: =C47/(K47/100) -> 455584.21 | E47: =0.9*F47 -> 102761.28 | F47: 114179.2 | G47: =F47-D47 -> -341405 | H47: =0.9*I47 -> 216166.5 | I47: 240185 | J47: =I47-D47 -> -215399.21 | K47: 0.28692219 | L47: ='# and Assessed Value of Parcels'!G42/'# and Assessed Value of Parcels'!O42 -> 0.95134062 | M47: ='# and Assessed Value of Parcels'!H42/'# and Assessed Value of Parcels'!P42 -> 0.44542234 | N47: =(L47+M47)/2 -> 0.69838148 | O47: ='Tax Levies and EQ Tax Rates'!I42 -> 1616042.3 | P47: =N47*O47 -> 1128614 | Q47: 2503 | R47: =P47/Q47 -> 450.90451
C48: =AVERAGE(C10:C47) -> 2334.337 | D48: =AVERAGE(D10:D47) -> 378394.27 | E48: =AVERAGE(E10:E47) -> 223680.18 | F48: =AVERAGE(F10:F47) -> 248533.53 | G48: =AVERAGE(G10:G47) -> -129860.74 | H48: =AVERAGE(H10:H47) -> 310513.82 | I48: =AVERAGE(I10:I47) -> 345015.35 | J48: =AVERAGE(J10:J47) -> -33378.915 | ... R48: =AVERAGE(R10:R47) -> 805.22145

Sheet  (SFA 2.5 Bed) Break Even
A1: 2020 Break Even Analysis for Single Family Attached (2.5 Bedroom) in Selected NJ Communities
A3: Single Family Attached (2.5 Bedroom) Multipliers
A4: Category | B4: Multiplier
A5: Household Size | B5: 2.507
A6: School Age Children | B6: 0.419
A8: Location | C8: 2.5 Bedroom Single Family Attached "Break Even Analysis" | G8: Fiscal Analysis | M8: School and Municipal Fiscal Impact Analysis
A9: County | B9: Municipality | C9: Municipal Tax Supported Cost | D9: School Tax Supported Cost | E9: Total Tax Supported Cost | F9: Market Value "Break Even" | G9: Adjusted Average Real (2020) Market Value of Buyout Properties | H9: Average Real (2020) Market Value of Buyout Properties | I9: Fiscal Surplus or Deficit (Based on Average Buyout Market Value) | J9: Adjusted Average 2020 Residential Value in Buyout Community | K9: Average 2020 Residential Value in Buyout Community | L9: Fiscal Surplus or Deficit (Based on Average Residential Value) | M9: Total Municipal + School Equalized Property Tax Rate | N9: Percent of Total Parcels that are Residential | O9: Percent of Total Assessed Value that is Residential | P9: Average of Residential Parcels % and Assessed Value % | Q9: Total Municipal Property Tax Levy | R9: Estimated Residential Share of Total Municipal Property Tax Levy | S9: 2020 Municipal Population | T9: 2020 Municipal Property Tax Supported Cost Per Person | U9: Total School Property Tax Levy | V9: 2020 Total School Enrollment | W9: 2020 School Property Tax Supported Cost Per Pupil
A10: Atlantic | B10: Pleasantville City | C10: =$B$5*T10 -> 2391.2093 | D10: =W10*$B$6 -> 974.28997 | E10: =C10+D10 -> 3365.4993 | F10: =E10/(M10/100) -> 77007.969 | G10: =0.85*H10 -> 51199.75 | H10: 60235 | I10: =H10-F10 -> -16772.969 | J10: =0.85*K10 -> 83608.353 | K10: 98362.768 | L10: =K10-F10 -> 21354.799 | M10: ='Tax Levies and EQ Tax Rates'!O5 -> 4.370326 | N10: ='# and Assessed Value of Parcels'!G5/'# and Assessed Value of Parcels'!O5 -> 0.92172813 | O10: ='# and Assessed Value of Parcels'!H5/'# and Assessed Value of Parcels'!P5 -> 0.73101366 | P10: =(N10+O10)/2 -> 0.8263709 | Q10: ='Tax Levies and EQ Tax Rates'!I5 -> 23810385 | R10: =P10*Q10 -> 19676209 | S10: 20629 | T10: =R10/S10 -> 953.81304 | U10: ='Tax Levies and EQ Tax Rates'!C5 -> 10152148 | V10: 4366 | W10: =U10/V10 -> 2325.2744
A11: Bergen | B11: New Milford Borough | C11: =$B$5*T11 -> 2460.883 | D11: =W11*$B$6 -> 6471.2646 | E11: =C11+D11 -> 8932.1476 | F11: =E11/(M11/100) -> 351721.76 | G11: =0.85*H11 -> 317665.4 | H11: 373724 | I11: =H11-F11 -> 22002.238 | J11: =0.85*K11 -> 362854.88 | K11: 426888.09 | L11: =K11-F11 -> 75166.328 | M11: ='Tax Levies and EQ Tax Rates'!O7 -> 2.5395493 | N11: ='# and Assessed Value of Parcels'!G7/'# and Assessed Value of Parcels'!O7 -> 0.98144233 | O11: ='# and Assessed Value of Parcels'!H7/'# and Assessed Value of Parcels'!P7 -> 0.94433259 | P11: =(N11+O11)/2 -> 0.96288746 | Q11: ='Tax Levies and EQ Tax Rates'!I7 -> 17251960 | R11: =P11*Q11 -> 16611696 | S11: 16923 | T11: =R11/S11 -> 981.6047 | U11: ='Tax Levies and EQ Tax Rates'!C7 -> 35244453 | V11: 2282 | W11: =U11/V11 -> 15444.546
A12: Essex | B12: Newark City | C12: =$B$5*T12 -> 1405.7625 | D12: =W12*$B$6 -> 946.34426 | E12: =C12+D12 -> 2352.1068 | F12: =E12/(M12/100) -> 88898.564 | G12: =0.85*H12 -> 139850.22 | H12: 164529.67 | I12: =H12-F12 -> 75631.103 | J12: =0.85*K12 -> 175809.77 | K12: 206835.02 | L12: =K12-F12 -> 117936.46 | M12: ='Tax Levies and EQ Tax Rates'!O18 -> 2.6458321 | N12: ='# and Assessed Value of Parcels'!G18/'# and Assessed Value of Parcels'!O18 -> 0.84162884 | O12: ='# and Assessed Value of Parcels'!H18/'# and Assessed Value of Parcels'!P18 -> 0.54365223 | P12: =(N12+O12)/2 -> 0.69264054 | Q12: ='Tax Levies and EQ Tax Rates'!I18 -> 252218004 | R12: =P12*Q12 -> 1.7469641e+08 | S12: 311549 | T12: =R12/S12 -> 560.73495 | U12: ='Tax Levies and EQ Tax Rates'!C18 -> 135819599 | V12: 60135 | W12: =U12/V12 -> 2258.5782
A13: Middlesex | B13: East Brunswick Township | C13: =$B$5*T13 -> 1974.417 | D13: =W13*$B$6 -> 6851.7804 | E13: =C13+D13 -> 8826.1974 | F13: =E13/(M13/100) -> 371119.6 | G13: =0.85*H13 -> 193957.96 | H13: 228185.83 | I13: =H13-F13 -> -142933.76 | J13: =0.85*K13 -> 323265.61 | K13: 380312.49 | L13: =K13-F13 -> 9192.8895 | M13: ='Tax Levies and EQ Tax Rates'!O20 -> 2.3782623 | N13: ='# and Assessed Value of Parcels'!G20/'# and Assessed Value of Parcels'!O20 -> 0.95667524 | O13: ='# and Assessed Value of Parcels'!H20/'# and Assessed Value of Parcels'!P20 -> 0.81220548 | P13: =(N13+O13)/2 -> 0.88444036 | Q13: ='Tax Levies and EQ Tax Rates'!I20 -> 44269380 | R13: =P13*Q13 -> 39153626 | S13: 49715 | T13: =R13/S13 -> 787.56163 | U13: ='Tax Levies and EQ Tax Rates'!C20 -> 137771480 | V13: 8425 | W13: =U13/V13 -> 16352.698
A14: Middlesex | B14: Old Bridge Township | C14: =$B$5*T14 -> 1317.6339 | D14: =W14*$B$6 -> 5533.5224 | E14: =C14+D14 -> 6851.1563 | F14: =E14/(M14/100) -> 406511.78 | G14: =0.85*H14 -> 111461.11 | H14: 131130.71 | I14: =H14-F14 -> -275381.07 | J14: =0.85*K14 -> 319196.3 | K14: 375525.05 | L14: =K14-F14 -> -30986.73 | M14: ='Tax Levies and EQ Tax Rates'!O21 -> 1.6853524 | N14: ='# and Assessed Value of Parcels'!G21/'# and Assessed Value of Parcels'!O21 -> 0.97122792 | O14: ='# and Assessed Value of Parcels'!H21/'# and Assessed Value of Parcels'!P21 -> 0.88589383 | P14: =(N14+O14)/2 -> 0.92856088 | Q14: ='Tax Levies and EQ Tax Rates'!I21 -> 37853002 | R14: =P14*Q14 -> 35148817 | S14: 66876 | T14: =R14/S14 -> 525.58193 | U14: ='Tax Levies and EQ Tax Rates'!C21 -> 106576433 | V14: 8070 | W14: =U14/V14 -> 13206.497
A15: Middlesex | B15: Middlesex Borough | C15: =$B$5*T15 -> 2082.366 | D15: =W15*$B$6 -> 5432.8865 | E15: =C15+D15 -> 7515.2525 | F15: =E15/(M15/100) -> 318800.53 | G15: =0.85*H15 -> 260167.84 | H15: 306079.81 | I15: =H15-F15 -> -12720.719 | J15: =0.85*K15 -> 276150.41 | K15: 324882.84 | L15: =K15-F15 -> 6082.3085 | M15: ='Tax Levies and EQ Tax Rates'!O22 -> 2.3573526 | N15: ='# and Assessed Value of Parcels'!G22/'# and Assessed Value of Parcels'!O22 -> 0.92460317 | O15: ='# and Assessed Value of Parcels'!H22/'# and Assessed Value of Parcels'!P22 -> 0.82398227 | P15: =(N15+O15)/2 -> 0.87429272 | Q15: ='Tax Levies and EQ Tax Rates'!I22 -> 13904913 | R15: =P15*Q15 -> 12156964 | S15: 14636 | T15: =R15/S15 -> 830.62065 | U15: ='Tax Levies and EQ Tax Rates'!C22 -> 26438319 | V15: 2039 | W15: =U15/V15 -> 12966.316
A16: Middlesex | B16: Sayreville Borough | C16: =$B$5*T16 -> 1781.7236 | D16: =W16*$B$6 -> 4303.8123 | E16: =C16+D16 -> 6085.5359 | F16: =E16/(M16/100) -> 309011.81 | G16: =0.85*H16 -> 177373.82 | H16: 208675.08 | I16: =H16-F16 -> -100336.73 | J16: =0.85*K16 -> 281311.55 | K16: 330954.76 | L16: =K16-F16 -> 21942.952 | M16: ='Tax Levies and EQ Tax Rates'!O23 -> 1.9693538 | N16: ='# and Assessed Value of Parcels'!G23/'# and Assessed Value of Parcels'!O23 -> 0.96279666 | O16: ='# and Assessed Value of Parcels'!H23/'# and Assessed Value of Parcels'!P23 -> 0.85286918 | P16: =(N16+O16)/2 -> 0.90783292 | Q16: ='Tax Levies and EQ Tax Rates'!I23 -> 35498458 | R16: =P16*Q16 -> 32226669 | S16: 45345 | T16: =R16/S16 -> 710.69949 | U16: ='Tax Levies and EQ Tax Rates'!C23 -> 67957093 | V16: 6616 | W16: =U16/V16 -> 10271.628
A17: Middlesex | B17: South River Borough | C17: =$B$5*T17 -> 1530.3094 | D17: =W17*$B$6 -> 3126.4035 | E17: =C17+D17 -> 4656.7129 | F17: =E17/(M17/100) -> 245497.81 | G17: =0.85*H17 -> 138949.22 | H17: 163469.67 | I17: =H17-F17 -> -82028.146 | J17: =0.85*K17 -> 249449.42 | K17: 293469.91 | L17: =K17-F17 -> 47972.097 | M17: ='Tax Levies and EQ Tax Rates'!O24 -> 1.896845 | N17: ='# and Assessed Value of Parcels'!G24/'# and Assessed Value of Parcels'!O24 -> 0.95376862 | O17: ='# and Assessed Value of Parcels'!H24/'# and Assessed Value of Parcels'!P24 -> 0.87694473 | P17: =(N17+O17)/2 -> 0.91535668 | Q17: ='Tax Levies and EQ Tax Rates'!I24 -> 10748447 | R17: =P17*Q17 -> 9838662.7 | S17: 16118 | T17: =R17/S17 -> 610.41461 | U17: ='Tax Levies and EQ Tax Rates'!C24 -> 18146571 | V17: 2432 | W17: =U17/V17 -> 7461.5835
A18: Middlesex | B18: Woodbridge Township | C18: =$B$5*T18 -> 2105.6044 | D18: =W18*$B$6 -> 5559.2429 | E18: =C18+D18 -> 7664.8473 | F18: =E18/(M18/100) -> 327633.78 | G18: =0.85*H18 -> 197913.72 | H18: 232839.67 | I18: =H18-F18 -> -94794.109 | J18: =0.85*K18 -> 261476.58 | K18: 307619.51 | L18: =K18-F18 -> -20014.273 | M18: ='Tax Levies and EQ Tax Rates'!O25 -> 2.3394558 | N18: ='# and Assessed Value of Parcels'!G25/'# and Assessed Value of Parcels'!O25 -> 0.95527754 | O18: ='# and Assessed Value of Parcels'!H25/'# and Assessed Value of Parcels'!P25 -> 0.7164271 | P18: =(N18+O18)/2 -> 0.83585232 | Q18: ='Tax Levies and EQ Tax Rates'!I25 -> 1.0413965e+08 | R18: =P18*Q18 -> 87045366 | S18: 103639 | T18: =R18/S18 -> 839.89006 | U18: ='Tax Levies and EQ Tax Rates'!C25 -> 190553334 | V18: 14362 | W18: =U18/V18 -> 13267.883
A19: Monmouth | B19: Keansburg Borough | C19: =$B$5*T19 -> 2860.0046 | D19: =W19*$B$6 -> 1246.4028 | E19: =C19+D19 -> 4106.4074 | F19: =E19/(M19/100) -> 152244.14 | G19: =0.85*H19 -> 114510.94 | H19: 134718.75 | I19: =H19-F19 -> -17525.389 | J19: =0.85*K19 -> 156307.44 | K19: 183891.1 | L19: =K19-F19 -> 31646.964 | M19: ='Tax Levies and EQ Tax Rates'!O26 -> 2.6972516 | N19: ='# and Assessed Value of Parcels'!G26/'# and Assessed Value of Parcels'!O26 -> 0.96441281 | O19: ='# and Assessed Value of Parcels'!H26/'# and Assessed Value of Parcels'!P26 -> 0.88303144 | P19: =(N19+O19)/2 -> 0.92372213 | Q19: ='Tax Levies and EQ Tax Rates'!I26 -> 12047538 | R19: =P19*Q19 -> 11128578 | S19: 9755 | T19: =R19/S19 -> 1140.8076 | U19: ='Tax Levies and EQ Tax Rates'!C26 -> 5294981 | V19: 1780 | W19: =U19/V19 -> 2974.7084
A20: Monmouth | B20: Manalapan Township | C20: =$B$5*T20 -> 1448.9359 | D20: =W20*$B$6 -> 5729.8485 | E20: =C20+D20 -> 7178.7843 | F20: =E20/(M20/100) -> 443493.85 | G20: =0.85*H20 -> 248253.12 | H20: 292062.5 | I20: =H20-F20 -> -151431.35 | J20: =0.85*K20 -> 408414.27 | K20: 480487.37 | L20: =K20-F20 -> 36993.521 | M20: ='Tax Levies and EQ Tax Rates'!O27 -> 1.6186886 | N20: ='# and Assessed Value of Parcels'!G27/'# and Assessed Value of Parcels'!O27 -> 0.97272104 | O20: ='# and Assessed Value of Parcels'!H27/'# and Assessed Value of Parcels'!P27 -> 0.9220575 | P20: =(N20+O20)/2 -> 0.94738927 | Q20: ='Tax Levies and EQ Tax Rates'!I27 -> 24954149 | R20: =P20*Q20 -> 23641293 | S20: 40905 | T20: =R20/S20 -> 577.95608 | U20: ='Tax Levies and EQ Tax Rates'!C27 -> 66693248 | V20: 4877 | W20: =U20/V20 -> 13675.056
A21: Passaic | B21: Paterson City | C21: =$B$5*T21 -> 1909.557 | D21: =W21*$B$6 -> 676.8696 | E21: =C21+D21 -> 2586.4266 | F21: =E21/(M21/100) -> 100097.17 | G21: =0.85*H21 -> 108548.5 | H21: 127704.12 | I21: =H21-F21 -> 27606.952 | J21: =0.85*K21 -> 220166.64 | K21: 259019.58 | L21: =K21-F21 -> 158922.41 | M21: ='Tax Levies and EQ Tax Rates'!O33 -> 2.5839159 | N21: ='# and Assessed Value of Parcels'!G33/'# and Assessed Value of Parcels'!O33 -> 0.82159481 | O21: ='# and Assessed Value of Parcels'!H33/'# and Assessed Value of Parcels'!P33 -> 0.65337602 | P21: =(N21+O21)/2 -> 0.73748542 | Q21: ='Tax Levies and EQ Tax Rates'!I33 -> 1.6497449e+08 | R21: =P21*Q21 -> 1.2166628e+08 | S21: 159732 | T21: =R21/S21 -> 761.69008 | U21: ='Tax Levies and EQ Tax Rates'!C33 -> 50970381 | V21: 31552 | W21: =U21/V21 -> 1615.4406
A22: Passaic | B22: Pompton Lakes Borough | C22: =$B$5*T22 -> 2226.9444 | D22: =W22*$B$6 -> 5551.9685 | E22: =C22+D22 -> 7778.9129 | F22: =E22/(M22/100) -> 272854.58 | G22: =0.85*H22 -> 236281.31 | H22: 277978.02 | I22: =H22-F22 -> 5123.4381 | J22: =0.85*K22 -> 252458.26 | K22: 297009.71 | L22: =K22-F22 -> 24155.136 | M22: ='Tax Levies and EQ Tax Rates'!O34 -> 2.8509373 | N22: ='# and Assessed Value of Parcels'!G34/'# and Assessed Value of Parcels'!O34 -> 0.95521999 | O22: ='# and Assessed Value of Parcels'!H34/'# and Assessed Value of Parcels'!P34 -> 0.87552226 | P22: =(N22+O22)/2 -> 0.91537113 | Q22: ='Tax Levies and EQ Tax Rates'!I34 -> 10797816 | R22: =P22*Q22 -> 9884009 | S22: 11127 | T22: =R22/S22 -> 888.29056 | U22: ='Tax Levies and EQ Tax Rates'!C34 -> 25639759 | V22: 1935 | W22: =U22/V22 -> 13250.521
A23: Passaic | B23: Wayne Township | C23: =$B$5*T23 -> 2517.1313 | D23: =W23*$B$6 -> 8338.5471 | E23: =C23+D23 -> 10855.678 | F23: =E23/(M23/100) -> 534432.41 | G23: =0.85*H23 -> 130321.47 | H23: 153319.37 | I23: =H23-F23 -> -381113.04 | J23: =0.85*K23 -> 406169.22 | K23: 477846.14 | L23: =K23-F23 -> -56586.275 | M23: ='Tax Levies and EQ Tax Rates'!O35 -> 2.0312538 | N23: ='# and Assessed Value of Parcels'!G35/'# and Assessed Value of Parcels'!O35 -> 0.95973428 | O23: ='# and Assessed Value of Parcels'!H35/'# and Assessed Value of Parcels'!P35 -> 0.74630979 | P23: =(N23+O23)/2 -> 0.85302204 | Q23: ='Tax Levies and EQ Tax Rates'!I35 -> 64546529 | R23: =P23*Q23 -> 55059612 | S23: 54838 | T23: =R23/S23 -> 1004.0412 | U23: ='Tax Levies and EQ Tax Rates'!C35 -> 156760706 | V23: 7877 | W23: =U23/V23 -> 19901.067
A24: Somerset | B24: Franklin Township | C24: =$B$5*T24 -> 1376.874 | D24: =W24*$B$6 -> 7482.9583 | E24: =C24+D24 -> 8859.8323 | F24: =E24/(M24/100) -> 545836.64 | G24: =0.85*H24 -> 120389.32 | H24: 141634.5 | I24: =H24-F24 -> -404202.14 | J24: =0.85*K24 -> 314061.34 | K24: 369483.93 | L24: =K24-F24 -> -176352.71 | M24: ='Tax Levies and EQ Tax Rates'!O38 -> 1.6231655 | N24: ='# and Assessed Value of Parcels'!G38/'# and Assessed Value of Parcels'!O38 -> 0.96646123 | O24: ='# and Assessed Value of Parcels'!H38/'# and Assessed Value of Parcels'!P38 -> 0.74002785 | P24: =(N24+O24)/2 -> 0.85324454 | Q24: ='Tax Levies and EQ Tax Rates'!I38 -> 44004169 | R24: =P24*Q24 -> 37546317 | S24: 68364 | T24: =R24/S24 -> 549.21182 | U24: ='Tax Levies and EQ Tax Rates'!C38 -> 151105752 | V24: 8461 | W24: =U24/V24 -> 17859.089
A25: Somerset | B25: Manville Borough | C25: =$B$5*T25 -> 1982.1464 | D25: =W25*$B$6 -> 3966.0645 | E25: =C25+D25 -> 5948.2109 | F25: =E25/(M25/100) -> 225452.94 | G25: =0.85*H25 -> 165344.49 | H25: 194522.93 | I25: =H25-F25 -> -30930.005 | J25: =0.85*K25 -> 215308.28 | K25: 253303.85 | L25: =K25-F25 -> 27850.916 | M25: ='Tax Levies and EQ Tax Rates'!O39 -> 2.6383382 | N25: ='# and Assessed Value of Parcels'!G39/'# and Assessed Value of Parcels'!O39 -> 0.95111773 | O25: ='# and Assessed Value of Parcels'!H39/'# and Assessed Value of Parcels'!P39 -> 0.86385135 | P25: =(N25+O25)/2 -> 0.90748454 | Q25: ='Tax Levies and EQ Tax Rates'!I39 -> 9542787.2 | R25: =P25*Q25 -> 8659931.8 | S25: 10953 | T25: =R25/S25 -> 790.64474 | U25: ='Tax Levies and EQ Tax Rates'!C39 -> 15656016 | V25: 1654 | W25: =U25/V25 -> 9465.5478
A26: Union | B26: Linden City | C26: =$B$5*T26 -> 2580.151 | D26: =W26*$B$6 -> 5995.8185 | E26: =C26+D26 -> 8575.9695 | F26: =E26/(M26/100) -> 369432.24 | G26: =0.85*H26 -> 177374.36 | H26: 208675.72 | I26: =H26-F26 -> -160756.52 | J26: =0.85*K26 -> 277672.67 | K26: 326673.73 | L26: =K26-F26 -> -42758.502 | M26: ='Tax Levies and EQ Tax Rates'!O40 -> 2.3213918 | N26: ='# and Assessed Value of Parcels'!G40/'# and Assessed Value of Parcels'!O40 -> 0.90298507 | O26: ='# and Assessed Value of Parcels'!H40/'# and Assessed Value of Parcels'!P40 -> 0.53546516 | P26: =(N26+O26)/2 -> 0.71922512 | Q26: ='Tax Levies and EQ Tax Rates'!I40 -> 62587105 | R26: =P26*Q26 -> 45014218 | S26: 43738 | T26: =R26/S26 -> 1029.1787 | U26: ='Tax Levies and EQ Tax Rates'!C40 -> 94215916 | V26: 6584 | W26: =U26/V26 -> 14309.829
A27: Union | B27: Rahway City | C27: =$B$5*T27 -> 2774.7627 | D27: =W27*$B$6 -> 4597.8768 | E27: =C27+D27 -> 7372.6396 | F27: =E27/(M27/100) -> 255510.8 | G27: =0.85*H27 -> 224658.87 | H27: 264304.56 | I27: =H27-F27 -> 8793.7581 | J27: =0.85*K27 -> 230872.6 | K27: 271614.82 | L27: =K27-F27 -> 16104.023 | M27: ='Tax Levies and EQ Tax Rates'!O41 -> 2.8854512 | N27: ='# and Assessed Value of Parcels'!G41/'# and Assessed Value of Parcels'!O41 -> 0.94367816 | O27: ='# and Assessed Value of Parcels'!H41/'# and Assessed Value of Parcels'!P41 -> 0.73460248 | P27: =(N27+O27)/2 -> 0.83914032 | Q27: ='Tax Levies and EQ Tax Rates'!I41 -> 38983658 | R27: =P27*Q27 -> 32712759 | S27: 29556 | T27: =R27/S27 -> 1106.806 | U27: ='Tax Levies and EQ Tax Rates'!C41 -> 45342308 | V27: 4132 | W27: =U27/V27 -> 10973.453
C28: =AVERAGE(C10:C27) -> 2040.3565 | D28: =AVERAGE(D10:D27) -> 4599.2167 | E28: =AVERAGE(E10:E27) -> 6639.5732 | F28: =AVERAGE(F10:F27) -> 299753.24 | G28: =AVERAGE(G10:G27) -> 173012.3 | H28: =AVERAGE(H10:H27) -> 203543.88 | I28: =AVERAGE(I10:I27) -> -96209.359 | J28: =AVERAGE(J10:J27) -> 267475.2 | ... W28: =AVERAGE(W10:W27) -> 10976.651

Sheet Adjusted (SFA 2.0 Bed) Break Ev
A1: 2020 Break Even Analysis for Single Family Attached (2.0 Bedroom) in Selected NJ Communities
A3: Single Family Attached (2.0 Bedroom) Multipliers
A4: Category | B4: Multiplier
A5: Household Size | B5: 2.115
A6: School Age Children | B6: 0.274
A8: Location | C8: 2.5 Bedroom Single Family Attached "Break Even Analysis" | G8: Fiscal Analysis | M8: School and Municipal Fiscal Impact Analysis
A9: County | B9: Municipality | C9: Municipal Tax Supported Cost | D9: School Tax Supported Cost | E9: Total Tax Supported Cost | F9: Market Value "Break Even" | G9: Adjusted Average Real (2020) Market Value of Buyout Properties | H9: Average Real (2020) Market Value of Buyout Properties | I9: Fiscal Surplus or Deficit (Based on Average Buyout Market Value) | J9: Adjusted Average 2020 Residential Value in Buyout Community | K9: Average 2020 Residential Value in Buyout Community | L9: Fiscal Surplus or Deficit (Based on Average Residential Value) | M9: Total Municipal + School Equalized Property Tax Rate | N9: Percent of Total Parcels that are Residential | O9: Percent of Total Assessed Value that is Residential | P9: Average of Residential Parcels % and Assessed Value % | Q9: Total Municipal Property Tax Levy | R9: Estimated Residential Share of Total Municipal Property Tax Levy | S9: 2020 Municipal Population | T9: 2020 Municipal Property Tax Supported Cost Per Person | U9: Total School Property Tax Levy | V9: 2020 Total School Enrollment | W9: 2020 School Property Tax Supported Cost Per Pupil
A10: Atlantic | B10: Pleasantville City | C10: =$B$5*T10 -> 2017.3146 | D10: =W10*$B$6 -> 637.12518 | E10: =C10+D10 -> 2654.4398 | F10: =E10/(M10/100) -> 60737.798 | G10: =0.8*H10 -> 48188 | H10: 60235 | I10: =H10-F10 -> -502.79809 | J10: =0.8*K10 -> 78690.215 | K10: 98362.768 | L10: =K10-F10 -> 37624.97 | M10: ='Tax Levies and EQ Tax Rates'!O5 -> 4.370326 | N10: ='# and Assessed Value of Parcels'!G5/'# and Assessed Value of Parcels'!O5 -> 0.92172813 | O10: ='# and Assessed Value of Parcels'!H5/'# and Assessed Value of Parcels'!P5 -> 0.73101366 | P10: =(N10+O10)/2 -> 0.8263709 | Q10: ='Tax Levies and EQ Tax Rates'!I5 -> 23810385 | R10: =P10*Q10 -> 19676209 | S10: 20629 | T10: =R10/S10 -> 953.81304 | U10: ='Tax Levies and EQ Tax Rates'!C5 -> 10152148 | V10: 4366 | W10: =U10/V10 -> 2325.2744
A11: Bergen | B11: New Milford Borough | C11: =$B$5*T11 -> 2076.0939 | D11: =W11*$B$6 -> 4231.8055 | E11: =C11+D11 -> 6307.8994 | F11: =E11/(M11/100) -> 248386.57 | G11: =0.8*H11 -> 298979.2 | H11: 373724 | I11: =H11-F11 -> 125337.43 | J11: =0.8*K11 -> 341510.47 | K11: 426888.09 | L11: =K11-F11 -> 178501.52 | M11: ='Tax Levies and EQ Tax Rates'!O7 -> 2.5395493 | N11: ='# and Assessed Value of Parcels'!G7/'# and Assessed Value of Parcels'!O7 -> 0.98144233 | O11: ='# and Assessed Value of Parcels'!H7/'# and Assessed Value of Parcels'!P7 -> 0.94433259 | P11: =(N11+O11)/2 -> 0.96288746 | Q11: ='Tax Levies and EQ Tax Rates'!I7 -> 17251960 | R11: =P11*Q11 -> 16611696 | S11: 16923 | T11: =R11/S11 -> 981.6047 | U11: ='Tax Levies and EQ Tax Rates'!C7 -> 35244453 | V11: 2282 | W11: =U11/V11 -> 15444.546
A12: Essex | B12: Newark City | C12: =$B$5*T12 -> 1185.9544 | D12: =W12*$B$6 -> 618.85042 | E12: =C12+D12 -> 1804.8048 | F12: =E12/(M12/100) -> 68213.127 | G12: =0.8*H12 -> 131623.73 | H12: 164529.67 | I12: =H12-F12 -> 96316.54 | J12: =0.8*K12 -> 165468.02 | K12: 206835.02 | L12: =K12-F12 -> 138621.89 | M12: ='Tax Levies and EQ Tax Rates'!O18 -> 2.6458321 | N12: ='# and Assessed Value of Parcels'!G18/'# and Assessed Value of Parcels'!O18 -> 0.84162884 | O12: ='# and Assessed Value of Parcels'!H18/'# and Assessed Value of Parcels'!P18 -> 0.54365223 | P12: =(N12+O12)/2 -> 0.69264054 | Q12: ='Tax Levies and EQ Tax Rates'!I18 -> 252218004 | R12: =P12*Q12 -> 1.7469641e+08 | S12: 311549 | T12: =R12/S12 -> 560.73495 | U12: ='Tax Levies and EQ Tax Rates'!C18 -> 135819599 | V12: 60135 | W12: =U12/V12 -> 2258.5782
A13: Middlesex | B13: East Brunswick Township | C13: =$B$5*T13 -> 1665.6928 | D13: =W13*$B$6 -> 4480.6392 | E13: =C13+D13 -> 6146.3321 | F13: =E13/(M13/100) -> 258437.94 | G13: =0.8*H13 -> 182548.67 | H13: 228185.83 | I13: =H13-F13 -> -30252.107 | J13: =0.8*K13 -> 304249.99 | K13: 380312.49 | L13: =K13-F13 -> 121874.55 | M13: ='Tax Levies and EQ Tax Rates'!O20 -> 2.3782623 | N13: ='# and Assessed Value of Parcels'!G20/'# and Assessed Value of Parcels'!O20 -> 0.95667524 | O13: ='# and Assessed Value of Parcels'!H20/'# and Assessed Value of Parcels'!P20 -> 0.81220548 | P13: =(N13+O13)/2 -> 0.88444036 | Q13: ='Tax Levies and EQ Tax Rates'!I20 -> 44269380 | R13: =P13*Q13 -> 39153626 | S13: 49715 | T13: =R13/S13 -> 787.56163 | U13: ='Tax Levies and EQ Tax Rates'!C20 -> 137771480 | V13: 8425 | W13: =U13/V13 -> 16352.698
A14: Middlesex | B14: Old Bridge Township | C14: =$B$5*T14 -> 1111.6058 | D14: =W14*$B$6 -> 3618.5803 | E14: =C14+D14 -> 4730.186 | F14: =E14/(M14/100) -> 280664.5 | G14: =0.8*H14 -> 104904.57 | H14: 131130.71 | I14: =H14-F14 -> -149533.79 | J14: =0.8*K14 -> 300420.04 | K14: 375525.05 | L14: =K14-F14 -> 94860.551 | M14: ='Tax Levies and EQ Tax Rates'!O21 -> 1.6853524 | N14: ='# and Assessed Value of Parcels'!G21/'# and Assessed Value of Parcels'!O21 -> 0.97122792 | O14: ='# and Assessed Value of Parcels'!H21/'# and Assessed Value of Parcels'!P21 -> 0.88589383 | P14: =(N14+O14)/2 -> 0.92856088 | Q14: ='Tax Levies and EQ Tax Rates'!I21 -> 37853002 | R14: =P14*Q14 -> 35148817 | S14: 66876 | T14: =R14/S14 -> 525.58193 | U14: ='Tax Levies and EQ Tax Rates'!C21 -> 106576433 | V14: 8070 | W14: =U14/V14 -> 13206.497
A15: Middlesex | B15: Middlesex Borough | C15: =$B$5*T15 -> 1756.7627 | D15: =W15*$B$6 -> 3552.7707 | E15: =C15+D15 -> 5309.5334 | F15: =E15/(M15/100) -> 225232.89 | G15: =0.8*H15 -> 244863.85 | H15: 306079.81 | I15: =H15-F15 -> 80846.921 | J15: =0.8*K15 -> 259906.27 | K15: 324882.84 | L15: =K15-F15 -> 99649.948 | M15: ='Tax Levies and EQ Tax Rates'!O22 -> 2.3573526 | N15: ='# and Assessed Value of Parcels'!G22/'# and Assessed Value of Parcels'!O22 -> 0.92460317 | O15: ='# and Assessed Value of Parcels'!H22/'# and Assessed Value of Parcels'!P22 -> 0.82398227 | P15: =(N15+O15)/2 -> 0.87429272 | Q15: ='Tax Levies and EQ Tax Rates'!I22 -> 13904913 | R15: =P15*Q15 -> 12156964 | S15: 14636 | T15: =R15/S15 -> 830.62065 | U15: ='Tax Levies and EQ Tax Rates'!C22 -> 26438319 | V15: 2039 | W15: =U15/V15 -> 12966.316
A16: Middlesex | B16: Sayreville Borough | C16: =$B$5*T16 -> 1503.1294 | D16: =W16*$B$6 -> 2814.4262 | E16: =C16+D16 -> 4317.5556 | F16: =E16/(M16/100) -> 219237.17 | G16: =0.8*H16 -> 166940.06 | H16: 208675.08 | I16: =H16-F16 -> -10562.089 | J16: =0.8*K16 -> 264763.81 | K16: 330954.76 | L16: =K16-F16 -> 111717.59 | M16: ='Tax Levies and EQ Tax Rates'!O23 -> 1.9693538 | N16: ='# and Assessed Value of Parcels'!G23/'# and Assessed Value of Parcels'!O23 -> 0.96279666 | O16: ='# and Assessed Value of Parcels'!H23/'# and Assessed Value of Parcels'!P23 -> 0.85286918 | P16: =(N16+O16)/2 -> 0.90783292 | Q16: ='Tax Levies and EQ Tax Rates'!I23 -> 35498458 | R16: =P16*Q16 -> 32226669 | S16: 45345 | T16: =R16/S16 -> 710.69949 | U16: ='Tax Levies and EQ Tax Rates'!C23 -> 67957093 | V16: 6616 | W16: =U16/V16 -> 10271.628
A17: Middlesex | B17: South River Borough | C17: =$B$5*T17 -> 1291.0269 | D17: =W17*$B$6 -> 2044.4739 | E17: =C17+D17 -> 3335.5008 | F17: =E17/(M17/100) -> 175844.67 | G17: =0.8*H17 -> 130775.73 | H17: 163469.67 | I17: =H17-F17 -> -12375.004 | J17: =0.8*K17 -> 234775.93 | K17: 293469.91 | L17: =K17-F17 -> 117625.24 | M17: ='Tax Levies and EQ Tax Rates'!O24 -> 1.896845 | N17: ='# and Assessed Value of Parcels'!G24/'# and Assessed Value of Parcels'!O24 -> 0.95376862 | O17: ='# and Assessed Value of Parcels'!H24/'# and Assessed Value of Parcels'!P24 -> 0.87694473 | P17: =(N17+O17)/2 -> 0.91535668 | Q17: ='Tax Levies and EQ Tax Rates'!I24 -> 10748447 | R17: =P17*Q17 -> 9838662.7 | S17: 16118 | T17: =R17/S17 -> 610.41461 | U17: ='Tax Levies and EQ Tax Rates'!C24 -> 18146571 | V17: 2432 | W17: =U17/V17 -> 7461.5835
A18: Middlesex | B18: Woodbridge Township | C18: =$B$5*T18 -> 1776.3675 | D18: =W18*$B$6 -> 3635.3999 | E18: =C18+D18 -> 5411.7674 | F18: =E18/(M18/100) -> 231325.91 | G18: =0.8*H18 -> 186271.74 | H18: 232839.67 | I18: =H18-F18 -> 1513.7576 | J18: =0.8*K18 -> 246095.6 | K18: 307619.51 | L18: =K18-F18 -> 76293.593 | M18: ='Tax Levies and EQ Tax Rates'!O25 -> 2.3394558 | N18: ='# and Assessed Value of Parcels'!G25/'# and Assessed Value of Parcels'!O25 -> 0.95527754 | O18: ='# and Assessed Value of Parcels'!H25/'# and Assessed Value of Parcels'!P25 -> 0.7164271 | P18: =(N18+O18)/2 -> 0.83585232 | Q18: ='Tax Levies and EQ Tax Rates'!I25 -> 1.0413965e+08 | R18: =P18*Q18 -> 87045366 | S18: 103639 | T18: =R18/S18 -> 839.89006 | U18: ='Tax Levies and EQ Tax Rates'!C25 -> 190553334 | V18: 14362 | W18: =U18/V18 -> 13267.883
A19: Monmouth | B19: Keansburg Borough | C19: =$B$5*T19 -> 2412.808 | D19: =W19*$B$6 -> 815.07011 | E19: =C19+D19 -> 3227.8781 | F19: =E19/(M19/100) -> 119672.86 | G19: =0.8*H19 -> 107775 | H19: 134718.75 | I19: =H19-F19 -> 15045.889 | J19: =0.8*K19 -> 147112.88 | K19: 183891.1 | L19: =K19-F19 -> 64218.242 | M19: ='Tax Levies and EQ Tax Rates'!O26 -> 2.6972516 | N19: ='# and Assessed Value of Parcels'!G26/'# and Assessed Value of Parcels'!O26 -> 0.96441281 | O19: ='# and Assessed Value of Parcels'!H26/'# and Assessed Value of Parcels'!P26 -> 0.88303144 | P19: =(N19+O19)/2 -> 0.92372213 | Q19: ='Tax Levies and EQ Tax Rates'!I26 -> 12047538 | R19: =P19*Q19 -> 11128578 | S19: 9755 | T19: =R19/S19 -> 1140.8076 | U19: ='Tax Levies and EQ Tax Rates'!C26 -> 5294981 | V19: 1780 | W19: =U19/V19 -> 2974.7084
A20: Monmouth | B20: Manalapan Township | C20: =$B$5*T20 -> 1222.3771 | D20: =W20*$B$6 -> 3746.9653 | E20: =C20+D20 -> 4969.3424 | F20: =E20/(M20/100) -> 306998.05 | G20: =0.8*H20 -> 233650 | H20: 292062.5 | I20: =H20-F20 -> -14935.555 | J20: =0.8*K20 -> 384389.9 | K20: 480487.37 | L20: =K20-F20 -> 173489.32 | M20: ='Tax Levies and EQ Tax Rates'!O27 -> 1.6186886 | N20: ='# and Assessed Value of Parcels'!G27/'# and Assessed Value of Parcels'!O27 -> 0.97272104 | O20: ='# and Assessed Value of Parcels'!H27/'# and Assessed Value of Parcels'!P27 -> 0.9220575 | P20: =(N20+O20)/2 -> 0.94738927 | Q20: ='Tax Levies and EQ Tax Rates'!I27 -> 24954149 | R20: =P20*Q20 -> 23641293 | S20: 40905 | T20: =R20/S20 -> 577.95608 | U20: ='Tax Levies and EQ Tax Rates'!C27 -> 66693248 | V20: 4877 | W20: =U20/V20 -> 13675.056
A21: Passaic | B21: Paterson City | C21: =$B$5*T21 -> 1610.9745 | D21: =W21*$B$6 -> 442.63072 | E21: =C21+D21 -> 2053.6052 | F21: =E21/(M21/100) -> 79476.474 | G21: =0.8*H21 -> 102163.3 | H21: 127704.12 | I21: =H21-F21 -> 48227.646 | J21: =0.8*K21 -> 207215.67 | K21: 259019.58 | L21: =K21-F21 -> 179543.11 | M21: ='Tax Levies and EQ Tax Rates'!O33 -> 2.5839159 | N21: ='# and Assessed Value of Parcels'!G33/'# and Assessed Value of Parcels'!O33 -> 0.82159481 | O21: ='# and Assessed Value of Parcels'!H33/'# and Assessed Value of Parcels'!P33 -> 0.65337602 | P21: =(N21+O21)/2 -> 0.73748542 | Q21: ='Tax Levies and EQ Tax Rates'!I33 -> 1.6497449e+08 | R21: =P21*Q21 -> 1.2166628e+08 | S21: 159732 | T21: =R21/S21 -> 761.69008 | U21: ='Tax Levies and EQ Tax Rates'!C33 -> 50970381 | V21: 31552 | W21: =U21/V21 -> 1615.4406
A22: Passaic | B22: Pompton Lakes Borough | C22: =$B$5*T22 -> 1878.7345 | D22: =W22*$B$6 -> 3630.6429 | E22: =C22+D22 -> 5509.3774 | F22: =E22/(M22/100) -> 193247.93 | G22: =0.8*H22 -> 222382.41 | H22: 277978.02 | I22: =H22-F22 -> 84730.082 | J22: =0.8*K22 -> 237607.77 | K22: 297009.71 | L22: =K22-F22 -> 103761.78 | M22: ='Tax Levies and EQ Tax Rates'!O34 -> 2.8509373 | N22: ='# and Assessed Value of Parcels'!G34/'# and Assessed Value of Parcels'!O34 -> 0.95521999 | O22: ='# and Assessed Value of Parcels'!H34/'# and Assessed Value of Parcels'!P34 -> 0.87552226 | P22: =(N22+O22)/2 -> 0.91537113 | Q22: ='Tax Levies and EQ Tax Rates'!I34 -> 10797816 | R22: =P22*Q22 -> 9884009 | S22: 11127 | T22: =R22/S22 -> 888.29056 | U22: ='Tax Levies and EQ Tax Rates'!C34 -> 25639759 | V22: 1935 | W22: =U22/V22 -> 13250.521
A23: Passaic | B23: Wayne Township | C23: =$B$5*T23 -> 2123.5472 | D23: =W23*$B$6 -> 5452.8924 | E23: =C23+D23 -> 7576.4396 | F23: =E23/(M23/100) -> 372993.26 | G23: =0.8*H23 -> 122655.5 | H23: 153319.37 | I23: =H23-F23 -> -219673.88 | J23: =0.8*K23 -> 382276.91 | K23: 477846.14 | L23: =K23-F23 -> 104852.88 | M23: ='Tax Levies and EQ Tax Rates'!O35 -> 2.0312538 | N23: ='# and Assessed Value of Parcels'!G35/'# and Assessed Value of Parcels'!O35 -> 0.95973428 | O23: ='# and Assessed Value of Parcels'!H35/'# and Assessed Value of Parcels'!P35 -> 0.74630979 | P23: =(N23+O23)/2 -> 0.85302204 | Q23: ='Tax Levies and EQ Tax Rates'!I35 -> 64546529 | R23: =P23*Q23 -> 55059612 | S23: 54838 | T23: =R23/S23 -> 1004.0412 | U23: ='Tax Levies and EQ Tax Rates'!C35 -> 156760706 | V23: 7877 | W23: =U23/V23 -> 19901.067
A24: Somerset | B24: Franklin Township | C24: =$B$5*T24 -> 1161.583 | D24: =W24*$B$6 -> 4893.3904 | E24: =C24+D24 -> 6054.9734 | F24: =E24/(M24/100) -> 373034.86 | G24: =0.8*H24 -> 113307.6 | H24: 141634.5 | I24: =H24-F24 -> -231400.36 | J24: =0.8*K24 -> 295587.15 | K24: 369483.93 | L24: =K24-F24 -> -3550.9304 | M24: ='Tax Levies and EQ Tax Rates'!O38 -> 1.6231655 | N24: ='# and Assessed Value of Parcels'!G38/'# and Assessed Value of Parcels'!O38 -> 0.96646123 | O24: ='# and Assessed Value of Parcels'!H38/'# and Assessed Value of Parcels'!P38 -> 0.74002785 | P24: =(N24+O24)/2 -> 0.85324454 | Q24: ='Tax Levies and EQ Tax Rates'!I38 -> 44004169 | R24: =P24*Q24 -> 37546317 | S24: 68364 | T24: =R24/S24 -> 549.21182 | U24: ='Tax Levies and EQ Tax Rates'!C38 -> 151105752 | V24: 8461 | W24: =U24/V24 -> 17859.089
A25: Somerset | B25: Manville Borough | C25: =$B$5*T25 -> 1672.2136 | D25: =W25*$B$6 -> 2593.5601 | E25: =C25+D25 -> 4265.7737 | F25: =E25/(M25/100) -> 161684.12 | G25: =0.8*H25 -> 155618.35 | H25: 194522.93 | I25: =H25-F25 -> 32838.817 | J25: =0.8*K25 -> 202643.08 | K25: 253303.85 | L25: =K25-F25 -> 91619.739 | M25: ='Tax Levies and EQ Tax Rates'!O39 -> 2.6383382 | N25: ='# and Assessed Value of Parcels'!G39/'# and Assessed Value of Parcels'!O39 -> 0.95111773 | O25: ='# and Assessed Value of Parcels'!H39/'# and Assessed Value of Parcels'!P39 -> 0.86385135 | P25: =(N25+O25)/2 -> 0.90748454 | Q25: ='Tax Levies and EQ Tax Rates'!I39 -> 9542787.2 | R25: =P25*Q25 -> 8659931.8 | S25: 10953 | T25: =R25/S25 -> 790.64474 | U25: ='Tax Levies and EQ Tax Rates'!C39 -> 15656016 | V25: 1654 | W25: =U25/V25 -> 9465.5478
A26: Union | B26: Linden City | C26: =$B$5*T26 -> 2176.713 | D26: =W26*$B$6 -> 3920.8932 | E26: =C26+D26 -> 6097.6062 | F26: =E26/(M26/100) -> 262670.28 | G26: =0.8*H26 -> 166940.58 | H26: 208675.72 | I26: =H26-F26 -> -53994.558 | J26: =0.8*K26 -> 261338.99 | K26: 326673.73 | L26: =K26-F26 -> 64003.456 | M26: ='Tax Levies and EQ Tax Rates'!O40 -> 2.3213918 | N26: ='# and Assessed Value of Parcels'!G40/'# and Assessed Value of Parcels'!O40 -> 0.90298507 | O26: ='# and Assessed Value of Parcels'!H40/'# and Assessed Value of Parcels'!P40 -> 0.53546516 | P26: =(N26+O26)/2 -> 0.71922512 | Q26: ='Tax Levies and EQ Tax Rates'!I40 -> 62587105 | R26: =P26*Q26 -> 45014218 | S26: 43738 | T26: =R26/S26 -> 1029.1787 | U26: ='Tax Levies and EQ Tax Rates'!C40 -> 94215916 | V26: 6584 | W26: =U26/V26 -> 14309.829
A27: Union | B27: Rahway City | C27: =$B$5*T27 -> 2340.8948 | D27: =W27*$B$6 -> 3006.7261 | E27: =C27+D27 -> 5347.6209 | F27: =E27/(M27/100) -> 185330.49 | G27: =0.8*H27 -> 211443.65 | H27: 264304.56 | I27: =H27-F27 -> 78974.069 | J27: =0.8*K27 -> 217291.86 | K27: 271614.82 | L27: =K27-F27 -> 86284.335 | M27: ='Tax Levies and EQ Tax Rates'!O41 -> 2.8854512 | N27: ='# and Assessed Value of Parcels'!G41/'# and Assessed Value of Parcels'!O41 -> 0.94367816 | O27: ='# and Assessed Value of Parcels'!H41/'# and Assessed Value of Parcels'!P41 -> 0.73460248 | P27: =(N27+O27)/2 -> 0.83914032 | Q27: ='Tax Levies and EQ Tax Rates'!I41 -> 38983658 | R27: =P27*Q27 -> 32712759 | S27: 29556 | T27: =R27/S27 -> 1106.806 | U27: ='Tax Levies and EQ Tax Rates'!C41 -> 45342308 | V27: 4132 | W27: =U27/V27 -> 10973.453
C28: =AVERAGE(C10:C27) -> 1721.3219 | D28: =AVERAGE(D10:D27) -> 3007.6024 | E28: =AVERAGE(E10:E27) -> 4728.9242 | F28: =AVERAGE(F10:F27) -> 212399.38 | G28: =AVERAGE(G10:G27) -> 162835.11 | H28: =AVERAGE(H10:H27) -> 203543.88 | I28: =AVERAGE(I10:I27) -> -8855.4995 | J28: =AVERAGE(J10:J27) -> 251741.36 | ... W28: =AVERAGE(W10:W27) -> 10976.651

Sheet  (SFA 2.5 Bed) Muni Break Even
A1: 2020 Municipal Break Even Analysis for Single Family Attached (2.5 Bedroom) in Selected NJ Communities
A3: Single Family Attached (2.5 Bedroom) Multipliers
A4: Category | B4: Multiplier
A5: Household Size | B5: 2.507
A6: School Age Children | B6: 0.419
A8: Location | C8: 2.5 Bedroom Single Family Attached Municipal "Break Even Analysis" | E8: Fiscal Analysis | K8: Municipal Fiscal Impact Analysis
A9: County | B9: Municipality | C9: Municipal Tax Supported Cost | D9: Market Value "Break Even" | E9: Adjusted Average Real (2020) Market Value of Buyout Properties | F9: Average Real (2020) Market Value of Buyout Properties | G9: Fiscal Surplus or Deficit (Based on Average Buyout Market Value) | H9: Adjusted Average 2020 Residential Value in Buyout Community | I9: Average 2020 Residential Value in Buyout Community | J9: Fiscal Surplus or Deficit (Based on Average Residential Value) | K9: Municipal Property Tax Rate | L9: Percent of Total Parcels that are Residential | M9: Percent of Total Assessed Value that is Residential | N9: Average of Residential Parcels % and Assessed Value % | O9: Total Municipal Property Tax Levy | P9: Estimated Residential Share of Total Municipal Property Tax Levy | Q9: 2020 Municipal Population | R9: 2020 Municipal Property Tax Supported Cost Per Person
A10: Atlantic | B10: Pleasantville City | C10: $2,391.21 | D10: =C10/(K10/100) -> 78043.645 | E10: =0.85*F10 -> 51199.75 | F10: 60235 | G10: =F10-D10 -> -17808.645 | H10: =0.85*I10 -> 83608.55 | I10: 98363 | J10: =I10-D10 -> 20319.355 | K10: 3.0639394 | L10: ='# and Assessed Value of Parcels'!G5/'# and Assessed Value of Parcels'!O5 -> 0.92172813 | M10: ='# and Assessed Value of Parcels'!H5/'# and Assessed Value of Parcels'!P5 -> 0.73101366 | N10: =(L10+M10)/2 -> 0.8263709 | O10: ='Tax Levies and EQ Tax Rates'!I5 -> 23810385 | P10: =N10*O10 -> 19676209 | Q10: 20629
A11: Bergen | B11: Hillsdale Borough | C11: =$B$5*R11 -> 2372.9204 | D11: =C11/(K11/100) -> 442543.77 | E11: =0.85*F11 -> 188604.8 | F11: 221888 | G11: =F11-D11 -> -220655.77 | H11: =0.85*I11 -> 445578.5 | I11: 524210 | J11: =I11-D11 -> 81666.226 | K11: 0.53620016 | L11: ='# and Assessed Value of Parcels'!G6/'# and Assessed Value of Parcels'!O6 -> 0.96785506 | M11: ='# and Assessed Value of Parcels'!H6/'# and Assessed Value of Parcels'!P6 -> 0.93507138 | N11: =(L11+M11)/2 -> 0.95146322 | O11: ='Tax Levies and EQ Tax Rates'!I6 -> 10090281 | P11: =N11*O11 -> 9600531.2 | Q11: 10143 | R11: =P11/Q11 -> 946.51792
A12: Bergen | B12: New Milford Borough | C12: =$B$5*R12 -> 2460.883 | D12: =C12/(K12/100) -> 294866.54 | E12: =0.85*F12 -> 317665.4 | F12: 373724 | G12: =F12-D12 -> 78857.461 | H12: =0.85*I12 -> 362854.8 | I12: 426888 | J12: =I12-D12 -> 132021.46 | K12: 0.83457519 | L12: ='# and Assessed Value of Parcels'!G7/'# and Assessed Value of Parcels'!O7 -> 0.98144233 | M12: ='# and Assessed Value of Parcels'!H7/'# and Assessed Value of Parcels'!P7 -> 0.94433259 | N12: =(L12+M12)/2 -> 0.96288746 | O12: ='Tax Levies and EQ Tax Rates'!I7 -> 17251960 | P12: =N12*O12 -> 16611696 | Q12: 16923 | R12: =P12/Q12 -> 981.6047
A13: Bergen | B13: Oakland Borough | C13: =$B$5*R13 -> 2803.413 | D13: =C13/(K13/100) -> 464701.75 | E13: =0.85*F13 -> 311247.05 | F13: 366173 | G13: =F13-D13 -> -98528.748 | H13: =0.85*I13 -> 423970.65 | I13: 498789 | J13: =I13-D13 -> 34087.252 | K13: 0.60327146 | L13: ='# and Assessed Value of Parcels'!G8/'# and Assessed Value of Parcels'!O8 -> 0.9566732 | M13: ='# and Assessed Value of Parcels'!H8/'# and Assessed Value of Parcels'!P8 -> 0.84635298 | N13: =(L13+M13)/2 -> 0.90151309 | O13: ='Tax Levies and EQ Tax Rates'!I8 -> 15812581 | P13: =N13*O13 -> 14255249 | Q13: 12748 | R13: =P13/Q13 -> 1118.2342
A14: Bergen | B14: Westwood Borough | C14: =$B$5*R14 -> 2919.4016 | D14: =C14/(K14/100) -> 397930.46 | E14: =0.85*F14 -> 398356.75 | F14: 468655 | G14: =F14-D14 -> 70724.541 | H14: =0.85*I14 -> 390546.95 | I14: 459467 | J14: =I14-D14 -> 61536.541 | K14: 0.73364618 | L14: ='# and Assessed Value of Parcels'!G9/'# and Assessed Value of Parcels'!O9 -> 0.91940211 | M14: ='# and Assessed Value of Parcels'!H9/'# and Assessed Value of Parcels'!P9 -> 0.75552222 | N14: =(L14+M14)/2 -> 0.83746217 | O14: ='Tax Levies and EQ Tax Rates'!I9 -> 15687741 | P14: =N14*O14 -> 13137890 | Q14: 11282 | R14: =P14/Q14 -> 1164.5
A15: Burlington | B15: Lumberton Township | C15: =$B$5*R15 -> 979.8757 | D15: =C15/(K15/100) -> 251144.78 | E15: =0.85*F15 -> 396433.34 | F15: 466392.16 | G15: =F15-D15 -> 215247.39 | H15: =0.85*I15 -> 260810.6 | I15: 306836 | J15: =I15-D15 -> 55691.223 | K15: 0.39016368 | L15: ='# and Assessed Value of Parcels'!G10/'# and Assessed Value of Parcels'!O10 -> 0.96040113 | M15: ='# and Assessed Value of Parcels'!H10/'# and Assessed Value of Parcels'!P10 -> 0.85301722 | N15: =(L15+M15)/2 -> 0.90670917 | O15: ='Tax Levies and EQ Tax Rates'!I10 -> 5518999.9 | P15: =N15*O15 -> 5004127.9 | Q15: 12803 | R15: =P15/Q15 -> 390.85588
A16: Burlington | B16: Medford Township | C16: =$B$5*R16 -> 1254.3186 | D16: =C16/(K16/100) -> 332213.92 | E16: =0.85*F16 -> 92946.933 | F16: 109349.33 | G16: =F16-D16 -> -222864.59 | H16: =0.85*I16 -> 315166.4 | I16: 370784 | J16: =I16-D16 -> 38570.078 | K16: 0.37756351 | L16: ='# and Assessed Value of Parcels'!G11/'# and Assessed Value of Parcels'!O11 -> 0.95851299 | M16: ='# and Assessed Value of Parcels'!H11/'# and Assessed Value of Parcels'!P11 -> 0.91282275 | N16: =(L16+M16)/2 -> 0.93566787 | O16: ='Tax Levies and EQ Tax Rates'!I11 -> 13099198 | P16: =N16*O16 -> 12256498 | Q16: 24497 | R16: =P16/Q16 -> 500.32651
A17: Burlington | B17: Pemberton Township | C17: =$B$5*R17 -> 1363.5614 | D17: =C17/(K17/100) -> 134498.29 | E17: =0.85*F17 -> 79820.738 | F17: 93906.75 | G17: =F17-D17 -> -40591.542 | H17: =0.85*I17 -> 141365.2 | I17: 166312 | J17: =I17-D17 -> 31813.708 | K17: 1.0138132 | L17: ='# and Assessed Value of Parcels'!G12/'# and Assessed Value of Parcels'!O12 -> 0.98128309 | M17: ='# and Assessed Value of Parcels'!H12/'# and Assessed Value of Parcels'!P12 -> 0.9332896 | N17: =(L17+M17)/2 -> 0.95728635 | O17: ='Tax Levies and EQ Tax Rates'!I12 -> 15285485 | P17: =N17*O17 -> 14632586 | Q17: 26903 | R17: =P17/Q17 -> 543.90165
A18: Burlington | B18: Southampton Township | C18: =$B$5*R18 -> 965.62616 | D18: =C18/(K18/100) -> 284629.24 | E18: =0.85*F18 -> 111745.29 | F18: 131465.05 | G18: =F18-D18 -> -153164.19 | H18: =0.85*I18 -> 202753.9 | I18: 238534 | J18: =I18-D18 -> -46095.243 | K18: 0.33925754 | L18: ='# and Assessed Value of Parcels'!G13/'# and Assessed Value of Parcels'!O13 -> 0.96051204 | M18: ='# and Assessed Value of Parcels'!H13/'# and Assessed Value of Parcels'!P13 -> 0.90183161 | N18: =(L18+M18)/2 -> 0.93117183 | O18: ='Tax Levies and EQ Tax Rates'!I13 -> 4267546.8 | P18: =N18*O18 -> 3973819.4 | Q18: 10317 | R18: =P18/Q18 -> 385.17198
A19: Cumberland | B19: Downe Township | C19: =$B$5*R19 -> 855.96648 | D19: =C19/(K19/100) -> 224885.38 | E19: =0.85*F19 -> 83827.291 | F19: 98620.342 | G19: =F19-D19 -> -126265.03 | H19: =0.85*I19 -> 100715.65 | I19: 118489 | J19: =I19-D19 -> -106396.38 | K19: 0.38062345 | L19: ='# and Assessed Value of Parcels'!G14/'# and Assessed Value of Parcels'!O14 -> 0.94935452 | M19: ='# and Assessed Value of Parcels'!H14/'# and Assessed Value of Parcels'!P14 -> 0.95309492 | N19: =(L19+M19)/2 -> 0.95122472 | O19: ='Tax Levies and EQ Tax Rates'!I14 -> 502154.1 | P19: =N19*O19 -> 477661.39 | Q19: 1399 | R19: =P19/Q19 -> 341.43059
A20: Cumberland | B20: Fairfield Township | C20: =$B$5*R20 -> 574.61714 | D20: =C20/(K20/100) -> 117556.41 | E20: =0.85*F20 -> 73999.009 | F20: 87057.657 | G20: =F20-D20 -> -30498.749 | H20: =0.85*I20 -> 121416.55 | I20: 142843 | J20: =I20-D20 -> 25286.594 | K20: 0.48880122 | L20: ='# and Assessed Value of Parcels'!G15/'# and Assessed Value of Parcels'!O15 -> 0.95576808 | M20: ='# and Assessed Value of Parcels'!H15/'# and Assessed Value of Parcels'!P15 -> 0.9003797 | N20: =(L20+M20)/2 -> 0.92807389 | O20: ='Tax Levies and EQ Tax Rates'!I15 -> 1369687.7 | P20: =N20*O20 -> 1271171.4 | Q20: 5546 | R20: =P20/Q20 -> 229.20508
A21: Cumberland | B21: Lawrence Township | C21: =$B$5*R21 -> 948.10158 | D21: =C21/(K21/100) -> 173887.7 | E21: =0.85*F21 -> 30672.25 | F21: 36085 | G21: =F21-D21 -> -137802.7 | H21: =0.85*I21 -> 140316.3 | I21: 165078 | J21: =I21-D21 -> -8809.7031 | K21: 0.54523786 | L21: ='# and Assessed Value of Parcels'!G16/'# and Assessed Value of Parcels'!O16 -> 0.96660808 | M21: ='# and Assessed Value of Parcels'!H16/'# and Assessed Value of Parcels'!P16 -> 0.93631576 | N21: =(L21+M21)/2 -> 0.95146192 | O21: ='Tax Levies and EQ Tax Rates'!I16 -> 1227003.4 | P21: =N21*O21 -> 1167447 | Q21: 3087 | R21: =P21/Q21 -> 378.18173
A22: Essex | B22: Fairfield Township | C22: =$B$5*R22 -> 3114.3811 | D22: =C22/(K22/100) -> 716320.64 | E22: =0.85*F22 -> 186735.65 | F22: 219689 | G22: =F22-D22 -> -496631.64 | H22: =0.85*I22 -> 512735.68 | I22: 603218.44 | J22: =I22-D22 -> -113102.19 | K22: 0.43477472 | L22: ='[1]# and Assessed Value of Parcels'!G17/'[1]# and Assessed Value of Parcels'!O17 -> 0.78907204 | M22: ='[1]# and Assessed Value of Parcels'!H17/'[1]# and Assessed Value of Parcels'!P17 -> 0.44402102 | N22: =(L22+M22)/2 -> 0.61654653 | O22: ='[1]Tax Levies and EQ Tax Rates'!I17 -> 15861222 | P22: =N22*O22 -> 9779181.4 | Q22: 7872 | R22: =P22/Q22 -> 1242.2741
A23: Essex | B23: Newark City | C23: =$B$5*R23 -> 1405.7625 | D23: =C23/(K23/100) -> 83506.81 | E23: =0.85*F23 -> 139850.22 | F23: 164529.67 | G23: =F23-D23 -> 81022.856 | H23: =0.85*I23 -> 175809.75 | I23: 206835 | J23: =I23-D23 -> 123328.19 | K23: 1.6834106 | L23: ='# and Assessed Value of Parcels'!G18/'# and Assessed Value of Parcels'!O18 -> 0.84162884 | M23: ='# and Assessed Value of Parcels'!H18/'# and Assessed Value of Parcels'!P18 -> 0.54365223 | N23: =(L23+M23)/2 -> 0.69264054 | O23: ='Tax Levies and EQ Tax Rates'!I18 -> 252218004 | P23: =N23*O23 -> 1.7469641e+08 | Q23: 311549 | R23: =P23/Q23 -> 560.73495
A24: Hunterdon | B24: Lebanon Township | C24: =$B$5*R24 -> 1074.1716 | D24: =C24/(K24/100) -> 362477.48 | E24: =0.85*F24 -> 51587.775 | F24: 60691.5 | G24: =F24-D24 -> -301785.98 | H24: =0.85*I24 -> 322852.95 | I24: 379827 | J24: =I24-D24 -> 17349.525 | K24: 0.29634161 | L24: ='# and Assessed Value of Parcels'!G19/'# and Assessed Value of Parcels'!O19 -> 0.96383866 | M24: ='# and Assessed Value of Parcels'!H19/'# and Assessed Value of Parcels'!P19 -> 0.93906348 | N24: =(L24+M24)/2 -> 0.95145107 | O24: ='Tax Levies and EQ Tax Rates'!I19 -> 2789807.1 | P24: =N24*O24 -> 2654365 | Q24: 6195 | R24: =P24/Q24 -> 428.46893
A25: Middlesex | B25: East Brunswick Township | C25: =$B$5*R25 -> 1974.417 | D25: =C25/(K25/100) -> 341385.11 | E25: =0.85*F25 -> 193957.96 | F25: 228185.83 | G25: =F25-D25 -> -113199.27 | H25: =0.85*I25 -> 323265.2 | I25: 380312 | J25: =I25-D25 -> 38926.892 | K25: 0.57835476 | L25: ='# and Assessed Value of Parcels'!G20/'# and Assessed Value of Parcels'!O20 -> 0.95667524 | M25: ='# and Assessed Value of Parcels'!H20/'# and Assessed Value of Parcels'!P20 -> 0.81220548 | N25: =(L25+M25)/2 -> 0.88444036 | O25: ='Tax Levies and EQ Tax Rates'!I20 -> 44269380 | P25: =N25*O25 -> 39153626 | Q25: 49715 | R25: =P25/Q25 -> 787.56163
A26: Middlesex | B26: Old Bridge Township | C26: =$B$5*R26 -> 1317.6339 | D26: =C26/(K26/100) -> 298304.23 | E26: =0.85*F26 -> 111461.11 | F26: 131130.71 | G26: =F26-D26 -> -167173.51 | H26: =0.85*I26 -> 319196.25 | I26: 375525 | J26: =I26-D26 -> 77220.774 | K26: 0.44170809 | L26: ='# and Assessed Value of Parcels'!G21/'# and Assessed Value of Parcels'!O21 -> 0.97122792 | M26: ='# and Assessed Value of Parcels'!H21/'# and Assessed Value of Parcels'!P21 -> 0.88589383 | N26: =(L26+M26)/2 -> 0.92856088 | O26: ='Tax Levies and EQ Tax Rates'!I21 -> 37853002 | P26: =N26*O26 -> 35148817 | Q26: 66876 | R26: =P26/Q26 -> 525.58193
A27: Middlesex | B27: Middlesex Borough | C27: =$B$5*R27 -> 2082.366 | D27: =C27/(K27/100) -> 256291.93 | E27: =0.85*F27 -> 260167.84 | F27: 306079.81 | G27: =F27-D27 -> 49787.878 | H27: =0.85*I27 -> 276150.55 | I27: 324883 | J27: =I27-D27 -> 68591.066 | K27: 0.81249766 | L27: ='# and Assessed Value of Parcels'!G22/'# and Assessed Value of Parcels'!O22 -> 0.92460317 | M27: ='# and Assessed Value of Parcels'!H22/'# and Assessed Value of Parcels'!P22 -> 0.82398227 | N27: =(L27+M27)/2 -> 0.87429272 | O27: ='Tax Levies and EQ Tax Rates'!I22 -> 13904913 | P27: =N27*O27 -> 12156964 | Q27: 14636 | R27: =P27/Q27 -> 830.62065
A28: Middlesex | B28: Sayreville Borough | C28: =$B$5*R28 -> 1781.7236 | D28: =C28/(K28/100) -> 263670.11 | E28: =0.85*F28 -> 177373.82 | F28: 208675.08 | G28: =F28-D28 -> -54995.03 | H28: =0.85*I28 -> 281311.75 | I28: 330955 | J28: =I28-D28 -> 67284.89 | K28: 0.67573971 | L28: ='# and Assessed Value of Parcels'!G23/'# and Assessed Value of Parcels'!O23 -> 0.96279666 | M28: ='# and Assessed Value of Parcels'!H23/'# and Assessed Value of Parcels'!P23 -> 0.85286918 | N28: =(L28+M28)/2 -> 0.90783292 | O28: ='Tax Levies and EQ Tax Rates'!I23 -> 35498458 | P28: =N28*O28 -> 32226669 | Q28: 45345 | R28: =P28/Q28 -> 710.69949
A29: Middlesex | B29: South River Borough | C29: =$B$5*R29 -> 1530.3094 | D29: =C29/(K29/100) -> 216882.58 | E29: =0.85*F29 -> 138949.22 | F29: 163469.67 | G29: =F29-D29 -> -53412.912 | H29: =0.85*I29 -> 249449.5 | I29: 293470 | J29: =I29-D29 -> 76587.421 | K29: 0.70559352 | L29: ='# and Assessed Value of Parcels'!G24/'# and Assessed Value of Parcels'!O24 -> 0.95376862 | M29: ='# and Assessed Value of Parcels'!H24/'# and Assessed Value of Parcels'!P24 -> 0.87694473 | N29: =(L29+M29)/2 -> 0.91535668 | O29: ='Tax Levies and EQ Tax Rates'!I24 -> 10748447 | P29: =N29*O29 -> 9838662.7 | Q29: 16118 | R29: =P29/Q29 -> 610.41461
A30: Middlesex | B30: Woodbridge Township | C30: =$B$5*R30 -> 2105.6044 | D30: =C30/(K30/100) -> 254692.19 | E30: =0.85*F30 -> 197913.72 | F30: 232839.67 | G30: =F30-D30 -> -21852.52 | H30: =0.85*I30 -> 261477 | I30: 307620 | J30: =I30-D30 -> 52927.81 | K30: 0.82672514 | L30: ='# and Assessed Value of Parcels'!G25/'# and Assessed Value of Parcels'!O25 -> 0.95527754 | M30: ='# and Assessed Value of Parcels'!H25/'# and Assessed Value of Parcels'!P25 -> 0.7164271 | N30: =(L30+M30)/2 -> 0.83585232 | O30: ='Tax Levies and EQ Tax Rates'!I25 -> 1.0413965e+08 | P30: =N30*O30 -> 87045366 | Q30: 103639 | R30: =P30/Q30 -> 839.89006
A31: Monmouth | B31: Keansburg Borough | C31: =$B$5*R31 -> 2860.0046 | D31: =C31/(K31/100) -> 152636.76 | E31: =0.85*F31 -> 114510.94 | F31: 134718.75 | G31: =F31-D31 -> -17918.012 | H31: =0.85*I31 -> 156307.35 | I31: 183891 | J31: =I31-D31 -> 31254.238 | K31: 1.8737325 | L31: ='# and Assessed Value of Parcels'!G26/'# and Assessed Value of Parcels'!O26 -> 0.96441281 | M31: ='# and Assessed Value of Parcels'!H26/'# and Assessed Value of Parcels'!P26 -> 0.88303144 | N31: =(L31+M31)/2 -> 0.92372213 | O31: ='Tax Levies and EQ Tax Rates'!I26 -> 12047538 | P31: =N31*O31 -> 11128578 | Q31: 9755 | R31: =P31/Q31 -> 1140.8076
A32: Monmouth | B32: Manalapan Township | C32: =$B$5*R32 -> 1448.9359 | D32: =C32/(K32/100) -> 434175.36 | E32: =0.85*F32 -> 248253.12 | F32: 292062.5 | G32: =F32-D32 -> -142112.86 | H32: =0.85*I32 -> 408413.95 | I32: 480487 | J32: =I32-D32 -> 46311.638 | K32: 0.33372135 | L32: ='# and Assessed Value of Parcels'!G27/'# and Assessed Value of Parcels'!O27 -> 0.97272104 | M32: ='# and Assessed Value of Parcels'!H27/'# and Assessed Value of Parcels'!P27 -> 0.9220575 | N32: =(L32+M32)/2 -> 0.94738927 | O32: ='Tax Levies and EQ Tax Rates'!I27 -> 24954149 | P32: =N32*O32 -> 23641293 | Q32: 40905 | R32: =P32/Q32 -> 577.95608
A33: Monmouth | B33: Ocean Township | C33: =$B$5*R33 -> 1904.87 | D33: =C33/(K33/100) -> 470665.99 | E33: =0.85*F33 -> 764998.98 | F33: 899998.8 | G33: =F33-D33 -> 429332.81 | H33: =0.85*I33 -> 460710.2 | I33: 542012 | J33: =I33-D33 -> 71346.01 | K33: 0.404718 | L33: ='# and Assessed Value of Parcels'!G28/'# and Assessed Value of Parcels'!O28 -> 0.95530169 | M33: ='# and Assessed Value of Parcels'!H28/'# and Assessed Value of Parcels'!P28 -> 0.88451081 | N33: =(L33+M33)/2 -> 0.91990625 | O33: ='Tax Levies and EQ Tax Rates'!I28 -> 22856408 | P33: =N33*O33 -> 21025753 | Q33: 27672 | R33: =P33/Q33 -> 759.82049
A34: Monmouth | B34: Sea Bright Borough | C34: =$B$5*R34 -> 7076.5079 | D34: =C34/(K34/100) -> 1377780.3 | E34: =0.85*F34 -> 1223129.6 | F34: 1438976 | G34: =F34-D34 -> 61195.697 | H34: =0.85*I34 -> 592720.3 | I34: 697318 | J34: =I34-D34 -> -680462.3 | K34: 0.51361656 | L34: ='# and Assessed Value of Parcels'!G29/'# and Assessed Value of Parcels'!O29 -> 0.9358047 | M34: ='# and Assessed Value of Parcels'!H29/'# and Assessed Value of Parcels'!P29 -> 0.81959946 | N34: =(L34+M34)/2 -> 0.87770208 | O34: ='Tax Levies and EQ Tax Rates'!I29 -> 4660000 | P34: =N34*O34 -> 4090091.7 | Q34: 1449 | R34: =P34/Q34 -> 2822.6996
... A47: Warren | B47: Harmony Township | C47: =$B$5*R47 -> 1130.4176 | D47: =C47/(K47/100) -> 393980.55 | E47: =0.85*F47 -> 97052.324 | F47: 114179.2 | G47: =F47-D47 -> -279801.34 | H47: =0.85*I47 -> 204157.25 | I47: 240185 | J47: =I47-D47 -> -153795.55 | K47: 0.28692219 | L47: ='# and Assessed Value of Parcels'!G42/'# and Assessed Value of Parcels'!O42 -> 0.95134062 | M47: ='# and Assessed Value of Parcels'!H42/'# and Assessed Value of Parcels'!P42 -> 0.44542234 | N47: =(L47+M47)/2 -> 0.69838148 | O47: ='Tax Levies and EQ Tax Rates'!I42 -> 1616042.3 | P47: =N47*O47 -> 1128614 | Q47: 2503 | R47: =P47/Q47 -> 450.90451
C48: =AVERAGE(C10:C47) -> 2008.6221 | D48: =AVERAGE(D10:D47) -> 327228.16 | E48: =AVERAGE(E10:E47) -> 211253.5 | F48: =AVERAGE(F10:F47) -> 248533.53 | G48: =AVERAGE(G10:G47) -> -78694.628 | H48: =AVERAGE(H10:H47) -> 293263.05 | I48: =AVERAGE(I10:I47) -> 345015.35 | J48: =AVERAGE(J10:J47) -> 17787.195 | ... R48: =AVERAGE(R10:R47) -> 801.20546

Sheet Adjusted (SFA 2.0 Bed) Muni Bre
A1: 2020 Municipal Break Even Analysis for Single Family Attached (2.0 Bedroom) in Selected NJ Communities
A3: Single Family Attached (2.0 Bedroom) Multipliers
A4: Category | B4: Multiplier
A5: Household Size | B5: 2.115
A6: School Age Children | B6: 0.274
A8: Location | C8: 2.5 Bedroom Single Family Attached Municipal "Break Even Analysis" | E8: Fiscal Analysis | K8: Municipal Fiscal Impact Analysis
A9: County | B9: Municipality | C9: Municipal Tax Supported Cost | D9: Market Value "Break Even" | E9: Adjusted Real (2020) Market Value of Buyout Properties | F9: Average Real (2020) Market Value of Buyout Properties | G9: Fiscal Surplus or Deficit (Based on Average Buyout Market Value) | H9: Adjusted Average 2020 Residential Value in Buyout Community | I9: Average 2020 Residential Value in Buyout Community | J9: Fiscal Surplus or Deficit (Based on Average Residential Value) | K9: Municipal Property Tax Rate | L9: Percent of Total Parcels that are Residential | M9: Percent of Total Assessed Value that is Residential | N9: Average of Residential Parcels % and Assessed Value % | O9: Total Municipal Property Tax Levy | P9: Estimated Residential Share of Total Municipal Property Tax Levy | Q9: 2020 Municipal Population | R9: 2020 Municipal Property Tax Supported Cost Per Person
A10: Atlantic | B10: Pleasantville City | C10: $2,391.21 | D10: =C10/(K10/100) -> 78043.645 | E10: =0.9*F10 -> 54211.5 | F10: 60235 | G10: =F10-D10 -> -17808.645 | H10: =0.9*I10 -> 88526.7 | I10: 98363 | J10: =I10-D10 -> 20319.355 | K10: 3.0639394 | L10: ='# and Assessed Value of Parcels'!G5/'# and Assessed Value of Parcels'!O5 -> 0.92172813 | M10: ='# and Assessed Value of Parcels'!H5/'# and Assessed Value of Parcels'!P5 -> 0.73101366 | N10: =(L10+M10)/2 -> 0.8263709 | O10: ='Tax Levies and EQ Tax Rates'!I5 -> 23810385 | P10: =N10*O10 -> 19676209 | Q10: 20629
A11: Bergen | B11: Hillsdale Borough | C11: =$B$5*R11 -> 2001.8854 | D11: =C11/(K11/100) -> 373346.66 | E11: =0.9*F11 -> 199699.2 | F11: 221888 | G11: =F11-D11 -> -151458.66 | H11: =0.9*I11 -> 471789 | I11: 524210 | J11: =I11-D11 -> 150863.34 | K11: 0.53620016 | L11: ='# and Assessed Value of Parcels'!G6/'# and Assessed Value of Parcels'!O6 -> 0.96785506 | M11: ='# and Assessed Value of Parcels'!H6/'# and Assessed Value of Parcels'!P6 -> 0.93507138 | N11: =(L11+M11)/2 -> 0.95146322 | O11: ='Tax Levies and EQ Tax Rates'!I6 -> 10090281 | P11: =N11*O11 -> 9600531.2 | Q11: 10143 | R11: =P11/Q11 -> 946.51792
A12: Bergen | B12: New Milford Borough | C12: =$B$5*R12 -> 2076.0939 | D12: =C12/(K12/100) -> 248760.56 | E12: =0.9*F12 -> 336351.6 | F12: 373724 | G12: =F12-D12 -> 124963.44 | H12: =0.9*I12 -> 384199.2 | I12: 426888 | J12: =I12-D12 -> 178127.44 | K12: 0.83457519 | L12: ='# and Assessed Value of Parcels'!G7/'# and Assessed Value of Parcels'!O7 -> 0.98144233 | M12: ='# and Assessed Value of Parcels'!H7/'# and Assessed Value of Parcels'!P7 -> 0.94433259 | N12: =(L12+M12)/2 -> 0.96288746 | O12: ='Tax Levies and EQ Tax Rates'!I7 -> 17251960 | P12: =N12*O12 -> 16611696 | Q12: 16923 | R12: =P12/Q12 -> 981.6047
A13: Bergen | B13: Oakland Borough | C13: =$B$5*R13 -> 2365.0652 | D13: =C13/(K13/100) -> 392039.97 | E13: =0.9*F13 -> 329555.7 | F13: 366173 | G13: =F13-D13 -> -25866.967 | H13: =0.9*I13 -> 448910.1 | I13: 498789 | J13: =I13-D13 -> 106749.03 | K13: 0.60327146 | L13: ='# and Assessed Value of Parcels'!G8/'# and Assessed Value of Parcels'!O8 -> 0.9566732 | M13: ='# and Assessed Value of Parcels'!H8/'# and Assessed Value of Parcels'!P8 -> 0.84635298 | N13: =(L13+M13)/2 -> 0.90151309 | O13: ='Tax Levies and EQ Tax Rates'!I8 -> 15812581 | P13: =N13*O13 -> 14255249 | Q13: 12748 | R13: =P13/Q13 -> 1118.2342
A14: Bergen | B14: Westwood Borough | C14: =$B$5*R14 -> 2462.9176 | D14: =C14/(K14/100) -> 335709.18 | E14: =0.9*F14 -> 421789.5 | F14: 468655 | G14: =F14-D14 -> 132945.82 | H14: =0.9*I14 -> 413520.3 | I14: 459467 | J14: =I14-D14 -> 123757.82 | K14: 0.73364618 | L14: ='# and Assessed Value of Parcels'!G9/'# and Assessed Value of Parcels'!O9 -> 0.91940211 | M14: ='# and Assessed Value of Parcels'!H9/'# and Assessed Value of Parcels'!P9 -> 0.75552222 | N14: =(L14+M14)/2 -> 0.83746217 | O14: ='Tax Levies and EQ Tax Rates'!I9 -> 15687741 | P14: =N14*O14 -> 13137890 | Q14: 11282 | R14: =P14/Q14 -> 1164.5
A15: Burlington | B15: Lumberton Township | C15: =$B$5*R15 -> 826.66019 | D15: =C15/(K15/100) -> 211875.23 | E15: =0.9*F15 -> 419752.95 | F15: 466392.16 | G15: =F15-D15 -> 254516.93 | H15: =0.9*I15 -> 276152.4 | I15: 306836 | J15: =I15-D15 -> 94960.769 | K15: 0.39016368 | L15: ='# and Assessed Value of Parcels'!G10/'# and Assessed Value of Parcels'!O10 -> 0.96040113 | M15: ='# and Assessed Value of Parcels'!H10/'# and Assessed Value of Parcels'!P10 -> 0.85301722 | N15: =(L15+M15)/2 -> 0.90670917 | O15: ='Tax Levies and EQ Tax Rates'!I10 -> 5518999.9 | P15: =N15*O15 -> 5004127.9 | Q15: 12803 | R15: =P15/Q15 -> 390.85588
A16: Burlington | B16: Medford Township | C16: =$B$5*R16 -> 1058.1906 | D16: =C16/(K16/100) -> 280268.23 | E16: =0.9*F16 -> 98414.4 | F16: 109349.33 | G16: =F16-D16 -> -170918.89 | H16: =0.9*I16 -> 333705.6 | I16: 370784 | J16: =I16-D16 -> 90515.773 | K16: 0.37756351 | L16: ='# and Assessed Value of Parcels'!G11/'# and Assessed Value of Parcels'!O11 -> 0.95851299 | M16: ='# and Assessed Value of Parcels'!H11/'# and Assessed Value of Parcels'!P11 -> 0.91282275 | N16: =(L16+M16)/2 -> 0.93566787 | O16: ='Tax Levies and EQ Tax Rates'!I11 -> 13099198 | P16: =N16*O16 -> 12256498 | Q16: 24497 | R16: =P16/Q16 -> 500.32651
A17: Burlington | B17: Pemberton Township | C17: =$B$5*R17 -> 1150.352 | D17: =C17/(K17/100) -> 113467.84 | E17: =0.9*F17 -> 84516.075 | F17: 93906.75 | G17: =F17-D17 -> -19561.095 | H17: =0.9*I17 -> 149680.8 | I17: 166312 | J17: =I17-D17 -> 52844.155 | K17: 1.0138132 | L17: ='# and Assessed Value of Parcels'!G12/'# and Assessed Value of Parcels'!O12 -> 0.98128309 | M17: ='# and Assessed Value of Parcels'!H12/'# and Assessed Value of Parcels'!P12 -> 0.9332896 | N17: =(L17+M17)/2 -> 0.95728635 | O17: ='Tax Levies and EQ Tax Rates'!I12 -> 15285485 | P17: =N17*O17 -> 14632586 | Q17: 26903 | R17: =P17/Q17 -> 543.90165
A18: Burlington | B18: Southampton Township | C18: =$B$5*R18 -> 814.63874 | D18: =C18/(K18/100) -> 240123.99 | E18: =0.9*F18 -> 118318.54 | F18: 131465.05 | G18: =F18-D18 -> -108658.94 | H18: =0.9*I18 -> 214680.6 | I18: 238534 | J18: =I18-D18 -> -1589.9924 | K18: 0.33925754 | L18: ='# and Assessed Value of Parcels'!G13/'# and Assessed Value of Parcels'!O13 -> 0.96051204 | M18: ='# and Assessed Value of Parcels'!H13/'# and Assessed Value of Parcels'!P13 -> 0.90183161 | N18: =(L18+M18)/2 -> 0.93117183 | O18: ='Tax Levies and EQ Tax Rates'!I13 -> 4267546.8 | P18: =N18*O18 -> 3973819.4 | Q18: 10317 | R18: =P18/Q18 -> 385.17198
A19: Cumberland | B19: Downe Township | C19: =$B$5*R19 -> 722.12569 | D19: =C19/(K19/100) -> 189721.81 | E19: =0.9*F19 -> 88758.308 | F19: 98620.342 | G19: =F19-D19 -> -91101.465 | H19: =0.9*I19 -> 106640.1 | I19: 118489 | J19: =I19-D19 -> -71232.807 | K19: 0.38062345 | L19: ='# and Assessed Value of Parcels'!G14/'# and Assessed Value of Parcels'!O14 -> 0.94935452 | M19: ='# and Assessed Value of Parcels'!H14/'# and Assessed Value of Parcels'!P14 -> 0.95309492 | N19: =(L19+M19)/2 -> 0.95122472 | O19: ='Tax Levies and EQ Tax Rates'!I14 -> 502154.1 | P19: =N19*O19 -> 477661.39 | Q19: 1399 | R19: =P19/Q19 -> 341.43059
A20: Cumberland | B20: Fairfield Township | C20: =$B$5*R20 -> 484.76875 | D20: =C20/(K20/100) -> 99175.029 | E20: =0.9*F20 -> 78351.891 | F20: 87057.657 | G20: =F20-D20 -> -12117.372 | H20: =0.9*I20 -> 128558.7 | I20: 142843 | J20: =I20-D20 -> 43667.971 | K20: 0.48880122 | L20: ='# and Assessed Value of Parcels'!G15/'# and Assessed Value of Parcels'!O15 -> 0.95576808 | M20: ='# and Assessed Value of Parcels'!H15/'# and Assessed Value of Parcels'!P15 -> 0.9003797 | N20: =(L20+M20)/2 -> 0.92807389 | O20: ='Tax Levies and EQ Tax Rates'!I15 -> 1369687.7 | P20: =N20*O20 -> 1271171.4 | Q20: 5546 | R20: =P20/Q20 -> 229.20508
A21: Cumberland | B21: Lawrence Township | C21: =$B$5*R21 -> 799.85435 | D21: =C21/(K21/100) -> 146698.24 | E21: =0.9*F21 -> 32476.5 | F21: 36085 | G21: =F21-D21 -> -110613.24 | H21: =0.9*I21 -> 148570.2 | I21: 165078 | J21: =I21-D21 -> 18379.758 | K21: 0.54523786 | L21: ='# and Assessed Value of Parcels'!G16/'# and Assessed Value of Parcels'!O16 -> 0.96660808 | M21: ='# and Assessed Value of Parcels'!H16/'# and Assessed Value of Parcels'!P16 -> 0.93631576 | N21: =(L21+M21)/2 -> 0.95146192 | O21: ='Tax Levies and EQ Tax Rates'!I16 -> 1227003.4 | P21: =N21*O21 -> 1167447 | Q21: 3087 | R21: =P21/Q21 -> 378.18173
A22: Essex | B22: Fairfield Township | C22: =$B$5*R22 -> 2627.4096 | D22: =C22/(K22/100) -> 604315.18 | E22: =0.9*F22 -> 197720.1 | F22: 219689 | G22: =F22-D22 -> -384626.18 | H22: =0.9*I22 -> 542896.6 | I22: 603218.44 | J22: =I22-D22 -> -1096.7315 | K22: 0.43477472 | L22: ='[1]# and Assessed Value of Parcels'!G17/'[1]# and Assessed Value of Parcels'!O17 -> 0.78907204 | M22: ='[1]# and Assessed Value of Parcels'!H17/'[1]# and Assessed Value of Parcels'!P17 -> 0.44402102 | N22: =(L22+M22)/2 -> 0.61654653 | O22: ='[1]Tax Levies and EQ Tax Rates'!I17 -> 15861222 | P22: =N22*O22 -> 9779181.4 | Q22: 7872 | R22: =P22/Q22 -> 1242.2741
A23: Essex | B23: Newark City | C23: =$B$5*R23 -> 1185.9544 | D23: =C23/(K23/100) -> 70449.503 | E23: =0.9*F23 -> 148076.7 | F23: 164529.67 | G23: =F23-D23 -> 94080.164 | H23: =0.9*I23 -> 186151.5 | I23: 206835 | J23: =I23-D23 -> 136385.5 | K23: 1.6834106 | L23: ='# and Assessed Value of Parcels'!G18/'# and Assessed Value of Parcels'!O18 -> 0.84162884 | M23: ='# and Assessed Value of Parcels'!H18/'# and Assessed Value of Parcels'!P18 -> 0.54365223 | N23: =(L23+M23)/2 -> 0.69264054 | O23: ='Tax Levies and EQ Tax Rates'!I18 -> 252218004 | P23: =N23*O23 -> 1.7469641e+08 | Q23: 311549 | R23: =P23/Q23 -> 560.73495
A24: Hunterdon | B24: Lebanon Township | C24: =$B$5*R24 -> 906.21178 | D24: =C24/(K24/100) -> 305799.71 | E24: =0.9*F24 -> 54622.35 | F24: 60691.5 | G24: =F24-D24 -> -245108.21 | H24: =0.9*I24 -> 341844.3 | I24: 379827 | J24: =I24-D24 -> 74027.295 | K24: 0.29634161 | L24: ='# and Assessed Value of Parcels'!G19/'# and Assessed Value of Parcels'!O19 -> 0.96383866 | M24: ='# and Assessed Value of Parcels'!H19/'# and Assessed Value of Parcels'!P19 -> 0.93906348 | N24: =(L24+M24)/2 -> 0.95145107 | O24: ='Tax Levies and EQ Tax Rates'!I19 -> 2789807.1 | P24: =N24*O24 -> 2654365 | Q24: 6195 | R24: =P24/Q24 -> 428.46893
A25: Middlesex | B25: East Brunswick Township | C25: =$B$5*R25 -> 1665.6928 | D25: =C25/(K25/100) -> 288005.39 | E25: =0.9*F25 -> 205367.25 | F25: 228185.83 | G25: =F25-D25 -> -59819.553 | H25: =0.9*I25 -> 342280.8 | I25: 380312 | J25: =I25-D25 -> 92306.614 | K25: 0.57835476 | L25: ='# and Assessed Value of Parcels'!G20/'# and Assessed Value of Parcels'!O20 -> 0.95667524 | M25: ='# and Assessed Value of Parcels'!H20/'# and Assessed Value of Parcels'!P20 -> 0.81220548 | N25: =(L25+M25)/2 -> 0.88444036 | O25: ='Tax Levies and EQ Tax Rates'!I20 -> 44269380 | P25: =N25*O25 -> 39153626 | Q25: 49715 | R25: =P25/Q25 -> 787.56163
A26: Middlesex | B26: Old Bridge Township | C26: =$B$5*R26 -> 1111.6058 | D26: =C26/(K26/100) -> 251660.73 | E26: =0.9*F26 -> 118017.64 | F26: 131130.71 | G26: =F26-D26 -> -120530.01 | H26: =0.9*I26 -> 337972.5 | I26: 375525 | J26: =I26-D26 -> 123864.27 | K26: 0.44170809 | L26: ='# and Assessed Value of Parcels'!G21/'# and Assessed Value of Parcels'!O21 -> 0.97122792 | M26: ='# and Assessed Value of Parcels'!H21/'# and Assessed Value of Parcels'!P21 -> 0.88589383 | N26: =(L26+M26)/2 -> 0.92856088 | O26: ='Tax Levies and EQ Tax Rates'!I21 -> 37853002 | P26: =N26*O26 -> 35148817 | Q26: 66876 | R26: =P26/Q26 -> 525.58193
A27: Middlesex | B27: Middlesex Borough | C27: =$B$5*R27 -> 1756.7627 | D27: =C27/(K27/100) -> 216217.57 | E27: =0.9*F27 -> 275471.83 | F27: 306079.81 | G27: =F27-D27 -> 89862.245 | H27: =0.9*I27 -> 292394.7 | I27: 324883 | J27: =I27-D27 -> 108665.43 | K27: 0.81249766 | L27: ='# and Assessed Value of Parcels'!G22/'# and Assessed Value of Parcels'!O22 -> 0.92460317 | M27: ='# and Assessed Value of Parcels'!H22/'# and Assessed Value of Parcels'!P22 -> 0.82398227 | N27: =(L27+M27)/2 -> 0.87429272 | O27: ='Tax Levies and EQ Tax Rates'!I22 -> 13904913 | P27: =N27*O27 -> 12156964 | Q27: 14636 | R27: =P27/Q27 -> 830.62065
A28: Middlesex | B28: Sayreville Borough | C28: =$B$5*R28 -> 1503.1294 | D28: =C28/(K28/100) -> 222442.08 | E28: =0.9*F28 -> 187807.57 | F28: 208675.08 | G28: =F28-D28 -> -13766.995 | H28: =0.9*I28 -> 297859.5 | I28: 330955 | J28: =I28-D28 -> 108512.92 | K28: 0.67573971 | L28: ='# and Assessed Value of Parcels'!G23/'# and Assessed Value of Parcels'!O23 -> 0.96279666 | M28: ='# and Assessed Value of Parcels'!H23/'# and Assessed Value of Parcels'!P23 -> 0.85286918 | N28: =(L28+M28)/2 -> 0.90783292 | O28: ='Tax Levies and EQ Tax Rates'!I23 -> 35498458 | P28: =N28*O28 -> 32226669 | Q28: 45345 | R28: =P28/Q28 -> 710.69949
A29: Middlesex | B29: South River Borough | C29: =$B$5*R29 -> 1291.0269 | D29: =C29/(K29/100) -> 182970.34 | E29: =0.9*F29 -> 147122.7 | F29: 163469.67 | G29: =F29-D29 -> -19500.678 | H29: =0.9*I29 -> 264123 | I29: 293470 | J29: =I29-D29 -> 110499.66 | K29: 0.70559352 | L29: ='# and Assessed Value of Parcels'!G24/'# and Assessed Value of Parcels'!O24 -> 0.95376862 | M29: ='# and Assessed Value of Parcels'!H24/'# and Assessed Value of Parcels'!P24 -> 0.87694473 | N29: =(L29+M29)/2 -> 0.91535668 | O29: ='Tax Levies and EQ Tax Rates'!I24 -> 10748447 | P29: =N29*O29 -> 9838662.7 | Q29: 16118 | R29: =P29/Q29 -> 610.41461
A30: Middlesex | B30: Woodbridge Township | C30: =$B$5*R30 -> 1776.3675 | D30: =C30/(K30/100) -> 214867.96 | E30: =0.9*F30 -> 209555.7 | F30: 232839.67 | G30: =F30-D30 -> 17971.708 | H30: =0.9*I30 -> 276858 | I30: 307620 | J30: =I30-D30 -> 92752.037 | K30: 0.82672514 | L30: ='# and Assessed Value of Parcels'!G25/'# and Assessed Value of Parcels'!O25 -> 0.95527754 | M30: ='# and Assessed Value of Parcels'!H25/'# and Assessed Value of Parcels'!P25 -> 0.7164271 | N30: =(L30+M30)/2 -> 0.83585232 | O30: ='Tax Levies and EQ Tax Rates'!I25 -> 1.0413965e+08 | P30: =N30*O30 -> 87045366 | Q30: 103639 | R30: =P30/Q30 -> 839.89006
A31: Monmouth | B31: Keansburg Borough | C31: =$B$5*R31 -> 2412.808 | D31: =C31/(K31/100) -> 128770.14 | E31: =0.9*F31 -> 121246.88 | F31: 134718.75 | G31: =F31-D31 -> 5948.6058 | H31: =0.9*I31 -> 165501.9 | I31: 183891 | J31: =I31-D31 -> 55120.856 | K31: 1.8737325 | L31: ='# and Assessed Value of Parcels'!G26/'# and Assessed Value of Parcels'!O26 -> 0.96441281 | M31: ='# and Assessed Value of Parcels'!H26/'# and Assessed Value of Parcels'!P26 -> 0.88303144 | N31: =(L31+M31)/2 -> 0.92372213 | O31: ='Tax Levies and EQ Tax Rates'!I26 -> 12047538 | P31: =N31*O31 -> 11128578 | Q31: 9755 | R31: =P31/Q31 -> 1140.8076
A32: Monmouth | B32: Manalapan Township | C32: =$B$5*R32 -> 1222.3771 | D32: =C32/(K32/100) -> 366286.75 | E32: =0.9*F32 -> 262856.25 | F32: 292062.5 | G32: =F32-D32 -> -74224.254 | H32: =0.9*I32 -> 432438.3 | I32: 480487 | J32: =I32-D32 -> 114200.25 | K32: 0.33372135 | L32: ='# and Assessed Value of Parcels'!G27/'# and Assessed Value of Parcels'!O27 -> 0.97272104 | M32: ='# and Assessed Value of Parcels'!H27/'# and Assessed Value of Parcels'!P27 -> 0.9220575 | N32: =(L32+M32)/2 -> 0.94738927 | O32: ='Tax Levies and EQ Tax Rates'!I27 -> 24954149 | P32: =N32*O32 -> 23641293 | Q32: 40905 | R32: =P32/Q32 -> 577.95608
A33: Monmouth | B33: Ocean Township | C33: =$B$5*R33 -> 1607.0203 | D33: =C33/(K33/100) -> 397071.63 | E33: =0.9*F33 -> 809998.92 | F33: 899998.8 | G33: =F33-D33 -> 502927.17 | H33: =0.9*I33 -> 487810.8 | I33: 542012 | J33: =I33-D33 -> 144940.37 | K33: 0.404718 | L33: ='# and Assessed Value of Parcels'!G28/'# and Assessed Value of Parcels'!O28 -> 0.95530169 | M33: ='# and Assessed Value of Parcels'!H28/'# and Assessed Value of Parcels'!P28 -> 0.88451081 | N33: =(L33+M33)/2 -> 0.91990625 | O33: ='Tax Levies and EQ Tax Rates'!I28 -> 22856408 | P33: =N33*O33 -> 21025753 | Q33: 27672 | R33: =P33/Q33 -> 759.82049
A34: Monmouth | B34: Sea Bright Borough | C34: =$B$5*R34 -> 5970.0096 | D34: =C34/(K34/100) -> 1162347.6 | E34: =0.9*F34 -> 1295078.4 | F34: 1438976 | G34: =F34-D34 -> 276628.44 | H34: =0.9*I34 -> 627586.2 | I34: 697318 | J34: =I34-D34 -> -465029.56 | K34: 0.51361656 | L34: ='# and Assessed Value of Parcels'!G29/'# and Assessed Value of Parcels'!O29 -> 0.9358047 | M34: ='# and Assessed Value of Parcels'!H29/'# and Assessed Value of Parcels'!P29 -> 0.81959946 | N34: =(L34+M34)/2 -> 0.87770208 | O34: ='Tax Levies and EQ Tax Rates'!I29 -> 4660000 | P34: =N34*O34 -> 4090091.7 | Q34: 1449 | R34: =P34/Q34 -> 2822.6996
... A47: Warren | B47: Harmony Township | C47: =$B$5*R47 -> 953.66305 | D47: =C47/(K47/100) -> 332376.89 | E47: =0.9*F47 -> 102761.28 | F47: 114179.2 | G47: =F47-D47 -> -218197.68 | H47: =0.9*I47 -> 216166.5 | I47: 240185 | J47: =I47-D47 -> -92191.888 | K47: 0.28692219 | L47: ='# and Assessed Value of Parcels'!G42/'# and Assessed Value of Parcels'!O42 -> 0.95134062 | M47: ='# and Assessed Value of Parcels'!H42/'# and Assessed Value of Parcels'!P42 -> 0.44542234 | N47: =(L47+M47)/2 -> 0.69838148 | O47: ='Tax Levies and EQ Tax Rates'!I42 -> 1616042.3 | P47: =N47*O47 -> 1128614 | Q47: 2503 | R47: =P47/Q47 -> 450.90451
C48: =AVERAGE(C10:C47) -> 1694.5496 | D48: =AVERAGE(D10:D47) -> 276383.18 | E48: =AVERAGE(E10:E47) -> 223680.18 | F48: =AVERAGE(F10:F47) -> 248533.53 | G48: =AVERAGE(G10:G47) -> -27849.651 | H48: =AVERAGE(H10:H47) -> 310513.82 | I48: =AVERAGE(I10:I47) -> 345015.35 | J48: =AVERAGE(J10:J47) -> 68632.172 | ... R48: =AVERAGE(R10:R47) -> 801.20546

Sheet (1.5 Bed Multi) Break Even
A1: 2020 Break Even Analysis for Multifamily (Owned) (1.5 Bedroom) in Selected NJ Communities
A3: Multifamily (1.5 Bedroom) Multipliers
A4: Category | B4: Multiplier
A5: Household Size | B5: 1.575
A6: School Age Children | B6: 0.081
A8: Location | C8: 1.5 Bedroom Multifamily "Break Even Analysis" | G8: Fiscal Analysis | M8: School and Municipal Fiscal Impact Analysis
A9: County | B9: Municipality | C9: Municipal Tax Supported Cost | D9: School Tax Supported Cost | E9: Total Tax Supported Cost | F9: Market Value "Break Even" | G9: Adjusted Average Real (2020) Market Value of Buyout Properties | H9: Average Real (2020) Market Value of Buyout Properties | I9: Fiscal Surplus or Deficit (Based on Average Buyout Market Value) | J9: Adjusted Average 2020 Residential Value in Buyout Community | K9: Average 2020 Residential Value in Buyout Community | L9: Fiscal Surplus or Deficit (Based on Average Residential Value) | M9: Total Municipal + School Equalized Property Tax Rate | N9: Percent of Total Parcels that are Residential | O9: Percent of Total Assessed Value that is Residential | P9: Average of Residential Parcels % and Assessed Value % | Q9: Total Municipal Property Tax Levy | R9: Estimated Residential Share of Total Municipal Property Tax Levy | S9: 2020 Municipal Population | T9: 2020 Municipal Property Tax Supported Cost Per Person | U9: Total School Property Tax Levy | V9: 2020 Total School Enrollment | W9: 2020 School Property Tax Supported Cost Per Pupil
A10: Atlantic | B10: Pleasantville City | C10: =$B$5*T10 -> 1502.2555 | D10: =W10*$B$6 -> 188.34723 | E10: =C10+D10 -> 1690.6028 | F10: =E10/(M10/100) -> 38683.677 | G10: =0.5*H10 -> 30117.5 | H10: 60235 | I10: =H10-F10 -> 21551.323 | J10: =0.5*K10 -> 49181.384 | K10: 98362.768 | L10: =K10-F10 -> 59679.092 | M10: ='Tax Levies and EQ Tax Rates'!O5 -> 4.370326 | N10: ='# and Assessed Value of Parcels'!G5/'# and Assessed Value of Parcels'!O5 -> 0.92172813 | O10: ='# and Assessed Value of Parcels'!H5/'# and Assessed Value of Parcels'!P5 -> 0.73101366 | P10: =(N10+O10)/2 -> 0.8263709 | Q10: ='Tax Levies and EQ Tax Rates'!I5 -> 23810385 | R10: =P10*Q10 -> 19676209 | S10: 20629 | T10: =R10/S10 -> 953.81304 | U10: ='Tax Levies and EQ Tax Rates'!C5 -> 10152148 | V10: 4366 | W10: =U10/V10 -> 2325.2744
A11: Bergen | B11: New Milford Borough | C11: =$B$5*T11 -> 1546.0274 | D11: =W11*$B$6 -> 1251.0082 | E11: =C11+D11 -> 2797.0356 | F11: =E11/(M11/100) -> 110139.05 | G11: =0.5*H11 -> 186862 | H11: 373724 | I11: =H11-F11 -> 263584.95 | J11: =0.5*K11 -> 213444.05 | K11: 426888.09 | L11: =K11-F11 -> 316749.04 | M11: ='Tax Levies and EQ Tax Rates'!O7 -> 2.5395493 | N11: ='# and Assessed Value of Parcels'!G7/'# and Assessed Value of Parcels'!O7 -> 0.98144233 | O11: ='# and Assessed Value of Parcels'!H7/'# and Assessed Value of Parcels'!P7 -> 0.94433259 | P11: =(N11+O11)/2 -> 0.96288746 | Q11: ='Tax Levies and EQ Tax Rates'!I7 -> 17251960 | R11: =P11*Q11 -> 16611696 | S11: 16923 | T11: =R11/S11 -> 981.6047 | U11: ='Tax Levies and EQ Tax Rates'!C7 -> 35244453 | V11: 2282 | W11: =U11/V11 -> 15444.546
A12: Essex | B12: Newark City | C12: =$B$5*T12 -> 883.15755 | D12: =W12*$B$6 -> 182.94483 | E12: =C12+D12 -> 1066.1024 | F12: =E12/(M12/100) -> 40293.651 | G12: =0.5*H12 -> 82264.833 | H12: 164529.67 | I12: =H12-F12 -> 124236.02 | J12: =0.5*K12 -> 103417.51 | K12: 206835.02 | L12: =K12-F12 -> 166541.37 | M12: ='Tax Levies and EQ Tax Rates'!O18 -> 2.6458321 | N12: ='# and Assessed Value of Parcels'!G18/'# and Assessed Value of Parcels'!O18 -> 0.84162884 | O12: ='# and Assessed Value of Parcels'!H18/'# and Assessed Value of Parcels'!P18 -> 0.54365223 | P12: =(N12+O12)/2 -> 0.69264054 | Q12: ='Tax Levies and EQ Tax Rates'!I18 -> 252218004 | R12: =P12*Q12 -> 1.7469641e+08 | S12: 311549 | T12: =R12/S12 -> 560.73495 | U12: ='Tax Levies and EQ Tax Rates'!C18 -> 135819599 | V12: 60135 | W12: =U12/V12 -> 2258.5782
A13: Middlesex | B13: East Brunswick Township | C13: =$B$5*T13 -> 1240.4096 | D13: =W13*$B$6 -> 1324.5685 | E13: =C13+D13 -> 2564.9781 | F13: =E13/(M13/100) -> 107850.93 | G13: =0.5*H13 -> 114092.92 | H13: 228185.83 | I13: =H13-F13 -> 120334.9 | J13: =0.5*K13 -> 190156.24 | K13: 380312.49 | L13: =K13-F13 -> 272461.55 | M13: ='Tax Levies and EQ Tax Rates'!O20 -> 2.3782623 | N13: ='# and Assessed Value of Parcels'!G20/'# and Assessed Value of Parcels'!O20 -> 0.95667524 | O13: ='# and Assessed Value of Parcels'!H20/'# and Assessed Value of Parcels'!P20 -> 0.81220548 | P13: =(N13+O13)/2 -> 0.88444036 | Q13: ='Tax Levies and EQ Tax Rates'!I20 -> 44269380 | R13: =P13*Q13 -> 39153626 | S13: 49715 | T13: =R13/S13 -> 787.56163 | U13: ='Tax Levies and EQ Tax Rates'!C20 -> 137771480 | V13: 8425 | W13: =U13/V13 -> 16352.698
A14: Middlesex | B14: Old Bridge Township | C14: =$B$5*T14 -> 827.79154 | D14: =W14*$B$6 -> 1069.7263 | E14: =C14+D14 -> 1897.5178 | F14: =E14/(M14/100) -> 112588.78 | G14: =0.5*H14 -> 65565.357 | H14: 131130.71 | I14: =H14-F14 -> 18541.93 | J14: =0.5*K14 -> 187762.53 | K14: 375525.05 | L14: =K14-F14 -> 262936.27 | M14: ='Tax Levies and EQ Tax Rates'!O21 -> 1.6853524 | N14: ='# and Assessed Value of Parcels'!G21/'# and Assessed Value of Parcels'!O21 -> 0.97122792 | O14: ='# and Assessed Value of Parcels'!H21/'# and Assessed Value of Parcels'!P21 -> 0.88589383 | P14: =(N14+O14)/2 -> 0.92856088 | Q14: ='Tax Levies and EQ Tax Rates'!I21 -> 37853002 | R14: =P14*Q14 -> 35148817 | S14: 66876 | T14: =R14/S14 -> 525.58193 | U14: ='Tax Levies and EQ Tax Rates'!C21 -> 106576433 | V14: 8070 | W14: =U14/V14 -> 13206.497
A15: Middlesex | B15: Middlesex Borough | C15: =$B$5*T15 -> 1308.2275 | D15: =W15*$B$6 -> 1050.2716 | E15: =C15+D15 -> 2358.4992 | F15: =E15/(M15/100) -> 100048.64 | G15: =0.5*H15 -> 153039.91 | H15: 306079.81 | I15: =H15-F15 -> 206031.17 | J15: =0.5*K15 -> 162441.42 | K15: 324882.84 | L15: =K15-F15 -> 224834.2 | M15: ='Tax Levies and EQ Tax Rates'!O22 -> 2.3573526 | N15: ='# and Assessed Value of Parcels'!G22/'# and Assessed Value of Parcels'!O22 -> 0.92460317 | O15: ='# and Assessed Value of Parcels'!H22/'# and Assessed Value of Parcels'!P22 -> 0.82398227 | P15: =(N15+O15)/2 -> 0.87429272 | Q15: ='Tax Levies and EQ Tax Rates'!I22 -> 13904913 | R15: =P15*Q15 -> 12156964 | S15: 14636 | T15: =R15/S15 -> 830.62065 | U15: ='Tax Levies and EQ Tax Rates'!C22 -> 26438319 | V15: 2039 | W15: =U15/V15 -> 12966.316
A16: Middlesex | B16: Sayreville Borough | C16: =$B$5*T16 -> 1119.3517 | D16: =W16*$B$6 -> 832.00189 | E16: =C16+D16 -> 1951.3536 | F16: =E16/(M16/100) -> 99085.983 | G16: =0.5*H16 -> 104337.54 | H16: 208675.08 | I16: =H16-F16 -> 109589.1 | J16: =0.5*K16 -> 165477.38 | K16: 330954.76 | L16: =K16-F16 -> 231868.78 | M16: ='Tax Levies and EQ Tax Rates'!O23 -> 1.9693538 | N16: ='# and Assessed Value of Parcels'!G23/'# and Assessed Value of Parcels'!O23 -> 0.96279666 | O16: ='# and Assessed Value of Parcels'!H23/'# and Assessed Value of Parcels'!P23 -> 0.85286918 | P16: =(N16+O16)/2 -> 0.90783292 | Q16: ='Tax Levies and EQ Tax Rates'!I23 -> 35498458 | R16: =P16*Q16 -> 32226669 | S16: 45345 | T16: =R16/S16 -> 710.69949 | U16: ='Tax Levies and EQ Tax Rates'!C23 -> 67957093 | V16: 6616 | W16: =U16/V16 -> 10271.628
A17: Middlesex | B17: South River Borough | C17: =$B$5*T17 -> 961.40302 | D17: =W17*$B$6 -> 604.38826 | E17: =C17+D17 -> 1565.7913 | F17: =E17/(M17/100) -> 82547.14 | G17: =0.5*H17 -> 81734.833 | H17: 163469.67 | I17: =H17-F17 -> 80922.526 | J17: =0.5*K17 -> 146734.95 | K17: 293469.91 | L17: =K17-F17 -> 210922.77 | M17: ='Tax Levies and EQ Tax Rates'!O24 -> 1.896845 | N17: ='# and Assessed Value of Parcels'!G24/'# and Assessed Value of Parcels'!O24 -> 0.95376862 | O17: ='# and Assessed Value of Parcels'!H24/'# and Assessed Value of Parcels'!P24 -> 0.87694473 | P17: =(N17+O17)/2 -> 0.91535668 | Q17: ='Tax Levies and EQ Tax Rates'!I24 -> 10748447 | R17: =P17*Q17 -> 9838662.7 | S17: 16118 | T17: =R17/S17 -> 610.41461 | U17: ='Tax Levies and EQ Tax Rates'!C24 -> 18146571 | V17: 2432 | W17: =U17/V17 -> 7461.5835
A18: Middlesex | B18: Woodbridge Township | C18: =$B$5*T18 -> 1322.8268 | D18: =W18*$B$6 -> 1074.6985 | E18: =C18+D18 -> 2397.5254 | F18: =E18/(M18/100) -> 102482.18 | G18: =0.5*H18 -> 116419.84 | H18: 232839.67 | I18: =H18-F18 -> 130357.49 | J18: =0.5*K18 -> 153809.75 | K18: 307619.51 | L18: =K18-F18 -> 205137.32 | M18: ='Tax Levies and EQ Tax Rates'!O25 -> 2.3394558 | N18: ='# and Assessed Value of Parcels'!G25/'# and Assessed Value of Parcels'!O25 -> 0.95527754 | O18: ='# and Assessed Value of Parcels'!H25/'# and Assessed Value of Parcels'!P25 -> 0.7164271 | P18: =(N18+O18)/2 -> 0.83585232 | Q18: ='Tax Levies and EQ Tax Rates'!I25 -> 1.0413965e+08 | R18: =P18*Q18 -> 87045366 | S18: 103639 | T18: =R18/S18 -> 839.89006 | U18: ='Tax Levies and EQ Tax Rates'!C25 -> 190553334 | V18: 14362 | W18: =U18/V18 -> 13267.883
A19: Monmouth | B19: Keansburg Borough | C19: =$B$5*T19 -> 1796.7719 | D19: =W19*$B$6 -> 240.95138 | E19: =C19+D19 -> 2037.7233 | F19: =E19/(M19/100) -> 75548.137 | G19: =0.5*H19 -> 67359.375 | H19: 134718.75 | I19: =H19-F19 -> 59170.613 | J19: =0.5*K19 -> 91945.551 | K19: 183891.1 | L19: =K19-F19 -> 108342.97 | M19: ='Tax Levies and EQ Tax Rates'!O26 -> 2.6972516 | N19: ='# and Assessed Value of Parcels'!G26/'# and Assessed Value of Parcels'!O26 -> 0.96441281 | O19: ='# and Assessed Value of Parcels'!H26/'# and Assessed Value of Parcels'!P26 -> 0.88303144 | P19: =(N19+O19)/2 -> 0.92372213 | Q19: ='Tax Levies and EQ Tax Rates'!I26 -> 12047538 | R19: =P19*Q19 -> 11128578 | S19: 9755 | T19: =R19/S19 -> 1140.8076 | U19: ='Tax Levies and EQ Tax Rates'!C26 -> 5294981 | V19: 1780 | W19: =U19/V19 -> 2974.7084
A20: Monmouth | B20: Manalapan Township | C20: =$B$5*T20 -> 910.28082 | D20: =W20*$B$6 -> 1107.6795 | E20: =C20+D20 -> 2017.9604 | F20: =E20/(M20/100) -> 124666.37 | G20: =0.5*H20 -> 146031.25 | H20: 292062.5 | I20: =H20-F20 -> 167396.13 | J20: =0.5*K20 -> 240243.69 | K20: 480487.37 | L20: =K20-F20 -> 355821 | M20: ='Tax Levies and EQ Tax Rates'!O27 -> 1.6186886 | N20: ='# and Assessed Value of Parcels'!G27/'# and Assessed Value of Parcels'!O27 -> 0.97272104 | O20: ='# and Assessed Value of Parcels'!H27/'# and Assessed Value of Parcels'!P27 -> 0.9220575 | P20: =(N20+O20)/2 -> 0.94738927 | Q20: ='Tax Levies and EQ Tax Rates'!I27 -> 24954149 | R20: =P20*Q20 -> 23641293 | S20: 40905 | T20: =R20/S20 -> 577.95608 | U20: ='Tax Levies and EQ Tax Rates'!C27 -> 66693248 | V20: 4877 | W20: =U20/V20 -> 13675.056
A21: Passaic | B21: Paterson City | C21: =$B$5*T21 -> 1199.6619 | D21: =W21*$B$6 -> 130.85069 | E21: =C21+D21 -> 1330.5126 | F21: =E21/(M21/100) -> 51492.1 | G21: =0.5*H21 -> 63852.06 | H21: 127704.12 | I21: =H21-F21 -> 76212.02 | J21: =0.5*K21 -> 129509.79 | K21: 259019.58 | L21: =K21-F21 -> 207527.48 | M21: ='Tax Levies and EQ Tax Rates'!O33 -> 2.5839159 | N21: ='# and Assessed Value of Parcels'!G33/'# and Assessed Value of Parcels'!O33 -> 0.82159481 | O21: ='# and Assessed Value of Parcels'!H33/'# and Assessed Value of Parcels'!P33 -> 0.65337602 | P21: =(N21+O21)/2 -> 0.73748542 | Q21: ='Tax Levies and EQ Tax Rates'!I33 -> 1.6497449e+08 | R21: =P21*Q21 -> 1.2166628e+08 | S21: 159732 | T21: =R21/S21 -> 761.69008 | U21: ='Tax Levies and EQ Tax Rates'!C33 -> 50970381 | V21: 31552 | W21: =U21/V21 -> 1615.4406
A22: Passaic | B22: Pompton Lakes Borough | C22: =$B$5*T22 -> 1399.0576 | D22: =W22*$B$6 -> 1073.2922 | E22: =C22+D22 -> 2472.3499 | F22: =E22/(M22/100) -> 86720.598 | G22: =0.5*H22 -> 138989.01 | H22: 277978.02 | I22: =H22-F22 -> 191257.42 | J22: =0.5*K22 -> 148504.86 | K22: 297009.71 | L22: =K22-F22 -> 210289.12 | M22: ='Tax Levies and EQ Tax Rates'!O34 -> 2.8509373 | N22: ='# and Assessed Value of Parcels'!G34/'# and Assessed Value of Parcels'!O34 -> 0.95521999 | O22: ='# and Assessed Value of Parcels'!H34/'# and Assessed Value of Parcels'!P34 -> 0.87552226 | P22: =(N22+O22)/2 -> 0.91537113 | Q22: ='Tax Levies and EQ Tax Rates'!I34 -> 10797816 | R22: =P22*Q22 -> 9884009 | S22: 11127 | T22: =R22/S22 -> 888.29056 | U22: ='Tax Levies and EQ Tax Rates'!C34 -> 25639759 | V22: 1935 | W22: =U22/V22 -> 13250.521
A23: Passaic | B23: Wayne Township | C23: =$B$5*T23 -> 1581.3649 | D23: =W23*$B$6 -> 1611.9864 | E23: =C23+D23 -> 3193.3513 | F23: =E23/(M23/100) -> 157210.85 | G23: =0.5*H23 -> 76659.687 | H23: 153319.37 | I23: =H23-F23 -> -3891.4777 | J23: =0.5*K23 -> 238923.07 | K23: 477846.14 | L23: =K23-F23 -> 320635.28 | M23: ='Tax Levies and EQ Tax Rates'!O35 -> 2.0312538 | N23: ='# and Assessed Value of Parcels'!G35/'# and Assessed Value of Parcels'!O35 -> 0.95973428 | O23: ='# and Assessed Value of Parcels'!H35/'# and Assessed Value of Parcels'!P35 -> 0.74630979 | P23: =(N23+O23)/2 -> 0.85302204 | Q23: ='Tax Levies and EQ Tax Rates'!I35 -> 64546529 | R23: =P23*Q23 -> 55059612 | S23: 54838 | T23: =R23/S23 -> 1004.0412 | U23: ='Tax Levies and EQ Tax Rates'!C35 -> 156760706 | V23: 7877 | W23: =U23/V23 -> 19901.067
A24: Somerset | B24: Franklin Township | C24: =$B$5*T24 -> 865.00862 | D24: =W24*$B$6 -> 1446.5862 | E24: =C24+D24 -> 2311.5948 | F24: =E24/(M24/100) -> 142412.76 | G24: =0.5*H24 -> 70817.25 | H24: 141634.5 | I24: =H24-F24 -> -778.25815 | J24: =0.5*K24 -> 184741.97 | K24: 369483.93 | L24: =K24-F24 -> 227071.17 | M24: ='Tax Levies and EQ Tax Rates'!O38 -> 1.6231655 | N24: ='# and Assessed Value of Parcels'!G38/'# and Assessed Value of Parcels'!O38 -> 0.96646123 | O24: ='# and Assessed Value of Parcels'!H38/'# and Assessed Value of Parcels'!P38 -> 0.74002785 | P24: =(N24+O24)/2 -> 0.85324454 | Q24: ='Tax Levies and EQ Tax Rates'!I38 -> 44004169 | R24: =P24*Q24 -> 37546317 | S24: 68364 | T24: =R24/S24 -> 549.21182 | U24: ='Tax Levies and EQ Tax Rates'!C38 -> 151105752 | V24: 8461 | W24: =U24/V24 -> 17859.089
A25: Somerset | B25: Manville Borough | C25: =$B$5*T25 -> 1245.2655 | D25: =W25*$B$6 -> 766.70937 | E25: =C25+D25 -> 2011.9748 | F25: =E25/(M25/100) -> 76259.172 | G25: =0.5*H25 -> 97261.466 | H25: 194522.93 | I25: =H25-F25 -> 118263.76 | J25: =0.5*K25 -> 126651.93 | K25: 253303.85 | L25: =K25-F25 -> 177044.68 | M25: ='Tax Levies and EQ Tax Rates'!O39 -> 2.6383382 | N25: ='# and Assessed Value of Parcels'!G39/'# and Assessed Value of Parcels'!O39 -> 0.95111773 | O25: ='# and Assessed Value of Parcels'!H39/'# and Assessed Value of Parcels'!P39 -> 0.86385135 | P25: =(N25+O25)/2 -> 0.90748454 | Q25: ='Tax Levies and EQ Tax Rates'!I39 -> 9542787.2 | R25: =P25*Q25 -> 8659931.8 | S25: 10953 | T25: =R25/S25 -> 790.64474 | U25: ='Tax Levies and EQ Tax Rates'!C39 -> 15656016 | V25: 1654 | W25: =U25/V25 -> 9465.5478
A26: Union | B26: Linden City | C26: =$B$5*T26 -> 1620.9565 | D26: =W26*$B$6 -> 1159.0962 | E26: =C26+D26 -> 2780.0526 | F26: =E26/(M26/100) -> 119758.01 | G26: =0.5*H26 -> 104337.86 | H26: 208675.72 | I26: =H26-F26 -> 88917.708 | J26: =0.5*K26 -> 163336.87 | K26: 326673.73 | L26: =K26-F26 -> 206915.72 | M26: ='Tax Levies and EQ Tax Rates'!O40 -> 2.3213918 | N26: ='# and Assessed Value of Parcels'!G40/'# and Assessed Value of Parcels'!O40 -> 0.90298507 | O26: ='# and Assessed Value of Parcels'!H40/'# and Assessed Value of Parcels'!P40 -> 0.53546516 | P26: =(N26+O26)/2 -> 0.71922512 | Q26: ='Tax Levies and EQ Tax Rates'!I40 -> 62587105 | R26: =P26*Q26 -> 45014218 | S26: 43738 | T26: =R26/S26 -> 1029.1787 | U26: ='Tax Levies and EQ Tax Rates'!C40 -> 94215916 | V26: 6584 | W26: =U26/V26 -> 14309.829
A27: Union | B27: Rahway City | C27: =$B$5*T27 -> 1743.2195 | D27: =W27*$B$6 -> 888.8497 | E27: =C27+D27 -> 2632.0692 | F27: =E27/(M27/100) -> 91218.634 | G27: =0.5*H27 -> 132152.28 | H27: 264304.56 | I27: =H27-F27 -> 173085.92 | J27: =0.5*K27 -> 135807.41 | K27: 271614.82 | L27: =K27-F27 -> 180396.19 | M27: ='Tax Levies and EQ Tax Rates'!O41 -> 2.8854512 | N27: ='# and Assessed Value of Parcels'!G41/'# and Assessed Value of Parcels'!O41 -> 0.94367816 | O27: ='# and Assessed Value of Parcels'!H41/'# and Assessed Value of Parcels'!P41 -> 0.73460248 | P27: =(N27+O27)/2 -> 0.83914032 | Q27: ='Tax Levies and EQ Tax Rates'!I41 -> 38983658 | R27: =P27*Q27 -> 32712759 | S27: 29556 | T27: =R27/S27 -> 1106.806 | U27: ='Tax Levies and EQ Tax Rates'!C41 -> 45342308 | V27: 4132 | W27: =U27/V27 -> 10973.453
C28: =AVERAGE(C10:C27) -> 1281.8354 | D28: =AVERAGE(D10:D27) -> 889.10873 | E28: =AVERAGE(E10:E27) -> 2170.9442 | F28: =AVERAGE(F10:F27) -> 95500.371 | G28: =AVERAGE(G10:G27) -> 101771.94 | H28: =AVERAGE(H10:H27) -> 203543.88 | I28: =AVERAGE(I10:I27) -> 108043.51 | J28: =AVERAGE(J10:J27) -> 157338.35 | ... W28: =AVERAGE(W10:W27) -> 10976.651

Sheet Adjusted(1.5 Bed Multi) Break E
A1: 2020 Break Even Analysis for Multifamily (Owned) (1.5 Bedroom) in Selected NJ Communities
A3: Multifamily (1.5 Bedroom) Multipliers
A4: Category | B4: Multiplier
A5: Household Size | B5: 1.575
A6: School Age Children | B6: 0.081
A8: Location | C8: 1.5 Bedroom Multifamily "Break Even Analysis" | G8: Fiscal Analysis | M8: School and Municipal Fiscal Impact Analysis
A9: County | B9: Municipality | C9: Municipal Tax Supported Cost | D9: School Tax Supported Cost | E9: Total Tax Supported Cost | F9: Market Value "Break Even" | G9: Adjusted Average Real (2020) Market Value of Buyout Properties | H9: Average Real (2020) Market Value of Buyout Properties | I9: Fiscal Surplus or Deficit (Based on Average Buyout Market Value) | J9: Adjusted Average 2020 Residential Value in Buyout Community | K9: Average 2020 Residential Value in Buyout Community | L9: Fiscal Surplus or Deficit (Based on Average Residential Value) | M9: Total Municipal + School Equalized Property Tax Rate | N9: Percent of Total Parcels that are Residential | O9: Percent of Total Assessed Value that is Residential | P9: Average of Residential Parcels % and Assessed Value % | Q9: Total Municipal Property Tax Levy | R9: Estimated Residential Share of Total Municipal Property Tax Levy | S9: 2020 Municipal Population | T9: 2020 Municipal Property Tax Supported Cost Per Person | U9: Total School Property Tax Levy | V9: 2020 Total School Enrollment | W9: 2020 School Property Tax Supported Cost Per Pupil
A10: Atlantic | B10: Pleasantville City | C10: =$B$5*T10 -> 1502.2555 | D10: =W10*$B$6 -> 188.34723 | E10: =C10+D10 -> 1690.6028 | F10: =E10/(M10/100) -> 38683.677 | G10: =0.5*H10 -> 30117.5 | H10: 60235 | I10: =H10-F10 -> 21551.323 | J10: =0.5*K10 -> 49181.384 | K10: 98362.768 | L10: =K10-F10 -> 59679.092 | M10: ='Tax Levies and EQ Tax Rates'!O5 -> 4.370326 | N10: ='# and Assessed Value of Parcels'!G5/'# and Assessed Value of Parcels'!O5 -> 0.92172813 | O10: ='# and Assessed Value of Parcels'!H5/'# and Assessed Value of Parcels'!P5 -> 0.73101366 | P10: =(N10+O10)/2 -> 0.8263709 | Q10: ='Tax Levies and EQ Tax Rates'!I5 -> 23810385 | R10: =P10*Q10 -> 19676209 | S10: 20629 | T10: =R10/S10 -> 953.81304 | U10: ='Tax Levies and EQ Tax Rates'!C5 -> 10152148 | V10: 4366 | W10: =U10/V10 -> 2325.2744
A11: Bergen | B11: New Milford Borough | C11: =$B$5*T11 -> 1546.0274 | D11: =W11*$B$6 -> 1251.0082 | E11: =C11+D11 -> 2797.0356 | F11: =E11/(M11/100) -> 110139.05 | G11: =0.5*H11 -> 186862 | H11: 373724 | I11: =H11-F11 -> 263584.95 | J11: =0.5*K11 -> 213444.05 | K11: 426888.09 | L11: =K11-F11 -> 316749.04 | M11: ='Tax Levies and EQ Tax Rates'!O7 -> 2.5395493 | N11: ='# and Assessed Value of Parcels'!G7/'# and Assessed Value of Parcels'!O7 -> 0.98144233 | O11: ='# and Assessed Value of Parcels'!H7/'# and Assessed Value of Parcels'!P7 -> 0.94433259 | P11: =(N11+O11)/2 -> 0.96288746 | Q11: ='Tax Levies and EQ Tax Rates'!I7 -> 17251960 | R11: =P11*Q11 -> 16611696 | S11: 16923 | T11: =R11/S11 -> 981.6047 | U11: ='Tax Levies and EQ Tax Rates'!C7 -> 35244453 | V11: 2282 | W11: =U11/V11 -> 15444.546
A12: Essex | B12: Newark City | C12: =$B$5*T12 -> 883.15755 | D12: =W12*$B$6 -> 182.94483 | E12: =C12+D12 -> 1066.1024 | F12: =E12/(M12/100) -> 40293.651 | G12: =0.5*H12 -> 82264.833 | H12: 164529.67 | I12: =H12-F12 -> 124236.02 | J12: =0.5*K12 -> 103417.51 | K12: 206835.02 | L12: =K12-F12 -> 166541.37 | M12: ='Tax Levies and EQ Tax Rates'!O18 -> 2.6458321 | N12: ='# and Assessed Value of Parcels'!G18/'# and Assessed Value of Parcels'!O18 -> 0.84162884 | O12: ='# and Assessed Value of Parcels'!H18/'# and Assessed Value of Parcels'!P18 -> 0.54365223 | P12: =(N12+O12)/2 -> 0.69264054 | Q12: ='Tax Levies and EQ Tax Rates'!I18 -> 252218004 | R12: =P12*Q12 -> 1.7469641e+08 | S12: 311549 | T12: =R12/S12 -> 560.73495 | U12: ='Tax Levies and EQ Tax Rates'!C18 -> 135819599 | V12: 60135 | W12: =U12/V12 -> 2258.5782
A13: Middlesex | B13: East Brunswick Township | C13: =$B$5*T13 -> 1240.4096 | D13: =W13*$B$6 -> 1324.5685 | E13: =C13+D13 -> 2564.9781 | F13: =E13/(M13/100) -> 107850.93 | G13: =0.5*H13 -> 114092.92 | H13: 228185.83 | I13: =H13-F13 -> 120334.9 | J13: =0.5*K13 -> 190156.24 | K13: 380312.49 | L13: =K13-F13 -> 272461.55 | M13: ='Tax Levies and EQ Tax Rates'!O20 -> 2.3782623 | N13: ='# and Assessed Value of Parcels'!G20/'# and Assessed Value of Parcels'!O20 -> 0.95667524 | O13: ='# and Assessed Value of Parcels'!H20/'# and Assessed Value of Parcels'!P20 -> 0.81220548 | P13: =(N13+O13)/2 -> 0.88444036 | Q13: ='Tax Levies and EQ Tax Rates'!I20 -> 44269380 | R13: =P13*Q13 -> 39153626 | S13: 49715 | T13: =R13/S13 -> 787.56163 | U13: ='Tax Levies and EQ Tax Rates'!C20 -> 137771480 | V13: 8425 | W13: =U13/V13 -> 16352.698
A14: Middlesex | B14: Old Bridge Township | C14: =$B$5*T14 -> 827.79154 | D14: =W14*$B$6 -> 1069.7263 | E14: =C14+D14 -> 1897.5178 | F14: =E14/(M14/100) -> 112588.78 | G14: =0.5*H14 -> 65565.357 | H14: 131130.71 | I14: =H14-F14 -> 18541.93 | J14: =0.5*K14 -> 187762.53 | K14: 375525.05 | L14: =K14-F14 -> 262936.27 | M14: ='Tax Levies and EQ Tax Rates'!O21 -> 1.6853524 | N14: ='# and Assessed Value of Parcels'!G21/'# and Assessed Value of Parcels'!O21 -> 0.97122792 | O14: ='# and Assessed Value of Parcels'!H21/'# and Assessed Value of Parcels'!P21 -> 0.88589383 | P14: =(N14+O14)/2 -> 0.92856088 | Q14: ='Tax Levies and EQ Tax Rates'!I21 -> 37853002 | R14: =P14*Q14 -> 35148817 | S14: 66876 | T14: =R14/S14 -> 525.58193 | U14: ='Tax Levies and EQ Tax Rates'!C21 -> 106576433 | V14: 8070 | W14: =U14/V14 -> 13206.497
A15: Middlesex | B15: Middlesex Borough | C15: =$B$5*T15 -> 1308.2275 | D15: =W15*$B$6 -> 1050.2716 | E15: =C15+D15 -> 2358.4992 | F15: =E15/(M15/100) -> 100048.64 | G15: =0.5*H15 -> 153039.91 | H15: 306079.81 | I15: =H15-F15 -> 206031.17 | J15: =0.5*K15 -> 162441.42 | K15: 324882.84 | L15: =K15-F15 -> 224834.2 | M15: ='Tax Levies and EQ Tax Rates'!O22 -> 2.3573526 | N15: ='# and Assessed Value of Parcels'!G22/'# and Assessed Value of Parcels'!O22 -> 0.92460317 | O15: ='# and Assessed Value of Parcels'!H22/'# and Assessed Value of Parcels'!P22 -> 0.82398227 | P15: =(N15+O15)/2 -> 0.87429272 | Q15: ='Tax Levies and EQ Tax Rates'!I22 -> 13904913 | R15: =P15*Q15 -> 12156964 | S15: 14636 | T15: =R15/S15 -> 830.62065 | U15: ='Tax Levies and EQ Tax Rates'!C22 -> 26438319 | V15: 2039 | W15: =U15/V15 -> 12966.316
A16: Middlesex | B16: Sayreville Borough | C16: =$B$5*T16 -> 1119.3517 | D16: =W16*$B$6 -> 832.00189 | E16: =C16+D16 -> 1951.3536 | F16: =E16/(M16/100) -> 99085.983 | G16: =0.5*H16 -> 104337.54 | H16: 208675.08 | I16: =H16-F16 -> 109589.1 | J16: =0.5*K16 -> 165477.38 | K16: 330954.76 | L16: =K16-F16 -> 231868.78 | M16: ='Tax Levies and EQ Tax Rates'!O23 -> 1.9693538 | N16: ='# and Assessed Value of Parcels'!G23/'# and Assessed Value of Parcels'!O23 -> 0.96279666 | O16: ='# and Assessed Value of Parcels'!H23/'# and Assessed Value of Parcels'!P23 -> 0.85286918 | P16: =(N16+O16)/2 -> 0.90783292 | Q16: ='Tax Levies and EQ Tax Rates'!I23 -> 35498458 | R16: =P16*Q16 -> 32226669 | S16: 45345 | T16: =R16/S16 -> 710.69949 | U16: ='Tax Levies and EQ Tax Rates'!C23 -> 67957093 | V16: 6616 | W16: =U16/V16 -> 10271.628
A17: Middlesex | B17: South River Borough | C17: =$B$5*T17 -> 961.40302 | D17: =W17*$B$6 -> 604.38826 | E17: =C17+D17 -> 1565.7913 | F17: =E17/(M17/100) -> 82547.14 | G17: =0.5*H17 -> 81734.833 | H17: 163469.67 | I17: =H17-F17 -> 80922.526 | J17: =0.5*K17 -> 146734.95 | K17: 293469.91 | L17: =K17-F17 -> 210922.77 | M17: ='Tax Levies and EQ Tax Rates'!O24 -> 1.896845 | N17: ='# and Assessed Value of Parcels'!G24/'# and Assessed Value of Parcels'!O24 -> 0.95376862 | O17: ='# and Assessed Value of Parcels'!H24/'# and Assessed Value of Parcels'!P24 -> 0.87694473 | P17: =(N17+O17)/2 -> 0.91535668 | Q17: ='Tax Levies and EQ Tax Rates'!I24 -> 10748447 | R17: =P17*Q17 -> 9838662.7 | S17: 16118 | T17: =R17/S17 -> 610.41461 | U17: ='Tax Levies and EQ Tax Rates'!C24 -> 18146571 | V17: 2432 | W17: =U17/V17 -> 7461.5835
A18: Middlesex | B18: Woodbridge Township | C18: =$B$5*T18 -> 1322.8268 | D18: =W18*$B$6 -> 1074.6985 | E18: =C18+D18 -> 2397.5254 | F18: =E18/(M18/100) -> 102482.18 | G18: =0.5*H18 -> 116419.84 | H18: 232839.67 | I18: =H18-F18 -> 130357.49 | J18: =0.5*K18 -> 153809.75 | K18: 307619.51 | L18: =K18-F18 -> 205137.32 | M18: ='Tax Levies and EQ Tax Rates'!O25 -> 2.3394558 | N18: ='# and Assessed Value of Parcels'!G25/'# and Assessed Value of Parcels'!O25 -> 0.95527754 | O18: ='# and Assessed Value of Parcels'!H25/'# and Assessed Value of Parcels'!P25 -> 0.7164271 | P18: =(N18+O18)/2 -> 0.83585232 | Q18: ='Tax Levies and EQ Tax Rates'!I25 -> 1.0413965e+08 | R18: =P18*Q18 -> 87045366 | S18: 103639 | T18: =R18/S18 -> 839.89006 | U18: ='Tax Levies and EQ Tax Rates'!C25 -> 190553334 | V18: 14362 | W18: =U18/V18 -> 13267.883
A19: Monmouth | B19: Keansburg Borough | C19: =$B$5*T19 -> 1796.7719 | D19: =W19*$B$6 -> 240.95138 | E19: =C19+D19 -> 2037.7233 | F19: =E19/(M19/100) -> 75548.137 | G19: =0.5*H19 -> 67359.375 | H19: 134718.75 | I19: =H19-F19 -> 59170.613 | J19: =0.5*K19 -> 91945.551 | K19: 183891.1 | L19: =K19-F19 -> 108342.97 | M19: ='Tax Levies and EQ Tax Rates'!O26 -> 2.6972516 | N19: ='# and Assessed Value of Parcels'!G26/'# and Assessed Value of Parcels'!O26 -> 0.96441281 | O19: ='# and Assessed Value of Parcels'!H26/'# and Assessed Value of Parcels'!P26 -> 0.88303144 | P19: =(N19+O19)/2 -> 0.92372213 | Q19: ='Tax Levies and EQ Tax Rates'!I26 -> 12047538 | R19: =P19*Q19 -> 11128578 | S19: 9755 | T19: =R19/S19 -> 1140.8076 | U19: ='Tax Levies and EQ Tax Rates'!C26 -> 5294981 | V19: 1780 | W19: =U19/V19 -> 2974.7084
A20: Monmouth | B20: Manalapan Township | C20: =$B$5*T20 -> 910.28082 | D20: =W20*$B$6 -> 1107.6795 | E20: =C20+D20 -> 2017.9604 | F20: =E20/(M20/100) -> 124666.37 | G20: =0.5*H20 -> 146031.25 | H20: 292062.5 | I20: =H20-F20 -> 167396.13 | J20: =0.5*K20 -> 240243.69 | K20: 480487.37 | L20: =K20-F20 -> 355821 | M20: ='Tax Levies and EQ Tax Rates'!O27 -> 1.6186886 | N20: ='# and Assessed Value of Parcels'!G27/'# and Assessed Value of Parcels'!O27 -> 0.97272104 | O20: ='# and Assessed Value of Parcels'!H27/'# and Assessed Value of Parcels'!P27 -> 0.9220575 | P20: =(N20+O20)/2 -> 0.94738927 | Q20: ='Tax Levies and EQ Tax Rates'!I27 -> 24954149 | R20: =P20*Q20 -> 23641293 | S20: 40905 | T20: =R20/S20 -> 577.95608 | U20: ='Tax Levies and EQ Tax Rates'!C27 -> 66693248 | V20: 4877 | W20: =U20/V20 -> 13675.056
A21: Passaic | B21: Paterson City | C21: =$B$5*T21 -> 1199.6619 | D21: =W21*$B$6 -> 130.85069 | E21: =C21+D21 -> 1330.5126 | F21: =E21/(M21/100) -> 51492.1 | G21: =0.5*H21 -> 63852.06 | H21: 127704.12 | I21: =H21-F21 -> 76212.02 | J21: =0.5*K21 -> 129509.79 | K21: 259019.58 | L21: =K21-F21 -> 207527.48 | M21: ='Tax Levies and EQ Tax Rates'!O33 -> 2.5839159 | N21: ='# and Assessed Value of Parcels'!G33/'# and Assessed Value of Parcels'!O33 -> 0.82159481 | O21: ='# and Assessed Value of Parcels'!H33/'# and Assessed Value of Parcels'!P33 -> 0.65337602 | P21: =(N21+O21)/2 -> 0.73748542 | Q21: ='Tax Levies and EQ Tax Rates'!I33 -> 1.6497449e+08 | R21: =P21*Q21 -> 1.2166628e+08 | S21: 159732 | T21: =R21/S21 -> 761.69008 | U21: ='Tax Levies and EQ Tax Rates'!C33 -> 50970381 | V21: 31552 | W21: =U21/V21 -> 1615.4406
A22: Passaic | B22: Pompton Lakes Borough | C22: =$B$5*T22 -> 1399.0576 | D22: =W22*$B$6 -> 1073.2922 | E22: =C22+D22 -> 2472.3499 | F22: =E22/(M22/100) -> 86720.598 | G22: =0.5*H22 -> 138989.01 | H22: 277978.02 | I22: =H22-F22 -> 191257.42 | J22: =0.5*K22 -> 148504.86 | K22: 297009.71 | L22: =K22-F22 -> 210289.12 | M22: ='Tax Levies and EQ Tax Rates'!O34 -> 2.8509373 | N22: ='# and Assessed Value of Parcels'!G34/'# and Assessed Value of Parcels'!O34 -> 0.95521999 | O22: ='# and Assessed Value of Parcels'!H34/'# and Assessed Value of Parcels'!P34 -> 0.87552226 | P22: =(N22+O22)/2 -> 0.91537113 | Q22: ='Tax Levies and EQ Tax Rates'!I34 -> 10797816 | R22: =P22*Q22 -> 9884009 | S22: 11127 | T22: =R22/S22 -> 888.29056 | U22: ='Tax Levies and EQ Tax Rates'!C34 -> 25639759 | V22: 1935 | W22: =U22/V22 -> 13250.521
A23: Passaic | B23: Wayne Township | C23: =$B$5*T23 -> 1581.3649 | D23: =W23*$B$6 -> 1611.9864 | E23: =C23+D23 -> 3193.3513 | F23: =E23/(M23/100) -> 157210.85 | G23: =0.5*H23 -> 76659.687 | H23: 153319.37 | I23: =H23-F23 -> -3891.4777 | J23: =0.5*K23 -> 238923.07 | K23: 477846.14 | L23: =K23-F23 -> 320635.28 | M23: ='Tax Levies and EQ Tax Rates'!O35 -> 2.0312538 | N23: ='# and Assessed Value of Parcels'!G35/'# and Assessed Value of Parcels'!O35 -> 0.95973428 | O23: ='# and Assessed Value of Parcels'!H35/'# and Assessed Value of Parcels'!P35 -> 0.74630979 | P23: =(N23+O23)/2 -> 0.85302204 | Q23: ='Tax Levies and EQ Tax Rates'!I35 -> 64546529 | R23: =P23*Q23 -> 55059612 | S23: 54838 | T23: =R23/S23 -> 1004.0412 | U23: ='Tax Levies and EQ Tax Rates'!C35 -> 156760706 | V23: 7877 | W23: =U23/V23 -> 19901.067
A24: Somerset | B24: Franklin Township | C24: =$B$5*T24 -> 865.00862 | D24: =W24*$B$6 -> 1446.5862 | E24: =C24+D24 -> 2311.5948 | F24: =E24/(M24/100) -> 142412.76 | G24: =0.5*H24 -> 70817.25 | H24: 141634.5 | I24: =H24-F24 -> -778.25815 | J24: =0.5*K24 -> 184741.97 | K24: 369483.93 | L24: =K24-F24 -> 227071.17 | M24: ='Tax Levies and EQ Tax Rates'!O38 -> 1.6231655 | N24: ='# and Assessed Value of Parcels'!G38/'# and Assessed Value of Parcels'!O38 -> 0.96646123 | O24: ='# and Assessed Value of Parcels'!H38/'# and Assessed Value of Parcels'!P38 -> 0.74002785 | P24: =(N24+O24)/2 -> 0.85324454 | Q24: ='Tax Levies and EQ Tax Rates'!I38 -> 44004169 | R24: =P24*Q24 -> 37546317 | S24: 68364 | T24: =R24/S24 -> 549.21182 | U24: ='Tax Levies and EQ Tax Rates'!C38 -> 151105752 | V24: 8461 | W24: =U24/V24 -> 17859.089
A25: Somerset | B25: Manville Borough | C25: =$B$5*T25 -> 1245.2655 | D25: =W25*$B$6 -> 766.70937 | E25: =C25+D25 -> 2011.9748 | F25: =E25/(M25/100) -> 76259.172 | G25: =0.5*H25 -> 97261.466 | H25: 194522.93 | I25: =H25-F25 -> 118263.76 | J25: =0.5*K25 -> 126651.93 | K25: 253303.85 | L25: =K25-F25 -> 177044.68 | M25: ='Tax Levies and EQ Tax Rates'!O39 -> 2.6383382 | N25: ='# and Assessed Value of Parcels'!G39/'# and Assessed Value of Parcels'!O39 -> 0.95111773 | O25: ='# and Assessed Value of Parcels'!H39/'# and Assessed Value of Parcels'!P39 -> 0.86385135 | P25: =(N25+O25)/2 -> 0.90748454 | Q25: ='Tax Levies and EQ Tax Rates'!I39 -> 9542787.2 | R25: =P25*Q25 -> 8659931.8 | S25: 10953 | T25: =R25/S25 -> 790.64474 | U25: ='Tax Levies and EQ Tax Rates'!C39 -> 15656016 | V25: 1654 | W25: =U25/V25 -> 9465.5478
A26: Union | B26: Linden City | C26: =$B$5*T26 -> 1620.9565 | D26: =W26*$B$6 -> 1159.0962 | E26: =C26+D26 -> 2780.0526 | F26: =E26/(M26/100) -> 119758.01 | G26: =0.5*H26 -> 104337.86 | H26: 208675.72 | I26: =H26-F26 -> 88917.708 | J26: =0.5*K26 -> 163336.87 | K26: 326673.73 | L26: =K26-F26 -> 206915.72 | M26: ='Tax Levies and EQ Tax Rates'!O40 -> 2.3213918 | N26: ='# and Assessed Value of Parcels'!G40/'# and Assessed Value of Parcels'!O40 -> 0.90298507 | O26: ='# and Assessed Value of Parcels'!H40/'# and Assessed Value of Parcels'!P40 -> 0.53546516 | P26: =(N26+O26)/2 -> 0.71922512 | Q26: ='Tax Levies and EQ Tax Rates'!I40 -> 62587105 | R26: =P26*Q26 -> 45014218 | S26: 43738 | T26: =R26/S26 -> 1029.1787 | U26: ='Tax Levies and EQ Tax Rates'!C40 -> 94215916 | V26: 6584 | W26: =U26/V26 -> 14309.829
A27: Union | B27: Rahway City | C27: =$B$5*T27 -> 1743.2195 | D27: =W27*$B$6 -> 888.8497 | E27: =C27+D27 -> 2632.0692 | F27: =E27/(M27/100) -> 91218.634 | G27: =0.5*H27 -> 132152.28 | H27: 264304.56 | I27: =H27-F27 -> 173085.92 | J27: =0.5*K27 -> 135807.41 | K27: 271614.82 | L27: =K27-F27 -> 180396.19 | M27: ='Tax Levies and EQ Tax Rates'!O41 -> 2.8854512 | N27: ='# and Assessed Value of Parcels'!G41/'# and Assessed Value of Parcels'!O41 -> 0.94367816 | O27: ='# and Assessed Value of Parcels'!H41/'# and Assessed Value of Parcels'!P41 -> 0.73460248 | P27: =(N27+O27)/2 -> 0.83914032 | Q27: ='Tax Levies and EQ Tax Rates'!I41 -> 38983658 | R27: =P27*Q27 -> 32712759 | S27: 29556 | T27: =R27/S27 -> 1106.806 | U27: ='Tax Levies and EQ Tax Rates'!C41 -> 45342308 | V27: 4132 | W27: =U27/V27 -> 10973.453
C28: =AVERAGE(C10:C27) -> 1281.8354 | D28: =AVERAGE(D10:D27) -> 889.10873 | E28: =AVERAGE(E10:E27) -> 2170.9442 | F28: =AVERAGE(F10:F27) -> 95500.371 | G28: =AVERAGE(G10:G27) -> 101771.94 | H28: =AVERAGE(H10:H27) -> 203543.88 | I28: =AVERAGE(I10:I27) -> 108043.51 | J28: =AVERAGE(J10:J27) -> 157338.35 | ... W28: =AVERAGE(W10:W27) -> 10976.651

Sheet (1.5 Bed Multi) Muni Break Even
A1: 2020 Municipal Break Even Analysis for Multifamily (Owned) (1.5 Bedroom) in Selected NJ Communities
A3: Multifamily (1.5 Bedroom) Multipliers
A4: Category | B4: Multiplier
A5: Household Size | B5: 1.575
A6: School Age Children | B6: 0.067
A8: Location | C8: 1.5 Bedroom Multifamily Municipal "Break Even Analysis" | F8: Fiscal Analysis | K8: Municipal Fiscal Impact Analysis
A9: County | B9: Municipality | C9: Municipal Tax Supported Cost | D9: Market Value "Break Even" | E9: Adjusted Average Real (2020) Market Value of Buyout Properties | F9: Average Real (2020) Market Value of Buyout Properties | G9: Fiscal Surplus or Deficit (Based on Average Buyout Market Value) | H9: Adjusted Average 2020 Residential Value in Buyout Community | I9: Average 2020 Residential Value in Buyout Community | J9: Fiscal Surplus or Deficit (Based on Average Residential Value) | K9: Municipal Equalized Property Tax Rate | L9: Percent of Total Parcels that are Residential | M9: Percent of Total Assessed Value that is Residential | N9: Average of Residential Parcels % and Assessed Value % | O9: Total Municipal Property Tax Levy | P9: Estimated Residential Share of Total Municipal Property Tax Levy | Q9: 2020 Municipal Population | R9: 2020 Municipal Property Tax Supported Cost Per Person
A10: Atlantic | B10: Pleasantville City | C10: =$B$5*R10 -> 1502.2555 | D10: =C10/(K10/100) -> 49030.197 | E10: =0.5*F10 -> 30117.5 | F10: 60235 | G10: =F10-D10 -> 11204.803 | H10: =0.5*I10 -> 49181.5 | I10: 98363 | J10: =I10-D10 -> 49332.803 | K10: 3.0639394 | L10: ='# and Assessed Value of Parcels'!G5/'# and Assessed Value of Parcels'!O5 -> 0.92172813 | M10: ='# and Assessed Value of Parcels'!H5/'# and Assessed Value of Parcels'!P5 -> 0.73101366 | N10: =(L10+M10)/2 -> 0.8263709 | O10: ='Tax Levies and EQ Tax Rates'!I5 -> 23810385 | P10: =N10*O10 -> 19676209 | Q10: 20629 | R10: =P10/Q10 -> 953.81304
A11: Bergen | B11: Hillsdale Borough | C11: =$B$5*R11 -> 1490.7657 | D11: =C11/(K11/100) -> 278024.11 | E11: =0.5*F11 -> 110944 | F11: 221888 | G11: =F11-D11 -> -56136.11 | H11: =0.5*I11 -> 262105 | I11: 524210 | J11: =I11-D11 -> 246185.89 | K11: 0.53620016 | L11: ='# and Assessed Value of Parcels'!G6/'# and Assessed Value of Parcels'!O6 -> 0.96785506 | M11: ='# and Assessed Value of Parcels'!H6/'# and Assessed Value of Parcels'!P6 -> 0.93507138 | N11: =(L11+M11)/2 -> 0.95146322 | O11: ='Tax Levies and EQ Tax Rates'!I6 -> 10090281 | P11: =N11*O11 -> 9600531.2 | Q11: 10143 | R11: =P11/Q11 -> 946.51792
A12: Bergen | B12: New Milford Borough | C12: =$B$5*R12 -> 1546.0274 | D12: =C12/(K12/100) -> 185247.23 | E12: =0.5*F12 -> 186862 | F12: 373724 | G12: =F12-D12 -> 188476.77 | H12: =0.5*I12 -> 213444 | I12: 426888 | J12: =I12-D12 -> 241640.77 | K12: 0.83457519 | L12: ='# and Assessed Value of Parcels'!G7/'# and Assessed Value of Parcels'!O7 -> 0.98144233 | M12: ='# and Assessed Value of Parcels'!H7/'# and Assessed Value of Parcels'!P7 -> 0.94433259 | N12: =(L12+M12)/2 -> 0.96288746 | O12: ='Tax Levies and EQ Tax Rates'!I7 -> 17251960 | P12: =N12*O12 -> 16611696 | Q12: 16923 | R12: =P12/Q12 -> 981.6047
A13: Bergen | B13: Oakland Borough | C13: =$B$5*R13 -> 1761.2188 | D13: =C13/(K13/100) -> 291944.66 | E13: =0.5*F13 -> 183086.5 | F13: 366173 | G13: =F13-D13 -> 74228.343 | H13: =0.5*I13 -> 249394.5 | I13: 498789 | J13: =I13-D13 -> 206844.34 | K13: 0.60327146 | L13: ='# and Assessed Value of Parcels'!G8/'# and Assessed Value of Parcels'!O8 -> 0.9566732 | M13: ='# and Assessed Value of Parcels'!H8/'# and Assessed Value of Parcels'!P8 -> 0.84635298 | N13: =(L13+M13)/2 -> 0.90151309 | O13: ='Tax Levies and EQ Tax Rates'!I8 -> 15812581 | P13: =N13*O13 -> 14255249 | Q13: 12748 | R13: =P13/Q13 -> 1118.2342
A14: Bergen | B14: Westwood Borough | C14: =$B$5*R14 -> 1834.0876 | D14: =C14/(K14/100) -> 249996.2 | E14: =0.5*F14 -> 234327.5 | F14: 468655 | G14: =F14-D14 -> 218658.8 | H14: =0.5*I14 -> 229733.5 | I14: 459467 | J14: =I14-D14 -> 209470.8 | K14: 0.73364618 | L14: ='# and Assessed Value of Parcels'!G9/'# and Assessed Value of Parcels'!O9 -> 0.91940211 | M14: ='# and Assessed Value of Parcels'!H9/'# and Assessed Value of Parcels'!P9 -> 0.75552222 | N14: =(L14+M14)/2 -> 0.83746217 | O14: ='Tax Levies and EQ Tax Rates'!I9 -> 15687741 | P14: =N14*O14 -> 13137890 | Q14: 11282 | R14: =P14/Q14 -> 1164.5
A15: Burlington | B15: Lumberton Township | C15: =$B$5*R15 -> 615.59801 | D15: =C15/(K15/100) -> 157779.43 | E15: =0.5*F15 -> 233196.08 | F15: 466392.16 | G15: =F15-D15 -> 308612.74 | H15: =0.5*I15 -> 153418 | I15: 306836 | J15: =I15-D15 -> 149056.57 | K15: 0.39016368 | L15: ='# and Assessed Value of Parcels'!G10/'# and Assessed Value of Parcels'!O10 -> 0.96040113 | M15: ='# and Assessed Value of Parcels'!H10/'# and Assessed Value of Parcels'!P10 -> 0.85301722 | N15: =(L15+M15)/2 -> 0.90670917 | O15: ='Tax Levies and EQ Tax Rates'!I10 -> 5518999.9 | P15: =N15*O15 -> 5004127.9 | Q15: 12803 | R15: =P15/Q15 -> 390.85588
A16: Burlington | B16: Medford Township | C16: =$B$5*R16 -> 788.01425 | D16: =C16/(K16/100) -> 208710.38 | E16: =0.5*F16 -> 54674.667 | F16: 109349.33 | G16: =F16-D16 -> -99361.049 | H16: =0.5*I16 -> 185392 | I16: 370784 | J16: =I16-D16 -> 162073.62 | K16: 0.37756351 | L16: ='# and Assessed Value of Parcels'!G11/'# and Assessed Value of Parcels'!O11 -> 0.95851299 | M16: ='# and Assessed Value of Parcels'!H11/'# and Assessed Value of Parcels'!P11 -> 0.91282275 | N16: =(L16+M16)/2 -> 0.93566787 | O16: ='Tax Levies and EQ Tax Rates'!I11 -> 13099198 | P16: =N16*O16 -> 12256498 | Q16: 24497 | R16: =P16/Q16 -> 500.32651
A17: Burlington | B17: Pemberton Township | C17: =$B$5*R17 -> 856.6451 | D17: =C17/(K17/100) -> 84497.331 | E17: =0.5*F17 -> 46953.375 | F17: 93906.75 | G17: =F17-D17 -> 9409.4189 | H17: =0.5*I17 -> 83156 | I17: 166312 | J17: =I17-D17 -> 81814.669 | K17: 1.0138132 | L17: ='# and Assessed Value of Parcels'!G12/'# and Assessed Value of Parcels'!O12 -> 0.98128309 | M17: ='# and Assessed Value of Parcels'!H12/'# and Assessed Value of Parcels'!P12 -> 0.9332896 | N17: =(L17+M17)/2 -> 0.95728635 | O17: ='Tax Levies and EQ Tax Rates'!I12 -> 15285485 | P17: =N17*O17 -> 14632586 | Q17: 26903 | R17: =P17/Q17 -> 543.90165
A18: Burlington | B18: Southampton Township | C18: =$B$5*R18 -> 606.64587 | D18: =C18/(K18/100) -> 178815.74 | E18: =0.5*F18 -> 65732.525 | F18: 131465.05 | G18: =F18-D18 -> -47350.689 | H18: =0.5*I18 -> 119267 | I18: 238534 | J18: =I18-D18 -> 59718.261 | K18: 0.33925754 | L18: ='# and Assessed Value of Parcels'!G13/'# and Assessed Value of Parcels'!O13 -> 0.96051204 | M18: ='# and Assessed Value of Parcels'!H13/'# and Assessed Value of Parcels'!P13 -> 0.90183161 | N18: =(L18+M18)/2 -> 0.93117183 | O18: ='Tax Levies and EQ Tax Rates'!I13 -> 4267546.8 | P18: =N18*O18 -> 3973819.4 | Q18: 10317 | R18: =P18/Q18 -> 385.17198
A19: Cumberland | B19: Downe Township | C19: =$B$5*R19 -> 537.75318 | D19: =C19/(K19/100) -> 141282.2 | E19: =0.5*F19 -> 49310.171 | F19: 98620.342 | G19: =F19-D19 -> -42661.855 | H19: =0.5*I19 -> 59244.5 | I19: 118489 | J19: =I19-D19 -> -22793.197 | K19: 0.38062345 | L19: ='# and Assessed Value of Parcels'!G14/'# and Assessed Value of Parcels'!O14 -> 0.94935452 | M19: ='# and Assessed Value of Parcels'!H14/'# and Assessed Value of Parcels'!P14 -> 0.95309492 | N19: =(L19+M19)/2 -> 0.95122472 | O19: ='Tax Levies and EQ Tax Rates'!I14 -> 502154.1 | P19: =N19*O19 -> 477661.39 | Q19: 1399 | R19: =P19/Q19 -> 341.43059
A20: Cumberland | B20: Fairfield Township | C20: =$B$5*R20 -> 360.99801 | D20: =C20/(K20/100) -> 73853.745 | E20: =0.5*F20 -> 43528.829 | F20: 87057.657 | G20: =F20-D20 -> 13203.912 | H20: =0.5*I20 -> 71421.5 | I20: 142843 | J20: =I20-D20 -> 68989.255 | K20: 0.48880122 | L20: ='# and Assessed Value of Parcels'!G15/'# and Assessed Value of Parcels'!O15 -> 0.95576808 | M20: ='# and Assessed Value of Parcels'!H15/'# and Assessed Value of Parcels'!P15 -> 0.9003797 | N20: =(L20+M20)/2 -> 0.92807389 | O20: ='Tax Levies and EQ Tax Rates'!I15 -> 1369687.7 | P20: =N20*O20 -> 1271171.4 | Q20: 5546 | R20: =P20/Q20 -> 229.20508
A21: Cumberland | B21: Lawrence Township | C21: =$B$5*R21 -> 595.63622 | D21: =C21/(K21/100) -> 109243.37 | E21: =0.5*F21 -> 18042.5 | F21: 36085 | G21: =F21-D21 -> -73158.372 | H21: =0.5*I21 -> 82539 | I21: 165078 | J21: =I21-D21 -> 55834.628 | K21: 0.54523786 | L21: ='# and Assessed Value of Parcels'!G16/'# and Assessed Value of Parcels'!O16 -> 0.96660808 | M21: ='# and Assessed Value of Parcels'!H16/'# and Assessed Value of Parcels'!P16 -> 0.93631576 | N21: =(L21+M21)/2 -> 0.95146192 | O21: ='Tax Levies and EQ Tax Rates'!I16 -> 1227003.4 | P21: =N21*O21 -> 1167447 | Q21: 3087 | R21: =P21/Q21 -> 378.18173
A22: Essex | B22: Fairfield Township | C22: =$B$5*R22 -> 1956.5816 | D22: =C22/(K22/100) -> 450021.94 | E22: =0.5*F22 -> 109844.5 | F22: 219689 | G22: =F22-D22 -> -230332.94 | H22: =0.5*I22 -> 301609.22 | I22: 603218.44 | J22: =I22-D22 -> 153196.5 | K22: 0.43477472 | L22: ='[1]# and Assessed Value of Parcels'!G17/'[1]# and Assessed Value of Parcels'!O17 -> 0.78907204 | M22: ='[1]# and Assessed Value of Parcels'!H17/'[1]# and Assessed Value of Parcels'!P17 -> 0.44402102 | N22: =(L22+M22)/2 -> 0.61654653 | O22: ='[1]Tax Levies and EQ Tax Rates'!I17 -> 15861222 | P22: =N22*O22 -> 9779181.4 | Q22: 7872 | R22: =P22/Q22 -> 1242.2741
A23: Essex | B23: Newark City | C23: =$B$5*R23 -> 883.15755 | D23: =C23/(K23/100) -> 52462.396 | E23: =0.5*F23 -> 82264.833 | F23: 164529.67 | G23: =F23-D23 -> 112067.27 | H23: =0.5*I23 -> 103417.5 | I23: 206835 | J23: =I23-D23 -> 154372.6 | K23: 1.6834106 | L23: ='# and Assessed Value of Parcels'!G18/'# and Assessed Value of Parcels'!O18 -> 0.84162884 | M23: ='# and Assessed Value of Parcels'!H18/'# and Assessed Value of Parcels'!P18 -> 0.54365223 | N23: =(L23+M23)/2 -> 0.69264054 | O23: ='Tax Levies and EQ Tax Rates'!I18 -> 252218004 | P23: =N23*O23 -> 1.7469641e+08 | Q23: 311549 | R23: =P23/Q23 -> 560.73495
A24: Hunterdon | B24: Lebanon Township | C24: =$B$5*R24 -> 674.83856 | D24: =C24/(K24/100) -> 227723.18 | E24: =0.5*F24 -> 30345.75 | F24: 60691.5 | G24: =F24-D24 -> -167031.68 | H24: =0.5*I24 -> 189913.5 | I24: 379827 | J24: =I24-D24 -> 152103.82 | K24: 0.29634161 | L24: ='# and Assessed Value of Parcels'!G19/'# and Assessed Value of Parcels'!O19 -> 0.96383866 | M24: ='# and Assessed Value of Parcels'!H19/'# and Assessed Value of Parcels'!P19 -> 0.93906348 | N24: =(L24+M24)/2 -> 0.95145107 | O24: ='Tax Levies and EQ Tax Rates'!I19 -> 2789807.1 | P24: =N24*O24 -> 2654365 | Q24: 6195 | R24: =P24/Q24 -> 428.46893
A25: Middlesex | B25: East Brunswick Township | C25: =$B$5*R25 -> 1240.4096 | D25: =C25/(K25/100) -> 214472.1 | E25: =0.5*F25 -> 114092.92 | F25: 228185.83 | G25: =F25-D25 -> 13713.737 | H25: =0.5*I25 -> 190156 | I25: 380312 | J25: =I25-D25 -> 165839.9 | K25: 0.57835476 | L25: ='# and Assessed Value of Parcels'!G20/'# and Assessed Value of Parcels'!O20 -> 0.95667524 | M25: ='# and Assessed Value of Parcels'!H20/'# and Assessed Value of Parcels'!P20 -> 0.81220548 | N25: =(L25+M25)/2 -> 0.88444036 | O25: ='Tax Levies and EQ Tax Rates'!I20 -> 44269380 | P25: =N25*O25 -> 39153626 | Q25: 49715 | R25: =P25/Q25 -> 787.56163
A26: Middlesex | B26: Old Bridge Township | C26: =$B$5*R26 -> 827.79154 | D26: =C26/(K26/100) -> 187406.92 | E26: =0.5*F26 -> 65565.357 | F26: 131130.71 | G26: =F26-D26 -> -56276.209 | H26: =0.5*I26 -> 187762.5 | I26: 375525 | J26: =I26-D26 -> 188118.08 | K26: 0.44170809 | L26: ='# and Assessed Value of Parcels'!G21/'# and Assessed Value of Parcels'!O21 -> 0.97122792 | M26: ='# and Assessed Value of Parcels'!H21/'# and Assessed Value of Parcels'!P21 -> 0.88589383 | N26: =(L26+M26)/2 -> 0.92856088 | O26: ='Tax Levies and EQ Tax Rates'!I21 -> 37853002 | P26: =N26*O26 -> 35148817 | Q26: 66876 | R26: =P26/Q26 -> 525.58193
A27: Middlesex | B27: Middlesex Borough | C27: =$B$5*R27 -> 1308.2275 | D27: =C27/(K27/100) -> 161013.08 | E27: =0.5*F27 -> 153039.91 | F27: 306079.81 | G27: =F27-D27 -> 145066.73 | H27: =0.5*I27 -> 162441.5 | I27: 324883 | J27: =I27-D27 -> 163869.92 | K27: 0.81249766 | L27: ='# and Assessed Value of Parcels'!G22/'# and Assessed Value of Parcels'!O22 -> 0.92460317 | M27: ='# and Assessed Value of Parcels'!H22/'# and Assessed Value of Parcels'!P22 -> 0.82398227 | N27: =(L27+M27)/2 -> 0.87429272 | O27: ='Tax Levies and EQ Tax Rates'!I22 -> 13904913 | P27: =N27*O27 -> 12156964 | Q27: 14636 | R27: =P27/Q27 -> 830.62065
A28: Middlesex | B28: Sayreville Borough | C28: =$B$5*R28 -> 1119.3517 | D28: =C28/(K28/100) -> 165648.35 | E28: =0.5*F28 -> 104337.54 | F28: 208675.08 | G28: =F28-D28 -> 43026.726 | H28: =0.5*I28 -> 165477.5 | I28: 330955 | J28: =I28-D28 -> 165306.65 | K28: 0.67573971 | L28: ='# and Assessed Value of Parcels'!G23/'# and Assessed Value of Parcels'!O23 -> 0.96279666 | M28: ='# and Assessed Value of Parcels'!H23/'# and Assessed Value of Parcels'!P23 -> 0.85286918 | N28: =(L28+M28)/2 -> 0.90783292 | O28: ='Tax Levies and EQ Tax Rates'!I23 -> 35498458 | P28: =N28*O28 -> 32226669 | Q28: 45345 | R28: =P28/Q28 -> 710.69949
A29: Middlesex | B29: South River Borough | C29: =$B$5*R29 -> 961.40302 | D29: =C29/(K29/100) -> 136254.51 | E29: =0.5*F29 -> 81734.833 | F29: 163469.67 | G29: =F29-D29 -> 27215.154 | H29: =0.5*I29 -> 146735 | I29: 293470 | J29: =I29-D29 -> 157215.49 | K29: 0.70559352 | L29: ='# and Assessed Value of Parcels'!G24/'# and Assessed Value of Parcels'!O24 -> 0.95376862 | M29: ='# and Assessed Value of Parcels'!H24/'# and Assessed Value of Parcels'!P24 -> 0.87694473 | N29: =(L29+M29)/2 -> 0.91535668 | O29: ='Tax Levies and EQ Tax Rates'!I24 -> 10748447 | P29: =N29*O29 -> 9838662.7 | Q29: 16118 | R29: =P29/Q29 -> 610.41461
A30: Middlesex | B30: Woodbridge Township | C30: =$B$5*R30 -> 1322.8268 | D30: =C30/(K30/100) -> 160008.06 | E30: =0.5*F30 -> 116419.84 | F30: 232839.67 | G30: =F30-D30 -> 72831.613 | H30: =0.5*I30 -> 153810 | I30: 307620 | J30: =I30-D30 -> 147611.94 | K30: 0.82672514 | L30: ='# and Assessed Value of Parcels'!G25/'# and Assessed Value of Parcels'!O25 -> 0.95527754 | M30: ='# and Assessed Value of Parcels'!H25/'# and Assessed Value of Parcels'!P25 -> 0.7164271 | N30: =(L30+M30)/2 -> 0.83585232 | O30: ='Tax Levies and EQ Tax Rates'!I25 -> 1.0413965e+08 | P30: =N30*O30 -> 87045366 | Q30: 103639 | R30: =P30/Q30 -> 839.89006
A31: Monmouth | B31: Keansburg Borough | C31: =$B$5*R31 -> 1796.7719 | D31: =C31/(K31/100) -> 95892.661 | E31: =0.5*F31 -> 67359.375 | F31: 134718.75 | G31: =F31-D31 -> 38826.089 | H31: =0.5*I31 -> 91945.5 | I31: 183891 | J31: =I31-D31 -> 87998.339 | K31: 1.8737325 | L31: ='# and Assessed Value of Parcels'!G26/'# and Assessed Value of Parcels'!O26 -> 0.96441281 | M31: ='# and Assessed Value of Parcels'!H26/'# and Assessed Value of Parcels'!P26 -> 0.88303144 | N31: =(L31+M31)/2 -> 0.92372213 | O31: ='Tax Levies and EQ Tax Rates'!I26 -> 12047538 | P31: =N31*O31 -> 11128578 | Q31: 9755 | R31: =P31/Q31 -> 1140.8076
A32: Monmouth | B32: Manalapan Township | C32: =$B$5*R32 -> 910.28082 | D32: =C32/(K32/100) -> 272766.73 | E32: =0.5*F32 -> 146031.25 | F32: 292062.5 | G32: =F32-D32 -> 19295.769 | H32: =0.5*I32 -> 240243.5 | I32: 480487 | J32: =I32-D32 -> 207720.27 | K32: 0.33372135 | L32: ='# and Assessed Value of Parcels'!G27/'# and Assessed Value of Parcels'!O27 -> 0.97272104 | M32: ='# and Assessed Value of Parcels'!H27/'# and Assessed Value of Parcels'!P27 -> 0.9220575 | N32: =(L32+M32)/2 -> 0.94738927 | O32: ='Tax Levies and EQ Tax Rates'!I27 -> 24954149 | P32: =N32*O32 -> 23641293 | Q32: 40905 | R32: =P32/Q32 -> 577.95608
A33: Monmouth | B33: Ocean Township | C33: =$B$5*R33 -> 1196.7173 | D33: =C33/(K33/100) -> 295691.64 | E33: =0.5*F33 -> 449999.4 | F33: 899998.8 | G33: =F33-D33 -> 604307.16 | H33: =0.5*I33 -> 271006 | I33: 542012 | J33: =I33-D33 -> 246320.36 | K33: 0.404718 | L33: ='# and Assessed Value of Parcels'!G28/'# and Assessed Value of Parcels'!O28 -> 0.95530169 | M33: ='# and Assessed Value of Parcels'!H28/'# and Assessed Value of Parcels'!P28 -> 0.88451081 | N33: =(L33+M33)/2 -> 0.91990625 | O33: ='Tax Levies and EQ Tax Rates'!I28 -> 22856408 | P33: =N33*O33 -> 21025753 | Q33: 27672 | R33: =P33/Q33 -> 759.82049
A34: Monmouth | B34: Sea Bright Borough | C34: =$B$5*R34 -> 4445.7518 | D34: =C34/(K34/100) -> 865577.97 | E34: =0.5*F34 -> 719488 | F34: 1438976 | G34: =F34-D34 -> 573398.03 | H34: =0.5*I34 -> 348659 | I34: 697318 | J34: =I34-D34 -> -168259.97 | K34: 0.51361656 | L34: ='# and Assessed Value of Parcels'!G29/'# and Assessed Value of Parcels'!O29 -> 0.9358047 | M34: ='# and Assessed Value of Parcels'!H29/'# and Assessed Value of Parcels'!P29 -> 0.81959946 | N34: =(L34+M34)/2 -> 0.87770208 | O34: ='Tax Levies and EQ Tax Rates'!I29 -> 4660000 | P34: =N34*O34 -> 4090091.7 | Q34: 1449 | R34: =P34/Q34 -> 2822.6996
... A47: Warren | B47: Harmony Township | C47: =$B$5*R47 -> 710.17461 | D47: =C47/(K47/100) -> 247514.7 | E47: =0.5*F47 -> 57089.602 | F47: 114179.2 | G47: =F47-D47 -> -133335.5 | H47: =0.5*I47 -> 120092.5 | I47: 240185 | J47: =I47-D47 -> -7329.7042 | K47: 0.28692219 | L47: ='# and Assessed Value of Parcels'!G42/'# and Assessed Value of Parcels'!O42 -> 0.95134062 | M47: ='# and Assessed Value of Parcels'!H42/'# and Assessed Value of Parcels'!P42 -> 0.44542234 | N47: =(L47+M47)/2 -> 0.69838148 | O47: ='Tax Levies and EQ Tax Rates'!I42 -> 1616042.3 | P47: =N47*O47 -> 1128614 | Q47: 2503 | R47: =P47/Q47 -> 450.90451
C48: =AVERAGE(C10:C47) -> 1268.2238 | D48: =AVERAGE(D10:D47) -> 205578.12 | E48: =AVERAGE(E10:E47) -> 124266.77 | F48: =AVERAGE(F10:F47) -> 248533.53 | G48: =AVERAGE(G10:G47) -> 42955.41 | H48: =AVERAGE(H10:H47) -> 172507.68 | I48: =AVERAGE(I10:I47) -> 345015.35 | J48: =AVERAGE(J10:J47) -> 139437.23 | ... R48: =AVERAGE(R10:R47) -> 805.22145

Sheet Adjusted (1.5 Bed Multi) Muni B
A1: 2020 Municipal Break Even Analysis for Multifamily (Owned) (1.5 Bedroom) in Selected NJ Communities
A3: Multifamily (1.5 Bedroom) Multipliers
A4: Category | B4: Multiplier
A5: Household Size | B5: 1.575
A6: School Age Children | B6: 0.067
A8: Location | C8: 1.5 Bedroom Multifamily Municipal "Break Even Analysis" | F8: Fiscal Analysis | K8: Municipal Fiscal Impact Analysis
A9: County | B9: Municipality | C9: Municipal Tax Supported Cost | D9: Market Value "Break Even" | E9: Adjusted Average Real (2020) Market Value of Buyout Properties | F9: Average Real (2020) Market Value of Buyout Properties | G9: Fiscal Surplus or Deficit (Based on Average Buyout Market Value) | H9: Adjusted Average 2020 Residential Value in Buyout Community | I9: Average 2020 Residential Value in Buyout Community | J9: Fiscal Surplus or Deficit (Based on Average Residential Value) | K9: Municipal Equalized Property Tax Rate | L9: Percent of Total Parcels that are Residential | M9: Percent of Total Assessed Value that is Residential | N9: Average of Residential Parcels % and Assessed Value % | O9: Total Municipal Property Tax Levy | P9: Estimated Residential Share of Total Municipal Property Tax Levy | Q9: 2020 Municipal Population | R9: 2020 Municipal Property Tax Supported Cost Per Person
A10: Atlantic | B10: Pleasantville City | C10: =$B$5*R10 -> 1502.2555 | D10: =C10/(K10/100) -> 49030.197 | E10: =0.5*F10 -> 30117.5 | F10: 60235 | G10: =F10-D10 -> 11204.803 | H10: =0.5*I10 -> 49181.5 | I10: 98363 | J10: =I10-D10 -> 49332.803 | K10: 3.0639394 | L10: ='# and Assessed Value of Parcels'!G5/'# and Assessed Value of Parcels'!O5 -> 0.92172813 | M10: ='# and Assessed Value of Parcels'!H5/'# and Assessed Value of Parcels'!P5 -> 0.73101366 | N10: =(L10+M10)/2 -> 0.8263709 | O10: ='Tax Levies and EQ Tax Rates'!I5 -> 23810385 | P10: =N10*O10 -> 19676209 | Q10: 20629 | R10: =P10/Q10 -> 953.81304
A11: Bergen | B11: Hillsdale Borough | C11: =$B$5*R11 -> 1490.7657 | D11: =C11/(K11/100) -> 278024.11 | E11: =0.5*F11 -> 110944 | F11: 221888 | G11: =F11-D11 -> -56136.11 | H11: =0.5*I11 -> 262105 | I11: 524210 | J11: =I11-D11 -> 246185.89 | K11: 0.53620016 | L11: ='# and Assessed Value of Parcels'!G6/'# and Assessed Value of Parcels'!O6 -> 0.96785506 | M11: ='# and Assessed Value of Parcels'!H6/'# and Assessed Value of Parcels'!P6 -> 0.93507138 | N11: =(L11+M11)/2 -> 0.95146322 | O11: ='Tax Levies and EQ Tax Rates'!I6 -> 10090281 | P11: =N11*O11 -> 9600531.2 | Q11: 10143 | R11: =P11/Q11 -> 946.51792
A12: Bergen | B12: New Milford Borough | C12: =$B$5*R12 -> 1546.0274 | D12: =C12/(K12/100) -> 185247.23 | E12: =0.5*F12 -> 186862 | F12: 373724 | G12: =F12-D12 -> 188476.77 | H12: =0.5*I12 -> 213444 | I12: 426888 | J12: =I12-D12 -> 241640.77 | K12: 0.83457519 | L12: ='# and Assessed Value of Parcels'!G7/'# and Assessed Value of Parcels'!O7 -> 0.98144233 | M12: ='# and Assessed Value of Parcels'!H7/'# and Assessed Value of Parcels'!P7 -> 0.94433259 | N12: =(L12+M12)/2 -> 0.96288746 | O12: ='Tax Levies and EQ Tax Rates'!I7 -> 17251960 | P12: =N12*O12 -> 16611696 | Q12: 16923 | R12: =P12/Q12 -> 981.6047
A13: Bergen | B13: Oakland Borough | C13: =$B$5*R13 -> 1761.2188 | D13: =C13/(K13/100) -> 291944.66 | E13: =0.5*F13 -> 183086.5 | F13: 366173 | G13: =F13-D13 -> 74228.343 | H13: =0.5*I13 -> 249394.5 | I13: 498789 | J13: =I13-D13 -> 206844.34 | K13: 0.60327146 | L13: ='# and Assessed Value of Parcels'!G8/'# and Assessed Value of Parcels'!O8 -> 0.9566732 | M13: ='# and Assessed Value of Parcels'!H8/'# and Assessed Value of Parcels'!P8 -> 0.84635298 | N13: =(L13+M13)/2 -> 0.90151309 | O13: ='Tax Levies and EQ Tax Rates'!I8 -> 15812581 | P13: =N13*O13 -> 14255249 | Q13: 12748 | R13: =P13/Q13 -> 1118.2342
A14: Bergen | B14: Westwood Borough | C14: =$B$5*R14 -> 1834.0876 | D14: =C14/(K14/100) -> 249996.2 | E14: =0.5*F14 -> 234327.5 | F14: 468655 | G14: =F14-D14 -> 218658.8 | H14: =0.5*I14 -> 229733.5 | I14: 459467 | J14: =I14-D14 -> 209470.8 | K14: 0.73364618 | L14: ='# and Assessed Value of Parcels'!G9/'# and Assessed Value of Parcels'!O9 -> 0.91940211 | M14: ='# and Assessed Value of Parcels'!H9/'# and Assessed Value of Parcels'!P9 -> 0.75552222 | N14: =(L14+M14)/2 -> 0.83746217 | O14: ='Tax Levies and EQ Tax Rates'!I9 -> 15687741 | P14: =N14*O14 -> 13137890 | Q14: 11282 | R14: =P14/Q14 -> 1164.5
A15: Burlington | B15: Lumberton Township | C15: =$B$5*R15 -> 615.59801 | D15: =C15/(K15/100) -> 157779.43 | E15: =0.5*F15 -> 233196.08 | F15: 466392.16 | G15: =F15-D15 -> 308612.74 | H15: =0.5*I15 -> 153418 | I15: 306836 | J15: =I15-D15 -> 149056.57 | K15: 0.39016368 | L15: ='# and Assessed Value of Parcels'!G10/'# and Assessed Value of Parcels'!O10 -> 0.96040113 | M15: ='# and Assessed Value of Parcels'!H10/'# and Assessed Value of Parcels'!P10 -> 0.85301722 | N15: =(L15+M15)/2 -> 0.90670917 | O15: ='Tax Levies and EQ Tax Rates'!I10 -> 5518999.9 | P15: =N15*O15 -> 5004127.9 | Q15: 12803 | R15: =P15/Q15 -> 390.85588
A16: Burlington | B16: Medford Township | C16: =$B$5*R16 -> 788.01425 | D16: =C16/(K16/100) -> 208710.38 | E16: =0.5*F16 -> 54674.667 | F16: 109349.33 | G16: =F16-D16 -> -99361.049 | H16: =0.5*I16 -> 185392 | I16: 370784 | J16: =I16-D16 -> 162073.62 | K16: 0.37756351 | L16: ='# and Assessed Value of Parcels'!G11/'# and Assessed Value of Parcels'!O11 -> 0.95851299 | M16: ='# and Assessed Value of Parcels'!H11/'# and Assessed Value of Parcels'!P11 -> 0.91282275 | N16: =(L16+M16)/2 -> 0.93566787 | O16: ='Tax Levies and EQ Tax Rates'!I11 -> 13099198 | P16: =N16*O16 -> 12256498 | Q16: 24497 | R16: =P16/Q16 -> 500.32651
A17: Burlington | B17: Pemberton Township | C17: =$B$5*R17 -> 856.6451 | D17: =C17/(K17/100) -> 84497.331 | E17: =0.5*F17 -> 46953.375 | F17: 93906.75 | G17: =F17-D17 -> 9409.4189 | H17: =0.5*I17 -> 83156 | I17: 166312 | J17: =I17-D17 -> 81814.669 | K17: 1.0138132 | L17: ='# and Assessed Value of Parcels'!G12/'# and Assessed Value of Parcels'!O12 -> 0.98128309 | M17: ='# and Assessed Value of Parcels'!H12/'# and Assessed Value of Parcels'!P12 -> 0.9332896 | N17: =(L17+M17)/2 -> 0.95728635 | O17: ='Tax Levies and EQ Tax Rates'!I12 -> 15285485 | P17: =N17*O17 -> 14632586 | Q17: 26903 | R17: =P17/Q17 -> 543.90165
A18: Burlington | B18: Southampton Township | C18: =$B$5*R18 -> 606.64587 | D18: =C18/(K18/100) -> 178815.74 | E18: =0.5*F18 -> 65732.525 | F18: 131465.05 | G18: =F18-D18 -> -47350.689 | H18: =0.5*I18 -> 119267 | I18: 238534 | J18: =I18-D18 -> 59718.261 | K18: 0.33925754 | L18: ='# and Assessed Value of Parcels'!G13/'# and Assessed Value of Parcels'!O13 -> 0.96051204 | M18: ='# and Assessed Value of Parcels'!H13/'# and Assessed Value of Parcels'!P13 -> 0.90183161 | N18: =(L18+M18)/2 -> 0.93117183 | O18: ='Tax Levies and EQ Tax Rates'!I13 -> 4267546.8 | P18: =N18*O18 -> 3973819.4 | Q18: 10317 | R18: =P18/Q18 -> 385.17198
A19: Cumberland | B19: Downe Township | C19: =$B$5*R19 -> 537.75318 | D19: =C19/(K19/100) -> 141282.2 | E19: =0.5*F19 -> 49310.171 | F19: 98620.342 | G19: =F19-D19 -> -42661.855 | H19: =0.5*I19 -> 59244.5 | I19: 118489 | J19: =I19-D19 -> -22793.197 | K19: 0.38062345 | L19: ='# and Assessed Value of Parcels'!G14/'# and Assessed Value of Parcels'!O14 -> 0.94935452 | M19: ='# and Assessed Value of Parcels'!H14/'# and Assessed Value of Parcels'!P14 -> 0.95309492 | N19: =(L19+M19)/2 -> 0.95122472 | O19: ='Tax Levies and EQ Tax Rates'!I14 -> 502154.1 | P19: =N19*O19 -> 477661.39 | Q19: 1399 | R19: =P19/Q19 -> 341.43059
